Workbook

Sheet Results
A2: Hong Seh 10-year fleet replacement and charging
A4: Fill Fleet register, Replacement plan, then Energy and charging. Inputs are amber. Horizon is fixed at 120 months.
A6: =IF('Operating costs'!$B$61="Demonstration","DEMONSTRATION. Not a customer savings claim.","Customer entry. Verify quotes, operations and source records.") -> DEMONSTRATION. Not a customer savings claim.
A8: Metric | B8: Keep ICE, then new ICE | C8: All-new ICE now | D8: Plan A | E8: Plan B
A9: Truck count | B9: =COUNTIFS(Paths!$B$7:$B$406,0,Paths!$C$7:$C$406,1) -> 6 | C9: =COUNTIFS(Paths!$B$7:$B$406,1,Paths!$C$7:$C$406,1) -> 6 | D9: =COUNTIFS(Paths!$B$7:$B$406,2,Paths!$C$7:$C$406,1) -> 6 | E9: =COUNTIFS(Paths!$B$7:$B$406,3,Paths!$C$7:$C$406,1) -> 6
A10: EVs at month 0 | B10: =COUNTIFS(Paths!$B$7:$B$406,0,Paths!$C$7:$C$406,1,Paths!$D$7:$D$406,"EV",Paths!$E$7:$E$406,0) -> 0 | C10: =COUNTIFS(Paths!$B$7:$B$406,1,Paths!$C$7:$C$406,1,Paths!$D$7:$D$406,"EV",Paths!$E$7:$E$406,0) -> 0 | D10: =COUNTIFS(Paths!$B$7:$B$406,2,Paths!$C$7:$C$406,1,Paths!$D$7:$D$406,"EV",Paths!$E$7:$E$406,0) -> 1 | E10: =COUNTIFS(Paths!$B$7:$B$406,3,Paths!$C$7:$C$406,1,Paths!$D$7:$D$406,"EV",Paths!$E$7:$E$406,0) -> 3
A11: EVs at year 10 | B11: =COUNTIFS(Paths!$B$7:$B$406,0,Paths!$C$7:$C$406,1,Paths!$D$7:$D$406,"EV",Paths!$E$7:$E$406,"<120") -> 0 | C11: =COUNTIFS(Paths!$B$7:$B$406,1,Paths!$C$7:$C$406,1,Paths!$D$7:$D$406,"EV",Paths!$E$7:$E$406,"<120") -> 0 | D11: =COUNTIFS(Paths!$B$7:$B$406,2,Paths!$C$7:$C$406,1,Paths!$D$7:$D$406,"EV",Paths!$E$7:$E$406,"<120") -> 1 | E11: =COUNTIFS(Paths!$B$7:$B$406,3,Paths!$C$7:$C$406,1,Paths!$D$7:$D$406,"EV",Paths!$E$7:$E$406,"<120") -> 3
A12: Vehicle economic TCO | B12: =IF(AND(COUNTIFS(Paths!$B$7:$B$406,0,Paths!$C$7:$C$406,1,Paths!$P$7:$P$406,"<>Complete")=0,COUNTIFS(Paths!$B$7:$B$406,0,Paths!$C$7:$C$406,1)=SUM('Fleet register'!$B$7:$B$106)),SUMIFS('Annual build'!$N$7:$N$4406,'Annual build'!$B$7:$B$4406,0),"n.a.") -> 2081781 | C12: =IF(AND(COUNTIFS(Paths!$B$7:$B$406,1,Paths!$C$7:$C$406,1,Paths!$P$7:$P$406,"<>Complete")=0,COUNTIFS(Paths!$B$7:$B$406,1,Paths!$C$7:$C$406,1)=SUM('Fleet register'!$B$7:$B$106)),SUMIFS('Annual build'!$N$7:$N$4406,'Annual build'!$B$7:$B$4406,1),"n.a.") -> 2103081 | D12: =IF(AND(COUNTIFS(Paths!$B$7:$B$406,2,Paths!$C$7:$C$406,1,Paths!$P$7:$P$406,"<>Complete")=0,COUNTIFS(Paths!$B$7:$B$406,2,Paths!$C$7:$C$406,1)=SUM('Fleet register'!$B$7:$B$106)),SUMIFS('Annual build'!$N$7:$N$4406,'Annual build'!$B$7:$B$4406,2),"n.a.") -> 2046736 | E12: =IF(AND(COUNTIFS(Paths!$B$7:$B$406,3,Paths!$C$7:$C$406,1,Paths!$P$7:$P$406,"<>Complete")=0,COUNTIFS(Paths!$B$7:$B$406,3,Paths!$C$7:$C$406,1)=SUM('Fleet register'!$B$7:$B$106)),SUMIFS('Annual build'!$N$7:$N$4406,'Annual build'!$B$7:$B$4406,3),"n.a.") -> 1986546
A13: Net site ownership cost | B13: =0 -> 0 | C13: =0 -> 0 | D13: =IF(COUNT(F45:F55)=11,SUM(F45:F55),"n.a.") -> n.a. | E13: =IF(COUNT(G45:G55)=11,SUM(G45:G55),"n.a.") -> n.a.
A14: Total economic TCO | B14: =IF(AND(ISNUMBER(B12),ISNUMBER(B13)),SUM(B12:B13),"n.a.") -> 2081781 | C14: =IF(AND(ISNUMBER(C12),ISNUMBER(C13)),SUM(C12:C13),"n.a.") -> 2103081 | D14: =IF(AND(ISNUMBER(D12),ISNUMBER(D13)),SUM(D12:D13),"n.a.") -> n.a. | E14: =IF(AND(ISNUMBER(E12),ISNUMBER(E13)),SUM(E12:E13),"n.a.") -> n.a.
A15: Saving vs Keep ICE | B15: =IF(AND(ISNUMBER(B14),ISNUMBER(B14)),B14-B14,"n.a.") -> 0 | C15: =IF(AND(ISNUMBER(B14),ISNUMBER(C14)),B14-C14,"n.a.") -> -21300 | D15: =IF(AND(ISNUMBER(B14),ISNUMBER(D14)),B14-D14,"n.a.") -> n.a. | E15: =IF(AND(ISNUMBER(B14),ISNUMBER(E14)),B14-E14,"n.a.") -> n.a.
A16: Saving percentage | B16: =IF(AND(ISNUMBER(B15),ISNUMBER(B14),B14>0),B15/B14,"n.a.") -> 0 | C16: =IF(AND(ISNUMBER(C15),ISNUMBER(B14),B14>0),C15/B14,"n.a.") -> -0.010231624 | D16: =IF(AND(ISNUMBER(D15),ISNUMBER(B14),B14>0),D15/B14,"n.a.") -> n.a. | E16: =IF(AND(ISNUMBER(E15),ISNUMBER(B14),B14>0),E15/B14,"n.a.") -> n.a.
A17: 15% fleet saving headroom | B17: =IF(AND(ISNUMBER(B14),ISNUMBER(B14)),0.85*B14-B14,"n.a.") -> -312267.15 | C17: =IF(AND(ISNUMBER(B14),ISNUMBER(C14)),0.85*B14-C14,"n.a.") -> -333567.15 | D17: =IF(AND(ISNUMBER(B14),ISNUMBER(D14)),0.85*B14-D14,"n.a.") -> n.a. | E17: =IF(AND(ISNUMBER(B14),ISNUMBER(E14)),0.85*B14-E14,"n.a.") -> n.a.
A18: Cash less year-10 assets | B18: =IF(COUNT(B45:B55)=11,SUM(B45:B55),"n.a.") -> 1847781 | C18: =IF(COUNT(C45:C55)=11,SUM(C45:C55),"n.a.") -> 1869081 | D18: =IF(COUNT(D45:D55)=11,SUM(D45:D55),"n.a.") -> n.a. | E18: =IF(COUNT(E45:E55)=11,SUM(E45:E55),"n.a.") -> n.a.
A19: Day-0 funding before loans | B19: =IF(AND(AND(COUNTIFS(Paths!$B$7:$B$406,0,Paths!$C$7:$C$406,1,Paths!$P$7:$P$406,"<>Complete")=0,COUNTIFS(Paths!$B$7:$B$406,0,Paths!$C$7:$C$406,1)=SUM('Fleet register'!$B$7:$B$106)),ISNUMBER(B45)),SUMIFS('Annual build'!$R$7:$R$4406,'Annual build'!$B$7:$B$4406,0),"n.a.") -> 0 | C19: =IF(AND(AND(COUNTIFS(Paths!$B$7:$B$406,1,Paths!$C$7:$C$406,1,Paths!$P$7:$P$406,"<>Complete")=0,COUNTIFS(Paths!$B$7:$B$406,1,Paths!$C$7:$C$406,1)=SUM('Fleet register'!$B$7:$B$106)),ISNUMBER(C45)),SUMIFS('Annual build'!$R$7:$R$4406,'Annual build'!$B$7:$B$4406,1),"n.a.") -> 852000 | D19: =IF(AND(AND(COUNTIFS(Paths!$B$7:$B$406,2,Paths!$C$7:$C$406,1,Paths!$P$7:$P$406,"<>Complete")=0,COUNTIFS(Paths!$B$7:$B$406,2,Paths!$C$7:$C$406,1)=SUM('Fleet register'!$B$7:$B$106)),ISNUMBER(D45)),SUMIFS('Annual build'!$R$7:$R$4406,'Annual build'!$B$7:$B$4406,2)+H45,"n.a.") -> n.a. | E19: =IF(AND(AND(COUNTIFS(Paths!$B$7:$B$406,3,Paths!$C$7:$C$406,1,Paths!$P$7:$P$406,"<>Complete")=0,COUNTIFS(Paths!$B$7:$B$406,3,Paths!$C$7:$C$406,1)=SUM('Fleet register'!$B$7:$B$106)),ISNUMBER(E45)),SUMIFS('Annual build'!$R$7:$R$4406,'Annual build'!$B$7:$B$4406,3)+I45,"n.a.") -> n.a.
A20: Incremental day-0 funding | B20: =IF(AND(ISNUMBER(B19),ISNUMBER(B19)),B19-B19,"n.a.") -> 0 | C20: =IF(AND(ISNUMBER(C19),ISNUMBER(B19)),C19-B19,"n.a.") -> 852000 | D20: =IF(AND(ISNUMBER(D19),ISNUMBER(B19)),D19-B19,"n.a.") -> n.a. | E20: =IF(AND(ISNUMBER(E19),ISNUMBER(B19)),E19-B19,"n.a.") -> n.a.
A21: Cost per productive km | B21: =IF(AND(ISNUMBER(B14),SUMIFS('Annual build'!$S$7:$S$4406,'Annual build'!$B$7:$B$4406,0)>0),B14/SUMIFS('Annual build'!$S$7:$S$4406,'Annual build'!$B$7:$B$4406,0),"n.a.") -> 0.77103 | C21: =IF(AND(ISNUMBER(C14),SUMIFS('Annual build'!$S$7:$S$4406,'Annual build'!$B$7:$B$4406,1)>0),C14/SUMIFS('Annual build'!$S$7:$S$4406,'Annual build'!$B$7:$B$4406,1),"n.a.") -> 0.77891889 | D21: =IF(AND(ISNUMBER(D14),SUMIFS('Annual build'!$S$7:$S$4406,'Annual build'!$B$7:$B$4406,2)>0),D14/SUMIFS('Annual build'!$S$7:$S$4406,'Annual build'!$B$7:$B$4406,2),"n.a.") -> n.a. | E21: =IF(AND(ISNUMBER(E14),SUMIFS('Annual build'!$S$7:$S$4406,'Annual build'!$B$7:$B$4406,3)>0),E14/SUMIFS('Annual build'!$S$7:$S$4406,'Annual build'!$B$7:$B$4406,3),"n.a.") -> n.a.
A22: Site completeness / access | B22: ="Not applicable" -> Not applicable | C22: ="Not applicable" -> Not applicable | D22: ='Energy and charging'!$B$67 -> Missing site quote | E22: ='Energy and charging'!$C$67 -> Missing site quote
A23: Vehicle service / evidence | B23: =IF(NOT(AND(COUNTIFS(Paths!$B$7:$B$406,0,Paths!$C$7:$C$406,1,Paths!$P$7:$P$406,"<>Complete")=0,COUNTIFS(Paths!$B$7:$B$406,0,Paths!$C$7:$C$406,1)=SUM('Fleet register'!$B$7:$B$106))),"Missing/invalid vehicle inputs",IF(COUNTIFS(Paths!$B$7:$B$406,0,Paths!$C$7:$C$406,1,Paths!$Q$7:$Q$406,"Fails entered limits")>0,"Fails entered limits",IF(COUNTIFS(Paths!$B$7:$B$406,0,Paths!$C$7:$C$406,1,Paths!$Q$7:$Q$406,"Unverified")>0,"Vehicle evidence open","Within entered limits"))) -> Within entered limits | C23: =IF(NOT(AND(COUNTIFS(Paths!$B$7:$B$406,1,Paths!$C$7:$C$406,1,Paths!$P$7:$P$406,"<>Complete")=0,COUNTIFS(Paths!$B$7:$B$406,1,Paths!$C$7:$C$406,1)=SUM('Fleet register'!$B$7:$B$106))),"Missing/invalid vehicle inputs",IF(COUNTIFS(Paths!$B$7:$B$406,1,Paths!$C$7:$C$406,1,Paths!$Q$7:$Q$406,"Fails entered limits")>0,"Fails entered limits",IF(COUNTIFS(Paths!$B$7:$B$406,1,Paths!$C$7:$C$406,1,Paths!$Q$7:$Q$406,"Unverified")>0,"Vehicle evidence open","Within entered limits"))) -> Within entered limits | D23: =IF(NOT(AND(COUNTIFS(Paths!$B$7:$B$406,2,Paths!$C$7:$C$406,1,Paths!$P$7:$P$406,"<>Complete")=0,COUNTIFS(Paths!$B$7:$B$406,2,Paths!$C$7:$C$406,1)=SUM('Fleet register'!$B$7:$B$106))),"Missing/invalid vehicle inputs",IF(COUNTIFS(Paths!$B$7:$B$406,2,Paths!$C$7:$C$406,1,Paths!$Q$7:$Q$406,"Fails entered limits")>0,"Fails entered limits",IF(COUNTIFS(Paths!$B$7:$B$406,2,Paths!$C$7:$C$406,1,Paths!$Q$7:$Q$406,"Unverified")>0,"Vehicle evidence open","Within entered limits"))) -> Fails entered limits | E23: =IF(NOT(AND(COUNTIFS(Paths!$B$7:$B$406,3,Paths!$C$7:$C$406,1,Paths!$P$7:$P$406,"<>Complete")=0,COUNTIFS(Paths!$B$7:$B$406,3,Paths!$C$7:$C$406,1)=SUM('Fleet register'!$B$7:$B$106))),"Missing/invalid vehicle inputs",IF(COUNTIFS(Paths!$B$7:$B$406,3,Paths!$C$7:$C$406,1,Paths!$Q$7:$Q$406,"Fails entered limits")>0,"Fails entered limits",IF(COUNTIFS(Paths!$B$7:$B$406,3,Paths!$C$7:$C$406,1,Paths!$Q$7:$Q$406,"Unverified")>0,"Vehicle evidence open","Within entered limits"))) -> Fails entered limits
A24: Saving claim status | B24: =IF(NOT(ISNUMBER(B14)),"Total incomplete",IF(OR(B9<=0,NOT(ISNUMBER(B16)),B23<>"Within entered limits",AND(0>=2,B11>0,NOT(OR(B22="Within entered site limits",B22="Public access entered"))),'Operating costs'!$B$61<>"Customer",'Operating costs'!$B$60<>"Yes",COUNTIFS('Fleet register'!$B$7:$B$106,1,'Fleet register'!$Q$7:$Q$106,"")>0,COUNTIFS(Paths!$B$7:$B$406,0,Paths!$C$7:$C$406,1,Paths!$AN$7:$AN$406,"<>Verified")>0),"Diagnostic only",IF(B16>=0.15,"Meets entered 15% target","Below entered 15% target"))) -> Diagnostic only | C24: =IF(NOT(ISNUMBER(C14)),"Total incomplete",IF(OR(C9<=0,NOT(ISNUMBER(C16)),C23<>"Within entered limits",AND(1>=2,C11>0,NOT(OR(C22="Within entered site limits",C22="Public access entered"))),'Operating costs'!$B$61<>"Customer",'Operating costs'!$B$60<>"Yes",COUNTIFS('Fleet register'!$B$7:$B$106,1,'Fleet register'!$Q$7:$Q$106,"")>0,COUNTIFS(Paths!$B$7:$B$406,1,Paths!$C$7:$C$406,1,Paths!$AN$7:$AN$406,"<>Verified")>0),"Diagnostic only",IF(C16>=0.15,"Meets entered 15% target","Below entered 15% target"))) -> Diagnostic only | D24: =IF(NOT(ISNUMBER(D14)),"Total incomplete",IF(OR(D9<=0,NOT(ISNUMBER(D16)),D23<>"Within entered limits",AND(2>=2,D11>0,NOT(OR(D22="Within entered site limits",D22="Public access entered"))),'Operating costs'!$B$61<>"Customer",'Operating costs'!$B$60<>"Yes",COUNTIFS('Fleet register'!$B$7:$B$106,1,'Fleet register'!$Q$7:$Q$106,"")>0,COUNTIFS(Paths!$B$7:$B$406,2,Paths!$C$7:$C$406,1,Paths!$AN$7:$AN$406,"<>Verified")>0),"Diagnostic only",IF(D16>=0.15,"Meets entered 15% target","Below entered 15% target"))) -> Total incomplete | E24: =IF(NOT(ISNUMBER(E14)),"Total incomplete",IF(OR(E9<=0,NOT(ISNUMBER(E16)),E23<>"Within entered limits",AND(3>=2,E11>0,NOT(OR(E22="Within entered site limits",E22="Public access entered"))),'Operating costs'!$B$61<>"Customer",'Operating costs'!$B$60<>"Yes",COUNTIFS('Fleet register'!$B$7:$B$106,1,'Fleet register'!$Q$7:$Q$106,"")>0,COUNTIFS(Paths!$B$7:$B$406,3,Paths!$C$7:$C$406,1,Paths!$AN$7:$AN$406,"<>Verified")>0),"Diagnostic only",IF(E16>=0.15,"Meets entered 15% target","Below entered 15% target"))) -> Total incomplete
A26: Max site TCO for 15% fleet saving | D26: =IF(AND(ISNUMBER(B14),ISNUMBER(D12)),0.85*B14-D12,"n.a.") -> -277222.17 | E26: =IF(AND(ISNUMBER(B14),ISNUMBER(E12)),0.85*B14-E12,"n.a.") -> -217032.2
A27: Commercial versus public rates (tariff-only, Plan A year-1 volume)
A28: Energy | B28: 100% commercial | C28: 100% public | D28: Entered blend
A29: ICE energy/year | B29: =SUMIFS(Paths!$AA$7:$AA$406,Paths!$B$7:$B$406,2,Paths!$C$7:$C$406,1)*'Energy and charging'!$B$7 -> 54273.6 | C29: =SUMIFS(Paths!$AA$7:$AA$406,Paths!$B$7:$B$406,2,Paths!$C$7:$C$406,1)*'Energy and charging'!$B$8 -> 81410.4 | D29: =SUMIFS(Paths!$AA$7:$AA$406,Paths!$B$7:$B$406,2,Paths!$C$7:$C$406,1)*('Energy and charging'!$B$9*'Energy and charging'!$B$7+(1-'Energy and charging'!$B$9)*'Energy and charging'!$B$8) -> 54273.6
A30: EV energy/year | B30: =SUMIFS(Paths!$X$7:$X$406,Paths!$B$7:$B$406,2,Paths!$C$7:$C$406,1,Paths!$D$7:$D$406,"EV")*'Energy and charging'!$B$10 -> 4741.8465 | C30: =SUMIFS(Paths!$X$7:$X$406,Paths!$B$7:$B$406,2,Paths!$C$7:$C$406,1,Paths!$D$7:$D$406,"EV")*'Energy and charging'!$B$11 -> 11588.757 | D30: =SUMIFS(Paths!$X$7:$X$406,Paths!$B$7:$B$406,2,Paths!$C$7:$C$406,1,Paths!$D$7:$D$406,"EV")*((1-'Energy and charging'!$B$12)*'Energy and charging'!$B$10+'Energy and charging'!$B$12*'Energy and charging'!$B$11) -> 6111.2286
A32: Tariff-only holds volumes fixed. Full plans change public-share detours, queues, paid time and installation costs.
A34: Additional day-0 budget | B34: ='Operating costs'!$B$55 -> 250000
A35: Budget headroom A / B | D35: =IF(ISNUMBER(D20),'Operating costs'!$B$55-MAX(0,D20),"n.a.") -> n.a. | E35: =IF(ISNUMBER(E20),'Operating costs'!$B$55-MAX(0,E20),"n.a.") -> n.a.
A37: To compare 1 EV with 1 ICE: include only that truck, or inspect vehicle-only cost and quote a standalone charging plan.
A39: No confirmed installation total yet. Equipment prices and site-rent schedules are benchmarks, not complete projects.
A41: Cash excludes financing. Refundable deposits affect cash, not full economic cost. Future residual values are forecasts.
A42: EV servicing uses the selected model's Hong Seh 200,000 km average unless Annual override is selected. The average smooths service timing.
A44: Year | B44: Keep ICE cash less assets | C44: New ICE cash less assets | D44: Plan A cash less assets | E44: Plan B cash less assets | F44: A site economic | G44: B site economic | H44: A site cash | I44: B site cash
A45: 0 | B45: =IF(AND(COUNTIFS(Paths!$B$7:$B$406,0,Paths!$C$7:$C$406,1,Paths!$P$7:$P$406,"<>Complete")=0,COUNTIFS(Paths!$B$7:$B$406,0,Paths!$C$7:$C$406,1)=SUM('Fleet register'!$B$7:$B$106)),SUMIFS('Annual build'!$O$7:$O$4406,'Annual build'!$B$7:$B$4406,0,'Annual build'!$C$7:$C$4406,$A45),"n.a.") -> 0 | C45: =IF(AND(COUNTIFS(Paths!$B$7:$B$406,1,Paths!$C$7:$C$406,1,Paths!$P$7:$P$406,"<>Complete")=0,COUNTIFS(Paths!$B$7:$B$406,1,Paths!$C$7:$C$406,1)=SUM('Fleet register'!$B$7:$B$106)),SUMIFS('Annual build'!$O$7:$O$4406,'Annual build'!$B$7:$B$4406,1,'Annual build'!$C$7:$C$4406,$A45),"n.a.") -> 852000 | D45: =IF(AND(COUNTIFS(Paths!$B$7:$B$406,2,Paths!$C$7:$C$406,1,Paths!$P$7:$P$406,"<>Complete")=0,COUNTIFS(Paths!$B$7:$B$406,2,Paths!$C$7:$C$406,1)=SUM('Fleet register'!$B$7:$B$106)),IF(ISNUMBER(H45),SUMIFS('Annual build'!$O$7:$O$4406,'Annual build'!$B$7:$B$4406,2,'Annual build'!$C$7:$C$4406,$A45)+H45,"n.a."),"n.a.") -> n.a. | E45: =IF(AND(COUNTIFS(Paths!$B$7:$B$406,3,Paths!$C$7:$C$406,1,Paths!$P$7:$P$406,"<>Complete")=0,COUNTIFS(Paths!$B$7:$B$406,3,Paths!$C$7:$C$406,1)=SUM('Fleet register'!$B$7:$B$106)),IF(ISNUMBER(I45),SUMIFS('Annual build'!$O$7:$O$4406,'Annual build'!$B$7:$B$4406,3,'Annual build'!$C$7:$C$4406,$A45)+I45,"n.a."),"n.a.") -> n.a. | F45: =IF('Energy and charging'!$B$60="No EV site",0,IF('Energy and charging'!$B$60="Public only",IF(IF('Energy and charging'!$B$33=0,$A45=0,AND($A45>0,'Energy and charging'!$B$33>($A45-1)*12,'Energy and charging'!$B$33<=$A45*12)),'Energy and charging'!$B$27,0)+0/12*'Energy and charging'!$B$29*(1+'Operating costs'!$B$53)^MAX(0,$A45-1),IF('Energy and charging'!$B$60="Complete",IF(IF('Energy and charging'!$B$33=0,$A45=0,AND($A45>0,'Energy and charging'!$B$33>($A45-1)*12,'Energy and charging'!$B$33<=$A45*12)),'Energy and charging'!$B$61,0)+0/12*'Energy and charging'!$B$62*(1+'Operating costs'!$B$53)^MAX(0,$A45-1)-IF(IF('Energy and charging'!$B$45=0,$A45=0,AND($A45>0,'Energy and charging'!$B$45>($A45-1)*12,'Energy and charging'!$B$45<=$A45*12)),'Energy and charging'!$B$44,0)+IF(IF('Energy and charging'!$B$38=0,$A45=0,AND($A45>0,'Energy and charging'!$B$38>($A45-1)*12,'Energy and charging'!$B$38<=$A45*12)),'Energy and charging'!$B$37,0)+IF(IF('Energy and charging'!$B$41=0,$A45=0,AND($A45>0,'Energy and charging'!$B$41>($A45-1)*12,'Energy and charging'!$B$41<=$A45*12)),'Energy and charging'!$B$16*'Energy and charging'!$B$40,0)+IF(IF('Energy and charging'!$B$33+'Energy and charging'!$B$34=0,$A45=0,AND($A45>0,'Energy and charging'!$B$33+'Energy and charging'!$B$34>($A45-1)*12,'Energy and charging'!$B$33+'Energy and charging'!$B$34<=$A45*12)),'Energy and charging'!$B$36,0)-IF($A45=10,'Energy and charging'!$B$35,0),"n.a."))) -> n.a. | G45: =IF('Energy and charging'!$C$60="No EV site",0,IF('Energy and charging'!$C$60="Public only",IF(IF('Energy and charging'!$C$33=0,$A45=0,AND($A45>0,'Energy and charging'!$C$33>($A45-1)*12,'Energy and charging'!$C$33<=$A45*12)),'Energy and charging'!$C$27,0)+0/12*'Energy and charging'!$C$29*(1+'Operating costs'!$B$53)^MAX(0,$A45-1),IF('Energy and charging'!$C$60="Complete",IF(IF('Energy and charging'!$C$33=0,$A45=0,AND($A45>0,'Energy and charging'!$C$33>($A45-1)*12,'Energy and charging'!$C$33<=$A45*12)),'Energy and charging'!$C$61,0)+0/12*'Energy and charging'!$C$62*(1+'Operating costs'!$B$53)^MAX(0,$A45-1)-IF(IF('Energy and charging'!$C$45=0,$A45=0,AND($A45>0,'Energy and charging'!$C$45>($A45-1)*12,'Energy and charging'!$C$45<=$A45*12)),'Energy and charging'!$C$44,0)+IF(IF('Energy and charging'!$C$38=0,$A45=0,AND($A45>0,'Energy and charging'!$C$38>($A45-1)*12,'Energy and charging'!$C$38<=$A45*12)),'Energy and charging'!$C$37,0)+IF(IF('Energy and charging'!$C$41=0,$A45=0,AND($A45>0,'Energy and charging'!$C$41>($A45-1)*12,'Energy and charging'!$C$41<=$A45*12)),'Energy and charging'!$C$16*'Energy and charging'!$C$40,0)+IF(IF('Energy and charging'!$C$33+'Energy and charging'!$C$34=0,$A45=0,AND($A45>0,'Energy and charging'!$C$33+'Energy and charging'!$C$34>($A45-1)*12,'Energy and charging'!$C$33+'Energy and charging'!$C$34<=$A45*12)),'Energy and charging'!$C$36,0)-IF($A45=10,'Energy and charging'!$C$35,0),"n.a."))) -> n.a. | H45: =IF(ISNUMBER(F45),F45+IF(AND('Energy and charging'!$B$60="Complete",IF('Energy and charging'!$B$33=0,$A45=0,AND($A45>0,'Energy and charging'!$B$33>($A45-1)*12,'Energy and charging'!$B$33<=$A45*12))),'Energy and charging'!$B$42,0)-IF(AND('Energy and charging'!$B$60="Complete",IF('Energy and charging'!$B$43=0,$A45=0,AND($A45>0,'Energy and charging'!$B$43>($A45-1)*12,'Energy and charging'!$B$43<=$A45*12))),'Energy and charging'!$B$42,0),"n.a.") -> n.a. | I45: =IF(ISNUMBER(G45),G45+IF(AND('Energy and charging'!$C$60="Complete",IF('Energy and charging'!$C$33=0,$A45=0,AND($A45>0,'Energy and charging'!$C$33>($A45-1)*12,'Energy and charging'!$C$33<=$A45*12))),'Energy and charging'!$C$42,0)-IF(AND('Energy and charging'!$C$60="Complete",IF('Energy and charging'!$C$43=0,$A45=0,AND($A45>0,'Energy and charging'!$C$43>($A45-1)*12,'Energy and charging'!$C$43<=$A45*12))),'Energy and charging'!$C$42,0),"n.a.") -> n.a.
A46: 1 | B46: =IF(AND(COUNTIFS(Paths!$B$7:$B$406,0,Paths!$C$7:$C$406,1,Paths!$P$7:$P$406,"<>Complete")=0,COUNTIFS(Paths!$B$7:$B$406,0,Paths!$C$7:$C$406,1)=SUM('Fleet register'!$B$7:$B$106)),SUMIFS('Annual build'!$O$7:$O$4406,'Annual build'!$B$7:$B$4406,0,'Annual build'!$C$7:$C$4406,$A46),"n.a.") -> 279908.1 | C46: =IF(AND(COUNTIFS(Paths!$B$7:$B$406,1,Paths!$C$7:$C$406,1,Paths!$P$7:$P$406,"<>Complete")=0,COUNTIFS(Paths!$B$7:$B$406,1,Paths!$C$7:$C$406,1)=SUM('Fleet register'!$B$7:$B$106)),SUMIFS('Annual build'!$O$7:$O$4406,'Annual build'!$B$7:$B$4406,1,'Annual build'!$C$7:$C$4406,$A46),"n.a.") -> 108908.1 | D46: =IF(AND(COUNTIFS(Paths!$B$7:$B$406,2,Paths!$C$7:$C$406,1,Paths!$P$7:$P$406,"<>Complete")=0,COUNTIFS(Paths!$B$7:$B$406,2,Paths!$C$7:$C$406,1)=SUM('Fleet register'!$B$7:$B$106)),IF(ISNUMBER(H46),SUMIFS('Annual build'!$O$7:$O$4406,'Annual build'!$B$7:$B$4406,2,'Annual build'!$C$7:$C$4406,$A46)+H46,"n.a."),"n.a.") -> n.a. | E46: =IF(AND(COUNTIFS(Paths!$B$7:$B$406,3,Paths!$C$7:$C$406,1,Paths!$P$7:$P$406,"<>Complete")=0,COUNTIFS(Paths!$B$7:$B$406,3,Paths!$C$7:$C$406,1)=SUM('Fleet register'!$B$7:$B$106)),IF(ISNUMBER(I46),SUMIFS('Annual build'!$O$7:$O$4406,'Annual build'!$B$7:$B$4406,3,'Annual build'!$C$7:$C$4406,$A46)+I46,"n.a."),"n.a.") -> n.a. | F46: =IF('Energy and charging'!$B$60="No EV site",0,IF('Energy and charging'!$B$60="Public only",IF(IF('Energy and charging'!$B$33=0,$A46=0,AND($A46>0,'Energy and charging'!$B$33>($A46-1)*12,'Energy and charging'!$B$33<=$A46*12)),'Energy and charging'!$B$27,0)+MAX(0,MIN(1*12,120)-MAX(0,'Energy and charging'!$B$33))/12*'Energy and charging'!$B$29*(1+'Operating costs'!$B$53)^MAX(0,$A46-1),IF('Energy and charging'!$B$60="Complete",IF(IF('Energy and charging'!$B$33=0,$A46=0,AND($A46>0,'Energy and charging'!$B$33>($A46-1)*12,'Energy and charging'!$B$33<=$A46*12)),'Energy and charging'!$B$61,0)+MAX(0,MIN(1*12,120)-MAX(0,'Energy and charging'!$B$33))/12*'Energy and charging'!$B$62*(1+'Operating costs'!$B$53)^MAX(0,$A46-1)-IF(IF('Energy and charging'!$B$45=0,$A46=0,AND($A46>0,'Energy and charging'!$B$45>($A46-1)*12,'Energy and charging'!$B$45<=$A46*12)),'Energy and charging'!$B$44,0)+IF(IF('Energy and charging'!$B$38=0,$A46=0,AND($A46>0,'Energy and charging'!$B$38>($A46-1)*12,'Energy and charging'!$B$38<=$A46*12)),'Energy and charging'!$B$37,0)+IF(IF('Energy and charging'!$B$41=0,$A46=0,AND($A46>0,'Energy and charging'!$B$41>($A46-1)*12,'Energy and charging'!$B$41<=$A46*12)),'Energy and charging'!$B$16*'Energy and charging'!$B$40,0)+IF(IF('Energy and charging'!$B$33+'Energy and charging'!$B$34=0,$A46=0,AND($A46>0,'Energy and charging'!$B$33+'Energy and charging'!$B$34>($A46-1)*12,'Energy and charging'!$B$33+'Energy and charging'!$B$34<=$A46*12)),'Energy and charging'!$B$36,0)-IF($A46=10,'Energy and charging'!$B$35,0),"n.a."))) -> n.a. | G46: =IF('Energy and charging'!$C$60="No EV site",0,IF('Energy and charging'!$C$60="Public only",IF(IF('Energy and charging'!$C$33=0,$A46=0,AND($A46>0,'Energy and charging'!$C$33>($A46-1)*12,'Energy and charging'!$C$33<=$A46*12)),'Energy and charging'!$C$27,0)+MAX(0,MIN(1*12,120)-MAX(0,'Energy and charging'!$C$33))/12*'Energy and charging'!$C$29*(1+'Operating costs'!$B$53)^MAX(0,$A46-1),IF('Energy and charging'!$C$60="Complete",IF(IF('Energy and charging'!$C$33=0,$A46=0,AND($A46>0,'Energy and charging'!$C$33>($A46-1)*12,'Energy and charging'!$C$33<=$A46*12)),'Energy and charging'!$C$61,0)+MAX(0,MIN(1*12,120)-MAX(0,'Energy and charging'!$C$33))/12*'Energy and charging'!$C$62*(1+'Operating costs'!$B$53)^MAX(0,$A46-1)-IF(IF('Energy and charging'!$C$45=0,$A46=0,AND($A46>0,'Energy and charging'!$C$45>($A46-1)*12,'Energy and charging'!$C$45<=$A46*12)),'Energy and charging'!$C$44,0)+IF(IF('Energy and charging'!$C$38=0,$A46=0,AND($A46>0,'Energy and charging'!$C$38>($A46-1)*12,'Energy and charging'!$C$38<=$A46*12)),'Energy and charging'!$C$37,0)+IF(IF('Energy and charging'!$C$41=0,$A46=0,AND($A46>0,'Energy and charging'!$C$41>($A46-1)*12,'Energy and charging'!$C$41<=$A46*12)),'Energy and charging'!$C$16*'Energy and charging'!$C$40,0)+IF(IF('Energy and charging'!$C$33+'Energy and charging'!$C$34=0,$A46=0,AND($A46>0,'Energy and charging'!$C$33+'Energy and charging'!$C$34>($A46-1)*12,'Energy and charging'!$C$33+'Energy and charging'!$C$34<=$A46*12)),'Energy and charging'!$C$36,0)-IF($A46=10,'Energy and charging'!$C$35,0),"n.a."))) -> n.a. | H46: =IF(ISNUMBER(F46),F46+IF(AND('Energy and charging'!$B$60="Complete",IF('Energy and charging'!$B$33=0,$A46=0,AND($A46>0,'Energy and charging'!$B$33>($A46-1)*12,'Energy and charging'!$B$33<=$A46*12))),'Energy and charging'!$B$42,0)-IF(AND('Energy and charging'!$B$60="Complete",IF('Energy and charging'!$B$43=0,$A46=0,AND($A46>0,'Energy and charging'!$B$43>($A46-1)*12,'Energy and charging'!$B$43<=$A46*12))),'Energy and charging'!$B$42,0),"n.a.") -> n.a. | I46: =IF(ISNUMBER(G46),G46+IF(AND('Energy and charging'!$C$60="Complete",IF('Energy and charging'!$C$33=0,$A46=0,AND($A46>0,'Energy and charging'!$C$33>($A46-1)*12,'Energy and charging'!$C$33<=$A46*12))),'Energy and charging'!$C$42,0)-IF(AND('Energy and charging'!$C$60="Complete",IF('Energy and charging'!$C$43=0,$A46=0,AND($A46>0,'Energy and charging'!$C$43>($A46-1)*12,'Energy and charging'!$C$43<=$A46*12))),'Energy and charging'!$C$42,0),"n.a.") -> n.a.
A47: 2 | B47: =IF(AND(COUNTIFS(Paths!$B$7:$B$406,0,Paths!$C$7:$C$406,1,Paths!$P$7:$P$406,"<>Complete")=0,COUNTIFS(Paths!$B$7:$B$406,0,Paths!$C$7:$C$406,1)=SUM('Fleet register'!$B$7:$B$106)),SUMIFS('Annual build'!$O$7:$O$4406,'Annual build'!$B$7:$B$4406,0,'Annual build'!$C$7:$C$4406,$A47),"n.a.") -> 279908.1 | C47: =IF(AND(COUNTIFS(Paths!$B$7:$B$406,1,Paths!$C$7:$C$406,1,Paths!$P$7:$P$406,"<>Complete")=0,COUNTIFS(Paths!$B$7:$B$406,1,Paths!$C$7:$C$406,1)=SUM('Fleet register'!$B$7:$B$106)),SUMIFS('Annual build'!$O$7:$O$4406,'Annual build'!$B$7:$B$4406,1,'Annual build'!$C$7:$C$4406,$A47),"n.a.") -> 108908.1 | D47: =IF(AND(COUNTIFS(Paths!$B$7:$B$406,2,Paths!$C$7:$C$406,1,Paths!$P$7:$P$406,"<>Complete")=0,COUNTIFS(Paths!$B$7:$B$406,2,Paths!$C$7:$C$406,1)=SUM('Fleet register'!$B$7:$B$106)),IF(ISNUMBER(H47),SUMIFS('Annual build'!$O$7:$O$4406,'Annual build'!$B$7:$B$4406,2,'Annual build'!$C$7:$C$4406,$A47)+H47,"n.a."),"n.a.") -> n.a. | E47: =IF(AND(COUNTIFS(Paths!$B$7:$B$406,3,Paths!$C$7:$C$406,1,Paths!$P$7:$P$406,"<>Complete")=0,COUNTIFS(Paths!$B$7:$B$406,3,Paths!$C$7:$C$406,1)=SUM('Fleet register'!$B$7:$B$106)),IF(ISNUMBER(I47),SUMIFS('Annual build'!$O$7:$O$4406,'Annual build'!$B$7:$B$4406,3,'Annual build'!$C$7:$C$4406,$A47)+I47,"n.a."),"n.a.") -> n.a. | F47: =IF('Energy and charging'!$B$60="No EV site",0,IF('Energy and charging'!$B$60="Public only",IF(IF('Energy and charging'!$B$33=0,$A47=0,AND($A47>0,'Energy and charging'!$B$33>($A47-1)*12,'Energy and charging'!$B$33<=$A47*12)),'Energy and charging'!$B$27,0)+MAX(0,MIN(2*12,120)-MAX(12,'Energy and charging'!$B$33))/12*'Energy and charging'!$B$29*(1+'Operating costs'!$B$53)^MAX(0,$A47-1),IF('Energy and charging'!$B$60="Complete",IF(IF('Energy and charging'!$B$33=0,$A47=0,AND($A47>0,'Energy and charging'!$B$33>($A47-1)*12,'Energy and charging'!$B$33<=$A47*12)),'Energy and charging'!$B$61,0)+MAX(0,MIN(2*12,120)-MAX(12,'Energy and charging'!$B$33))/12*'Energy and charging'!$B$62*(1+'Operating costs'!$B$53)^MAX(0,$A47-1)-IF(IF('Energy and charging'!$B$45=0,$A47=0,AND($A47>0,'Energy and charging'!$B$45>($A47-1)*12,'Energy and charging'!$B$45<=$A47*12)),'Energy and charging'!$B$44,0)+IF(IF('Energy and charging'!$B$38=0,$A47=0,AND($A47>0,'Energy and charging'!$B$38>($A47-1)*12,'Energy and charging'!$B$38<=$A47*12)),'Energy and charging'!$B$37,0)+IF(IF('Energy and charging'!$B$41=0,$A47=0,AND($A47>0,'Energy and charging'!$B$41>($A47-1)*12,'Energy and charging'!$B$41<=$A47*12)),'Energy and charging'!$B$16*'Energy and charging'!$B$40,0)+IF(IF('Energy and charging'!$B$33+'Energy and charging'!$B$34=0,$A47=0,AND($A47>0,'Energy and charging'!$B$33+'Energy and charging'!$B$34>($A47-1)*12,'Energy and charging'!$B$33+'Energy and charging'!$B$34<=$A47*12)),'Energy and charging'!$B$36,0)-IF($A47=10,'Energy and charging'!$B$35,0),"n.a."))) -> n.a. | G47: =IF('Energy and charging'!$C$60="No EV site",0,IF('Energy and charging'!$C$60="Public only",IF(IF('Energy and charging'!$C$33=0,$A47=0,AND($A47>0,'Energy and charging'!$C$33>($A47-1)*12,'Energy and charging'!$C$33<=$A47*12)),'Energy and charging'!$C$27,0)+MAX(0,MIN(2*12,120)-MAX(12,'Energy and charging'!$C$33))/12*'Energy and charging'!$C$29*(1+'Operating costs'!$B$53)^MAX(0,$A47-1),IF('Energy and charging'!$C$60="Complete",IF(IF('Energy and charging'!$C$33=0,$A47=0,AND($A47>0,'Energy and charging'!$C$33>($A47-1)*12,'Energy and charging'!$C$33<=$A47*12)),'Energy and charging'!$C$61,0)+MAX(0,MIN(2*12,120)-MAX(12,'Energy and charging'!$C$33))/12*'Energy and charging'!$C$62*(1+'Operating costs'!$B$53)^MAX(0,$A47-1)-IF(IF('Energy and charging'!$C$45=0,$A47=0,AND($A47>0,'Energy and charging'!$C$45>($A47-1)*12,'Energy and charging'!$C$45<=$A47*12)),'Energy and charging'!$C$44,0)+IF(IF('Energy and charging'!$C$38=0,$A47=0,AND($A47>0,'Energy and charging'!$C$38>($A47-1)*12,'Energy and charging'!$C$38<=$A47*12)),'Energy and charging'!$C$37,0)+IF(IF('Energy and charging'!$C$41=0,$A47=0,AND($A47>0,'Energy and charging'!$C$41>($A47-1)*12,'Energy and charging'!$C$41<=$A47*12)),'Energy and charging'!$C$16*'Energy and charging'!$C$40,0)+IF(IF('Energy and charging'!$C$33+'Energy and charging'!$C$34=0,$A47=0,AND($A47>0,'Energy and charging'!$C$33+'Energy and charging'!$C$34>($A47-1)*12,'Energy and charging'!$C$33+'Energy and charging'!$C$34<=$A47*12)),'Energy and charging'!$C$36,0)-IF($A47=10,'Energy and charging'!$C$35,0),"n.a."))) -> n.a. | H47: =IF(ISNUMBER(F47),F47+IF(AND('Energy and charging'!$B$60="Complete",IF('Energy and charging'!$B$33=0,$A47=0,AND($A47>0,'Energy and charging'!$B$33>($A47-1)*12,'Energy and charging'!$B$33<=$A47*12))),'Energy and charging'!$B$42,0)-IF(AND('Energy and charging'!$B$60="Complete",IF('Energy and charging'!$B$43=0,$A47=0,AND($A47>0,'Energy and charging'!$B$43>($A47-1)*12,'Energy and charging'!$B$43<=$A47*12))),'Energy and charging'!$B$42,0),"n.a.") -> n.a. | I47: =IF(ISNUMBER(G47),G47+IF(AND('Energy and charging'!$C$60="Complete",IF('Energy and charging'!$C$33=0,$A47=0,AND($A47>0,'Energy and charging'!$C$33>($A47-1)*12,'Energy and charging'!$C$33<=$A47*12))),'Energy and charging'!$C$42,0)-IF(AND('Energy and charging'!$C$60="Complete",IF('Energy and charging'!$C$43=0,$A47=0,AND($A47>0,'Energy and charging'!$C$43>($A47-1)*12,'Energy and charging'!$C$43<=$A47*12))),'Energy and charging'!$C$42,0),"n.a.") -> n.a.
A48: 3 | B48: =IF(AND(COUNTIFS(Paths!$B$7:$B$406,0,Paths!$C$7:$C$406,1,Paths!$P$7:$P$406,"<>Complete")=0,COUNTIFS(Paths!$B$7:$B$406,0,Paths!$C$7:$C$406,1)=SUM('Fleet register'!$B$7:$B$106)),SUMIFS('Annual build'!$O$7:$O$4406,'Annual build'!$B$7:$B$4406,0,'Annual build'!$C$7:$C$4406,$A48),"n.a.") -> 279908.1 | C48: =IF(AND(COUNTIFS(Paths!$B$7:$B$406,1,Paths!$C$7:$C$406,1,Paths!$P$7:$P$406,"<>Complete")=0,COUNTIFS(Paths!$B$7:$B$406,1,Paths!$C$7:$C$406,1)=SUM('Fleet register'!$B$7:$B$106)),SUMIFS('Annual build'!$O$7:$O$4406,'Annual build'!$B$7:$B$4406,1,'Annual build'!$C$7:$C$4406,$A48),"n.a.") -> 108908.1 | D48: =IF(AND(COUNTIFS(Paths!$B$7:$B$406,2,Paths!$C$7:$C$406,1,Paths!$P$7:$P$406,"<>Complete")=0,COUNTIFS(Paths!$B$7:$B$406,2,Paths!$C$7:$C$406,1)=SUM('Fleet register'!$B$7:$B$106)),IF(ISNUMBER(H48),SUMIFS('Annual build'!$O$7:$O$4406,'Annual build'!$B$7:$B$4406,2,'Annual build'!$C$7:$C$4406,$A48)+H48,"n.a."),"n.a.") -> n.a. | E48: =IF(AND(COUNTIFS(Paths!$B$7:$B$406,3,Paths!$C$7:$C$406,1,Paths!$P$7:$P$406,"<>Complete")=0,COUNTIFS(Paths!$B$7:$B$406,3,Paths!$C$7:$C$406,1)=SUM('Fleet register'!$B$7:$B$106)),IF(ISNUMBER(I48),SUMIFS('Annual build'!$O$7:$O$4406,'Annual build'!$B$7:$B$4406,3,'Annual build'!$C$7:$C$4406,$A48)+I48,"n.a."),"n.a.") -> n.a. | F48: =IF('Energy and charging'!$B$60="No EV site",0,IF('Energy and charging'!$B$60="Public only",IF(IF('Energy and charging'!$B$33=0,$A48=0,AND($A48>0,'Energy and charging'!$B$33>($A48-1)*12,'Energy and charging'!$B$33<=$A48*12)),'Energy and charging'!$B$27,0)+MAX(0,MIN(3*12,120)-MAX(24,'Energy and charging'!$B$33))/12*'Energy and charging'!$B$29*(1+'Operating costs'!$B$53)^MAX(0,$A48-1),IF('Energy and charging'!$B$60="Complete",IF(IF('Energy and charging'!$B$33=0,$A48=0,AND($A48>0,'Energy and charging'!$B$33>($A48-1)*12,'Energy and charging'!$B$33<=$A48*12)),'Energy and charging'!$B$61,0)+MAX(0,MIN(3*12,120)-MAX(24,'Energy and charging'!$B$33))/12*'Energy and charging'!$B$62*(1+'Operating costs'!$B$53)^MAX(0,$A48-1)-IF(IF('Energy and charging'!$B$45=0,$A48=0,AND($A48>0,'Energy and charging'!$B$45>($A48-1)*12,'Energy and charging'!$B$45<=$A48*12)),'Energy and charging'!$B$44,0)+IF(IF('Energy and charging'!$B$38=0,$A48=0,AND($A48>0,'Energy and charging'!$B$38>($A48-1)*12,'Energy and charging'!$B$38<=$A48*12)),'Energy and charging'!$B$37,0)+IF(IF('Energy and charging'!$B$41=0,$A48=0,AND($A48>0,'Energy and charging'!$B$41>($A48-1)*12,'Energy and charging'!$B$41<=$A48*12)),'Energy and charging'!$B$16*'Energy and charging'!$B$40,0)+IF(IF('Energy and charging'!$B$33+'Energy and charging'!$B$34=0,$A48=0,AND($A48>0,'Energy and charging'!$B$33+'Energy and charging'!$B$34>($A48-1)*12,'Energy and charging'!$B$33+'Energy and charging'!$B$34<=$A48*12)),'Energy and charging'!$B$36,0)-IF($A48=10,'Energy and charging'!$B$35,0),"n.a."))) -> n.a. | G48: =IF('Energy and charging'!$C$60="No EV site",0,IF('Energy and charging'!$C$60="Public only",IF(IF('Energy and charging'!$C$33=0,$A48=0,AND($A48>0,'Energy and charging'!$C$33>($A48-1)*12,'Energy and charging'!$C$33<=$A48*12)),'Energy and charging'!$C$27,0)+MAX(0,MIN(3*12,120)-MAX(24,'Energy and charging'!$C$33))/12*'Energy and charging'!$C$29*(1+'Operating costs'!$B$53)^MAX(0,$A48-1),IF('Energy and charging'!$C$60="Complete",IF(IF('Energy and charging'!$C$33=0,$A48=0,AND($A48>0,'Energy and charging'!$C$33>($A48-1)*12,'Energy and charging'!$C$33<=$A48*12)),'Energy and charging'!$C$61,0)+MAX(0,MIN(3*12,120)-MAX(24,'Energy and charging'!$C$33))/12*'Energy and charging'!$C$62*(1+'Operating costs'!$B$53)^MAX(0,$A48-1)-IF(IF('Energy and charging'!$C$45=0,$A48=0,AND($A48>0,'Energy and charging'!$C$45>($A48-1)*12,'Energy and charging'!$C$45<=$A48*12)),'Energy and charging'!$C$44,0)+IF(IF('Energy and charging'!$C$38=0,$A48=0,AND($A48>0,'Energy and charging'!$C$38>($A48-1)*12,'Energy and charging'!$C$38<=$A48*12)),'Energy and charging'!$C$37,0)+IF(IF('Energy and charging'!$C$41=0,$A48=0,AND($A48>0,'Energy and charging'!$C$41>($A48-1)*12,'Energy and charging'!$C$41<=$A48*12)),'Energy and charging'!$C$16*'Energy and charging'!$C$40,0)+IF(IF('Energy and charging'!$C$33+'Energy and charging'!$C$34=0,$A48=0,AND($A48>0,'Energy and charging'!$C$33+'Energy and charging'!$C$34>($A48-1)*12,'Energy and charging'!$C$33+'Energy and charging'!$C$34<=$A48*12)),'Energy and charging'!$C$36,0)-IF($A48=10,'Energy and charging'!$C$35,0),"n.a."))) -> n.a. | H48: =IF(ISNUMBER(F48),F48+IF(AND('Energy and charging'!$B$60="Complete",IF('Energy and charging'!$B$33=0,$A48=0,AND($A48>0,'Energy and charging'!$B$33>($A48-1)*12,'Energy and charging'!$B$33<=$A48*12))),'Energy and charging'!$B$42,0)-IF(AND('Energy and charging'!$B$60="Complete",IF('Energy and charging'!$B$43=0,$A48=0,AND($A48>0,'Energy and charging'!$B$43>($A48-1)*12,'Energy and charging'!$B$43<=$A48*12))),'Energy and charging'!$B$42,0),"n.a.") -> n.a. | I48: =IF(ISNUMBER(G48),G48+IF(AND('Energy and charging'!$C$60="Complete",IF('Energy and charging'!$C$33=0,$A48=0,AND($A48>0,'Energy and charging'!$C$33>($A48-1)*12,'Energy and charging'!$C$33<=$A48*12))),'Energy and charging'!$C$42,0)-IF(AND('Energy and charging'!$C$60="Complete",IF('Energy and charging'!$C$43=0,$A48=0,AND($A48>0,'Energy and charging'!$C$43>($A48-1)*12,'Energy and charging'!$C$43<=$A48*12))),'Energy and charging'!$C$42,0),"n.a.") -> n.a.
A49: 4 | B49: =IF(AND(COUNTIFS(Paths!$B$7:$B$406,0,Paths!$C$7:$C$406,1,Paths!$P$7:$P$406,"<>Complete")=0,COUNTIFS(Paths!$B$7:$B$406,0,Paths!$C$7:$C$406,1)=SUM('Fleet register'!$B$7:$B$106)),SUMIFS('Annual build'!$O$7:$O$4406,'Annual build'!$B$7:$B$4406,0,'Annual build'!$C$7:$C$4406,$A49),"n.a.") -> 279908.1 | C49: =IF(AND(COUNTIFS(Paths!$B$7:$B$406,1,Paths!$C$7:$C$406,1,Paths!$P$7:$P$406,"<>Complete")=0,COUNTIFS(Paths!$B$7:$B$406,1,Paths!$C$7:$C$406,1)=SUM('Fleet register'!$B$7:$B$106)),SUMIFS('Annual build'!$O$7:$O$4406,'Annual build'!$B$7:$B$4406,1,'Annual build'!$C$7:$C$4406,$A49),"n.a.") -> 108908.1 | D49: =IF(AND(COUNTIFS(Paths!$B$7:$B$406,2,Paths!$C$7:$C$406,1,Paths!$P$7:$P$406,"<>Complete")=0,COUNTIFS(Paths!$B$7:$B$406,2,Paths!$C$7:$C$406,1)=SUM('Fleet register'!$B$7:$B$106)),IF(ISNUMBER(H49),SUMIFS('Annual build'!$O$7:$O$4406,'Annual build'!$B$7:$B$4406,2,'Annual build'!$C$7:$C$4406,$A49)+H49,"n.a."),"n.a.") -> n.a. | E49: =IF(AND(COUNTIFS(Paths!$B$7:$B$406,3,Paths!$C$7:$C$406,1,Paths!$P$7:$P$406,"<>Complete")=0,COUNTIFS(Paths!$B$7:$B$406,3,Paths!$C$7:$C$406,1)=SUM('Fleet register'!$B$7:$B$106)),IF(ISNUMBER(I49),SUMIFS('Annual build'!$O$7:$O$4406,'Annual build'!$B$7:$B$4406,3,'Annual build'!$C$7:$C$4406,$A49)+I49,"n.a."),"n.a.") -> n.a. | F49: =IF('Energy and charging'!$B$60="No EV site",0,IF('Energy and charging'!$B$60="Public only",IF(IF('Energy and charging'!$B$33=0,$A49=0,AND($A49>0,'Energy and charging'!$B$33>($A49-1)*12,'Energy and charging'!$B$33<=$A49*12)),'Energy and charging'!$B$27,0)+MAX(0,MIN(4*12,120)-MAX(36,'Energy and charging'!$B$33))/12*'Energy and charging'!$B$29*(1+'Operating costs'!$B$53)^MAX(0,$A49-1),IF('Energy and charging'!$B$60="Complete",IF(IF('Energy and charging'!$B$33=0,$A49=0,AND($A49>0,'Energy and charging'!$B$33>($A49-1)*12,'Energy and charging'!$B$33<=$A49*12)),'Energy and charging'!$B$61,0)+MAX(0,MIN(4*12,120)-MAX(36,'Energy and charging'!$B$33))/12*'Energy and charging'!$B$62*(1+'Operating costs'!$B$53)^MAX(0,$A49-1)-IF(IF('Energy and charging'!$B$45=0,$A49=0,AND($A49>0,'Energy and charging'!$B$45>($A49-1)*12,'Energy and charging'!$B$45<=$A49*12)),'Energy and charging'!$B$44,0)+IF(IF('Energy and charging'!$B$38=0,$A49=0,AND($A49>0,'Energy and charging'!$B$38>($A49-1)*12,'Energy and charging'!$B$38<=$A49*12)),'Energy and charging'!$B$37,0)+IF(IF('Energy and charging'!$B$41=0,$A49=0,AND($A49>0,'Energy and charging'!$B$41>($A49-1)*12,'Energy and charging'!$B$41<=$A49*12)),'Energy and charging'!$B$16*'Energy and charging'!$B$40,0)+IF(IF('Energy and charging'!$B$33+'Energy and charging'!$B$34=0,$A49=0,AND($A49>0,'Energy and charging'!$B$33+'Energy and charging'!$B$34>($A49-1)*12,'Energy and charging'!$B$33+'Energy and charging'!$B$34<=$A49*12)),'Energy and charging'!$B$36,0)-IF($A49=10,'Energy and charging'!$B$35,0),"n.a."))) -> n.a. | G49: =IF('Energy and charging'!$C$60="No EV site",0,IF('Energy and charging'!$C$60="Public only",IF(IF('Energy and charging'!$C$33=0,$A49=0,AND($A49>0,'Energy and charging'!$C$33>($A49-1)*12,'Energy and charging'!$C$33<=$A49*12)),'Energy and charging'!$C$27,0)+MAX(0,MIN(4*12,120)-MAX(36,'Energy and charging'!$C$33))/12*'Energy and charging'!$C$29*(1+'Operating costs'!$B$53)^MAX(0,$A49-1),IF('Energy and charging'!$C$60="Complete",IF(IF('Energy and charging'!$C$33=0,$A49=0,AND($A49>0,'Energy and charging'!$C$33>($A49-1)*12,'Energy and charging'!$C$33<=$A49*12)),'Energy and charging'!$C$61,0)+MAX(0,MIN(4*12,120)-MAX(36,'Energy and charging'!$C$33))/12*'Energy and charging'!$C$62*(1+'Operating costs'!$B$53)^MAX(0,$A49-1)-IF(IF('Energy and charging'!$C$45=0,$A49=0,AND($A49>0,'Energy and charging'!$C$45>($A49-1)*12,'Energy and charging'!$C$45<=$A49*12)),'Energy and charging'!$C$44,0)+IF(IF('Energy and charging'!$C$38=0,$A49=0,AND($A49>0,'Energy and charging'!$C$38>($A49-1)*12,'Energy and charging'!$C$38<=$A49*12)),'Energy and charging'!$C$37,0)+IF(IF('Energy and charging'!$C$41=0,$A49=0,AND($A49>0,'Energy and charging'!$C$41>($A49-1)*12,'Energy and charging'!$C$41<=$A49*12)),'Energy and charging'!$C$16*'Energy and charging'!$C$40,0)+IF(IF('Energy and charging'!$C$33+'Energy and charging'!$C$34=0,$A49=0,AND($A49>0,'Energy and charging'!$C$33+'Energy and charging'!$C$34>($A49-1)*12,'Energy and charging'!$C$33+'Energy and charging'!$C$34<=$A49*12)),'Energy and charging'!$C$36,0)-IF($A49=10,'Energy and charging'!$C$35,0),"n.a."))) -> n.a. | H49: =IF(ISNUMBER(F49),F49+IF(AND('Energy and charging'!$B$60="Complete",IF('Energy and charging'!$B$33=0,$A49=0,AND($A49>0,'Energy and charging'!$B$33>($A49-1)*12,'Energy and charging'!$B$33<=$A49*12))),'Energy and charging'!$B$42,0)-IF(AND('Energy and charging'!$B$60="Complete",IF('Energy and charging'!$B$43=0,$A49=0,AND($A49>0,'Energy and charging'!$B$43>($A49-1)*12,'Energy and charging'!$B$43<=$A49*12))),'Energy and charging'!$B$42,0),"n.a.") -> n.a. | I49: =IF(ISNUMBER(G49),G49+IF(AND('Energy and charging'!$C$60="Complete",IF('Energy and charging'!$C$33=0,$A49=0,AND($A49>0,'Energy and charging'!$C$33>($A49-1)*12,'Energy and charging'!$C$33<=$A49*12))),'Energy and charging'!$C$42,0)-IF(AND('Energy and charging'!$C$60="Complete",IF('Energy and charging'!$C$43=0,$A49=0,AND($A49>0,'Energy and charging'!$C$43>($A49-1)*12,'Energy and charging'!$C$43<=$A49*12))),'Energy and charging'!$C$42,0),"n.a.") -> n.a.
A50: 5 | B50: =IF(AND(COUNTIFS(Paths!$B$7:$B$406,0,Paths!$C$7:$C$406,1,Paths!$P$7:$P$406,"<>Complete")=0,COUNTIFS(Paths!$B$7:$B$406,0,Paths!$C$7:$C$406,1)=SUM('Fleet register'!$B$7:$B$106)),SUMIFS('Annual build'!$O$7:$O$4406,'Annual build'!$B$7:$B$4406,0,'Annual build'!$C$7:$C$4406,$A50),"n.a.") -> 279908.1 | C50: =IF(AND(COUNTIFS(Paths!$B$7:$B$406,1,Paths!$C$7:$C$406,1,Paths!$P$7:$P$406,"<>Complete")=0,COUNTIFS(Paths!$B$7:$B$406,1,Paths!$C$7:$C$406,1)=SUM('Fleet register'!$B$7:$B$106)),SUMIFS('Annual build'!$O$7:$O$4406,'Annual build'!$B$7:$B$4406,1,'Annual build'!$C$7:$C$4406,$A50),"n.a.") -> 108908.1 | D50: =IF(AND(COUNTIFS(Paths!$B$7:$B$406,2,Paths!$C$7:$C$406,1,Paths!$P$7:$P$406,"<>Complete")=0,COUNTIFS(Paths!$B$7:$B$406,2,Paths!$C$7:$C$406,1)=SUM('Fleet register'!$B$7:$B$106)),IF(ISNUMBER(H50),SUMIFS('Annual build'!$O$7:$O$4406,'Annual build'!$B$7:$B$4406,2,'Annual build'!$C$7:$C$4406,$A50)+H50,"n.a."),"n.a.") -> n.a. | E50: =IF(AND(COUNTIFS(Paths!$B$7:$B$406,3,Paths!$C$7:$C$406,1,Paths!$P$7:$P$406,"<>Complete")=0,COUNTIFS(Paths!$B$7:$B$406,3,Paths!$C$7:$C$406,1)=SUM('Fleet register'!$B$7:$B$106)),IF(ISNUMBER(I50),SUMIFS('Annual build'!$O$7:$O$4406,'Annual build'!$B$7:$B$4406,3,'Annual build'!$C$7:$C$4406,$A50)+I50,"n.a."),"n.a.") -> n.a. | F50: =IF('Energy and charging'!$B$60="No EV site",0,IF('Energy and charging'!$B$60="Public only",IF(IF('Energy and charging'!$B$33=0,$A50=0,AND($A50>0,'Energy and charging'!$B$33>($A50-1)*12,'Energy and charging'!$B$33<=$A50*12)),'Energy and charging'!$B$27,0)+MAX(0,MIN(5*12,120)-MAX(48,'Energy and charging'!$B$33))/12*'Energy and charging'!$B$29*(1+'Operating costs'!$B$53)^MAX(0,$A50-1),IF('Energy and charging'!$B$60="Complete",IF(IF('Energy and charging'!$B$33=0,$A50=0,AND($A50>0,'Energy and charging'!$B$33>($A50-1)*12,'Energy and charging'!$B$33<=$A50*12)),'Energy and charging'!$B$61,0)+MAX(0,MIN(5*12,120)-MAX(48,'Energy and charging'!$B$33))/12*'Energy and charging'!$B$62*(1+'Operating costs'!$B$53)^MAX(0,$A50-1)-IF(IF('Energy and charging'!$B$45=0,$A50=0,AND($A50>0,'Energy and charging'!$B$45>($A50-1)*12,'Energy and charging'!$B$45<=$A50*12)),'Energy and charging'!$B$44,0)+IF(IF('Energy and charging'!$B$38=0,$A50=0,AND($A50>0,'Energy and charging'!$B$38>($A50-1)*12,'Energy and charging'!$B$38<=$A50*12)),'Energy and charging'!$B$37,0)+IF(IF('Energy and charging'!$B$41=0,$A50=0,AND($A50>0,'Energy and charging'!$B$41>($A50-1)*12,'Energy and charging'!$B$41<=$A50*12)),'Energy and charging'!$B$16*'Energy and charging'!$B$40,0)+IF(IF('Energy and charging'!$B$33+'Energy and charging'!$B$34=0,$A50=0,AND($A50>0,'Energy and charging'!$B$33+'Energy and charging'!$B$34>($A50-1)*12,'Energy and charging'!$B$33+'Energy and charging'!$B$34<=$A50*12)),'Energy and charging'!$B$36,0)-IF($A50=10,'Energy and charging'!$B$35,0),"n.a."))) -> n.a. | G50: =IF('Energy and charging'!$C$60="No EV site",0,IF('Energy and charging'!$C$60="Public only",IF(IF('Energy and charging'!$C$33=0,$A50=0,AND($A50>0,'Energy and charging'!$C$33>($A50-1)*12,'Energy and charging'!$C$33<=$A50*12)),'Energy and charging'!$C$27,0)+MAX(0,MIN(5*12,120)-MAX(48,'Energy and charging'!$C$33))/12*'Energy and charging'!$C$29*(1+'Operating costs'!$B$53)^MAX(0,$A50-1),IF('Energy and charging'!$C$60="Complete",IF(IF('Energy and charging'!$C$33=0,$A50=0,AND($A50>0,'Energy and charging'!$C$33>($A50-1)*12,'Energy and charging'!$C$33<=$A50*12)),'Energy and charging'!$C$61,0)+MAX(0,MIN(5*12,120)-MAX(48,'Energy and charging'!$C$33))/12*'Energy and charging'!$C$62*(1+'Operating costs'!$B$53)^MAX(0,$A50-1)-IF(IF('Energy and charging'!$C$45=0,$A50=0,AND($A50>0,'Energy and charging'!$C$45>($A50-1)*12,'Energy and charging'!$C$45<=$A50*12)),'Energy and charging'!$C$44,0)+IF(IF('Energy and charging'!$C$38=0,$A50=0,AND($A50>0,'Energy and charging'!$C$38>($A50-1)*12,'Energy and charging'!$C$38<=$A50*12)),'Energy and charging'!$C$37,0)+IF(IF('Energy and charging'!$C$41=0,$A50=0,AND($A50>0,'Energy and charging'!$C$41>($A50-1)*12,'Energy and charging'!$C$41<=$A50*12)),'Energy and charging'!$C$16*'Energy and charging'!$C$40,0)+IF(IF('Energy and charging'!$C$33+'Energy and charging'!$C$34=0,$A50=0,AND($A50>0,'Energy and charging'!$C$33+'Energy and charging'!$C$34>($A50-1)*12,'Energy and charging'!$C$33+'Energy and charging'!$C$34<=$A50*12)),'Energy and charging'!$C$36,0)-IF($A50=10,'Energy and charging'!$C$35,0),"n.a."))) -> n.a. | H50: =IF(ISNUMBER(F50),F50+IF(AND('Energy and charging'!$B$60="Complete",IF('Energy and charging'!$B$33=0,$A50=0,AND($A50>0,'Energy and charging'!$B$33>($A50-1)*12,'Energy and charging'!$B$33<=$A50*12))),'Energy and charging'!$B$42,0)-IF(AND('Energy and charging'!$B$60="Complete",IF('Energy and charging'!$B$43=0,$A50=0,AND($A50>0,'Energy and charging'!$B$43>($A50-1)*12,'Energy and charging'!$B$43<=$A50*12))),'Energy and charging'!$B$42,0),"n.a.") -> n.a. | I50: =IF(ISNUMBER(G50),G50+IF(AND('Energy and charging'!$C$60="Complete",IF('Energy and charging'!$C$33=0,$A50=0,AND($A50>0,'Energy and charging'!$C$33>($A50-1)*12,'Energy and charging'!$C$33<=$A50*12))),'Energy and charging'!$C$42,0)-IF(AND('Energy and charging'!$C$60="Complete",IF('Energy and charging'!$C$43=0,$A50=0,AND($A50>0,'Energy and charging'!$C$43>($A50-1)*12,'Energy and charging'!$C$43<=$A50*12))),'Energy and charging'!$C$42,0),"n.a.") -> n.a.
A51: 6 | B51: =IF(AND(COUNTIFS(Paths!$B$7:$B$406,0,Paths!$C$7:$C$406,1,Paths!$P$7:$P$406,"<>Complete")=0,COUNTIFS(Paths!$B$7:$B$406,0,Paths!$C$7:$C$406,1)=SUM('Fleet register'!$B$7:$B$106)),SUMIFS('Annual build'!$O$7:$O$4406,'Annual build'!$B$7:$B$4406,0,'Annual build'!$C$7:$C$4406,$A51),"n.a.") -> 279908.1 | C51: =IF(AND(COUNTIFS(Paths!$B$7:$B$406,1,Paths!$C$7:$C$406,1,Paths!$P$7:$P$406,"<>Complete")=0,COUNTIFS(Paths!$B$7:$B$406,1,Paths!$C$7:$C$406,1)=SUM('Fleet register'!$B$7:$B$106)),SUMIFS('Annual build'!$O$7:$O$4406,'Annual build'!$B$7:$B$4406,1,'Annual build'!$C$7:$C$4406,$A51),"n.a.") -> 108908.1 | D51: =IF(AND(COUNTIFS(Paths!$B$7:$B$406,2,Paths!$C$7:$C$406,1,Paths!$P$7:$P$406,"<>Complete")=0,COUNTIFS(Paths!$B$7:$B$406,2,Paths!$C$7:$C$406,1)=SUM('Fleet register'!$B$7:$B$106)),IF(ISNUMBER(H51),SUMIFS('Annual build'!$O$7:$O$4406,'Annual build'!$B$7:$B$4406,2,'Annual build'!$C$7:$C$4406,$A51)+H51,"n.a."),"n.a.") -> n.a. | E51: =IF(AND(COUNTIFS(Paths!$B$7:$B$406,3,Paths!$C$7:$C$406,1,Paths!$P$7:$P$406,"<>Complete")=0,COUNTIFS(Paths!$B$7:$B$406,3,Paths!$C$7:$C$406,1)=SUM('Fleet register'!$B$7:$B$106)),IF(ISNUMBER(I51),SUMIFS('Annual build'!$O$7:$O$4406,'Annual build'!$B$7:$B$4406,3,'Annual build'!$C$7:$C$4406,$A51)+I51,"n.a."),"n.a.") -> n.a. | F51: =IF('Energy and charging'!$B$60="No EV site",0,IF('Energy and charging'!$B$60="Public only",IF(IF('Energy and charging'!$B$33=0,$A51=0,AND($A51>0,'Energy and charging'!$B$33>($A51-1)*12,'Energy and charging'!$B$33<=$A51*12)),'Energy and charging'!$B$27,0)+MAX(0,MIN(6*12,120)-MAX(60,'Energy and charging'!$B$33))/12*'Energy and charging'!$B$29*(1+'Operating costs'!$B$53)^MAX(0,$A51-1),IF('Energy and charging'!$B$60="Complete",IF(IF('Energy and charging'!$B$33=0,$A51=0,AND($A51>0,'Energy and charging'!$B$33>($A51-1)*12,'Energy and charging'!$B$33<=$A51*12)),'Energy and charging'!$B$61,0)+MAX(0,MIN(6*12,120)-MAX(60,'Energy and charging'!$B$33))/12*'Energy and charging'!$B$62*(1+'Operating costs'!$B$53)^MAX(0,$A51-1)-IF(IF('Energy and charging'!$B$45=0,$A51=0,AND($A51>0,'Energy and charging'!$B$45>($A51-1)*12,'Energy and charging'!$B$45<=$A51*12)),'Energy and charging'!$B$44,0)+IF(IF('Energy and charging'!$B$38=0,$A51=0,AND($A51>0,'Energy and charging'!$B$38>($A51-1)*12,'Energy and charging'!$B$38<=$A51*12)),'Energy and charging'!$B$37,0)+IF(IF('Energy and charging'!$B$41=0,$A51=0,AND($A51>0,'Energy and charging'!$B$41>($A51-1)*12,'Energy and charging'!$B$41<=$A51*12)),'Energy and charging'!$B$16*'Energy and charging'!$B$40,0)+IF(IF('Energy and charging'!$B$33+'Energy and charging'!$B$34=0,$A51=0,AND($A51>0,'Energy and charging'!$B$33+'Energy and charging'!$B$34>($A51-1)*12,'Energy and charging'!$B$33+'Energy and charging'!$B$34<=$A51*12)),'Energy and charging'!$B$36,0)-IF($A51=10,'Energy and charging'!$B$35,0),"n.a."))) -> n.a. | G51: =IF('Energy and charging'!$C$60="No EV site",0,IF('Energy and charging'!$C$60="Public only",IF(IF('Energy and charging'!$C$33=0,$A51=0,AND($A51>0,'Energy and charging'!$C$33>($A51-1)*12,'Energy and charging'!$C$33<=$A51*12)),'Energy and charging'!$C$27,0)+MAX(0,MIN(6*12,120)-MAX(60,'Energy and charging'!$C$33))/12*'Energy and charging'!$C$29*(1+'Operating costs'!$B$53)^MAX(0,$A51-1),IF('Energy and charging'!$C$60="Complete",IF(IF('Energy and charging'!$C$33=0,$A51=0,AND($A51>0,'Energy and charging'!$C$33>($A51-1)*12,'Energy and charging'!$C$33<=$A51*12)),'Energy and charging'!$C$61,0)+MAX(0,MIN(6*12,120)-MAX(60,'Energy and charging'!$C$33))/12*'Energy and charging'!$C$62*(1+'Operating costs'!$B$53)^MAX(0,$A51-1)-IF(IF('Energy and charging'!$C$45=0,$A51=0,AND($A51>0,'Energy and charging'!$C$45>($A51-1)*12,'Energy and charging'!$C$45<=$A51*12)),'Energy and charging'!$C$44,0)+IF(IF('Energy and charging'!$C$38=0,$A51=0,AND($A51>0,'Energy and charging'!$C$38>($A51-1)*12,'Energy and charging'!$C$38<=$A51*12)),'Energy and charging'!$C$37,0)+IF(IF('Energy and charging'!$C$41=0,$A51=0,AND($A51>0,'Energy and charging'!$C$41>($A51-1)*12,'Energy and charging'!$C$41<=$A51*12)),'Energy and charging'!$C$16*'Energy and charging'!$C$40,0)+IF(IF('Energy and charging'!$C$33+'Energy and charging'!$C$34=0,$A51=0,AND($A51>0,'Energy and charging'!$C$33+'Energy and charging'!$C$34>($A51-1)*12,'Energy and charging'!$C$33+'Energy and charging'!$C$34<=$A51*12)),'Energy and charging'!$C$36,0)-IF($A51=10,'Energy and charging'!$C$35,0),"n.a."))) -> n.a. | H51: =IF(ISNUMBER(F51),F51+IF(AND('Energy and charging'!$B$60="Complete",IF('Energy and charging'!$B$33=0,$A51=0,AND($A51>0,'Energy and charging'!$B$33>($A51-1)*12,'Energy and charging'!$B$33<=$A51*12))),'Energy and charging'!$B$42,0)-IF(AND('Energy and charging'!$B$60="Complete",IF('Energy and charging'!$B$43=0,$A51=0,AND($A51>0,'Energy and charging'!$B$43>($A51-1)*12,'Energy and charging'!$B$43<=$A51*12))),'Energy and charging'!$B$42,0),"n.a.") -> n.a. | I51: =IF(ISNUMBER(G51),G51+IF(AND('Energy and charging'!$C$60="Complete",IF('Energy and charging'!$C$33=0,$A51=0,AND($A51>0,'Energy and charging'!$C$33>($A51-1)*12,'Energy and charging'!$C$33<=$A51*12))),'Energy and charging'!$C$42,0)-IF(AND('Energy and charging'!$C$60="Complete",IF('Energy and charging'!$C$43=0,$A51=0,AND($A51>0,'Energy and charging'!$C$43>($A51-1)*12,'Energy and charging'!$C$43<=$A51*12))),'Energy and charging'!$C$42,0),"n.a.") -> n.a.
A52: 7 | B52: =IF(AND(COUNTIFS(Paths!$B$7:$B$406,0,Paths!$C$7:$C$406,1,Paths!$P$7:$P$406,"<>Complete")=0,COUNTIFS(Paths!$B$7:$B$406,0,Paths!$C$7:$C$406,1)=SUM('Fleet register'!$B$7:$B$106)),SUMIFS('Annual build'!$O$7:$O$4406,'Annual build'!$B$7:$B$4406,0,'Annual build'!$C$7:$C$4406,$A52),"n.a.") -> 108908.1 | C52: =IF(AND(COUNTIFS(Paths!$B$7:$B$406,1,Paths!$C$7:$C$406,1,Paths!$P$7:$P$406,"<>Complete")=0,COUNTIFS(Paths!$B$7:$B$406,1,Paths!$C$7:$C$406,1)=SUM('Fleet register'!$B$7:$B$106)),SUMIFS('Annual build'!$O$7:$O$4406,'Annual build'!$B$7:$B$4406,1,'Annual build'!$C$7:$C$4406,$A52),"n.a.") -> 108908.1 | D52: =IF(AND(COUNTIFS(Paths!$B$7:$B$406,2,Paths!$C$7:$C$406,1,Paths!$P$7:$P$406,"<>Complete")=0,COUNTIFS(Paths!$B$7:$B$406,2,Paths!$C$7:$C$406,1)=SUM('Fleet register'!$B$7:$B$106)),IF(ISNUMBER(H52),SUMIFS('Annual build'!$O$7:$O$4406,'Annual build'!$B$7:$B$4406,2,'Annual build'!$C$7:$C$4406,$A52)+H52,"n.a."),"n.a.") -> n.a. | E52: =IF(AND(COUNTIFS(Paths!$B$7:$B$406,3,Paths!$C$7:$C$406,1,Paths!$P$7:$P$406,"<>Complete")=0,COUNTIFS(Paths!$B$7:$B$406,3,Paths!$C$7:$C$406,1)=SUM('Fleet register'!$B$7:$B$106)),IF(ISNUMBER(I52),SUMIFS('Annual build'!$O$7:$O$4406,'Annual build'!$B$7:$B$4406,3,'Annual build'!$C$7:$C$4406,$A52)+I52,"n.a."),"n.a.") -> n.a. | F52: =IF('Energy and charging'!$B$60="No EV site",0,IF('Energy and charging'!$B$60="Public only",IF(IF('Energy and charging'!$B$33=0,$A52=0,AND($A52>0,'Energy and charging'!$B$33>($A52-1)*12,'Energy and charging'!$B$33<=$A52*12)),'Energy and charging'!$B$27,0)+MAX(0,MIN(7*12,120)-MAX(72,'Energy and charging'!$B$33))/12*'Energy and charging'!$B$29*(1+'Operating costs'!$B$53)^MAX(0,$A52-1),IF('Energy and charging'!$B$60="Complete",IF(IF('Energy and charging'!$B$33=0,$A52=0,AND($A52>0,'Energy and charging'!$B$33>($A52-1)*12,'Energy and charging'!$B$33<=$A52*12)),'Energy and charging'!$B$61,0)+MAX(0,MIN(7*12,120)-MAX(72,'Energy and charging'!$B$33))/12*'Energy and charging'!$B$62*(1+'Operating costs'!$B$53)^MAX(0,$A52-1)-IF(IF('Energy and charging'!$B$45=0,$A52=0,AND($A52>0,'Energy and charging'!$B$45>($A52-1)*12,'Energy and charging'!$B$45<=$A52*12)),'Energy and charging'!$B$44,0)+IF(IF('Energy and charging'!$B$38=0,$A52=0,AND($A52>0,'Energy and charging'!$B$38>($A52-1)*12,'Energy and charging'!$B$38<=$A52*12)),'Energy and charging'!$B$37,0)+IF(IF('Energy and charging'!$B$41=0,$A52=0,AND($A52>0,'Energy and charging'!$B$41>($A52-1)*12,'Energy and charging'!$B$41<=$A52*12)),'Energy and charging'!$B$16*'Energy and charging'!$B$40,0)+IF(IF('Energy and charging'!$B$33+'Energy and charging'!$B$34=0,$A52=0,AND($A52>0,'Energy and charging'!$B$33+'Energy and charging'!$B$34>($A52-1)*12,'Energy and charging'!$B$33+'Energy and charging'!$B$34<=$A52*12)),'Energy and charging'!$B$36,0)-IF($A52=10,'Energy and charging'!$B$35,0),"n.a."))) -> n.a. | G52: =IF('Energy and charging'!$C$60="No EV site",0,IF('Energy and charging'!$C$60="Public only",IF(IF('Energy and charging'!$C$33=0,$A52=0,AND($A52>0,'Energy and charging'!$C$33>($A52-1)*12,'Energy and charging'!$C$33<=$A52*12)),'Energy and charging'!$C$27,0)+MAX(0,MIN(7*12,120)-MAX(72,'Energy and charging'!$C$33))/12*'Energy and charging'!$C$29*(1+'Operating costs'!$B$53)^MAX(0,$A52-1),IF('Energy and charging'!$C$60="Complete",IF(IF('Energy and charging'!$C$33=0,$A52=0,AND($A52>0,'Energy and charging'!$C$33>($A52-1)*12,'Energy and charging'!$C$33<=$A52*12)),'Energy and charging'!$C$61,0)+MAX(0,MIN(7*12,120)-MAX(72,'Energy and charging'!$C$33))/12*'Energy and charging'!$C$62*(1+'Operating costs'!$B$53)^MAX(0,$A52-1)-IF(IF('Energy and charging'!$C$45=0,$A52=0,AND($A52>0,'Energy and charging'!$C$45>($A52-1)*12,'Energy and charging'!$C$45<=$A52*12)),'Energy and charging'!$C$44,0)+IF(IF('Energy and charging'!$C$38=0,$A52=0,AND($A52>0,'Energy and charging'!$C$38>($A52-1)*12,'Energy and charging'!$C$38<=$A52*12)),'Energy and charging'!$C$37,0)+IF(IF('Energy and charging'!$C$41=0,$A52=0,AND($A52>0,'Energy and charging'!$C$41>($A52-1)*12,'Energy and charging'!$C$41<=$A52*12)),'Energy and charging'!$C$16*'Energy and charging'!$C$40,0)+IF(IF('Energy and charging'!$C$33+'Energy and charging'!$C$34=0,$A52=0,AND($A52>0,'Energy and charging'!$C$33+'Energy and charging'!$C$34>($A52-1)*12,'Energy and charging'!$C$33+'Energy and charging'!$C$34<=$A52*12)),'Energy and charging'!$C$36,0)-IF($A52=10,'Energy and charging'!$C$35,0),"n.a."))) -> n.a. | H52: =IF(ISNUMBER(F52),F52+IF(AND('Energy and charging'!$B$60="Complete",IF('Energy and charging'!$B$33=0,$A52=0,AND($A52>0,'Energy and charging'!$B$33>($A52-1)*12,'Energy and charging'!$B$33<=$A52*12))),'Energy and charging'!$B$42,0)-IF(AND('Energy and charging'!$B$60="Complete",IF('Energy and charging'!$B$43=0,$A52=0,AND($A52>0,'Energy and charging'!$B$43>($A52-1)*12,'Energy and charging'!$B$43<=$A52*12))),'Energy and charging'!$B$42,0),"n.a.") -> n.a. | I52: =IF(ISNUMBER(G52),G52+IF(AND('Energy and charging'!$C$60="Complete",IF('Energy and charging'!$C$33=0,$A52=0,AND($A52>0,'Energy and charging'!$C$33>($A52-1)*12,'Energy and charging'!$C$33<=$A52*12))),'Energy and charging'!$C$42,0)-IF(AND('Energy and charging'!$C$60="Complete",IF('Energy and charging'!$C$43=0,$A52=0,AND($A52>0,'Energy and charging'!$C$43>($A52-1)*12,'Energy and charging'!$C$43<=$A52*12))),'Energy and charging'!$C$42,0),"n.a.") -> n.a.
A53: 8 | B53: =IF(AND(COUNTIFS(Paths!$B$7:$B$406,0,Paths!$C$7:$C$406,1,Paths!$P$7:$P$406,"<>Complete")=0,COUNTIFS(Paths!$B$7:$B$406,0,Paths!$C$7:$C$406,1)=SUM('Fleet register'!$B$7:$B$106)),SUMIFS('Annual build'!$O$7:$O$4406,'Annual build'!$B$7:$B$4406,0,'Annual build'!$C$7:$C$4406,$A53),"n.a.") -> 108908.1 | C53: =IF(AND(COUNTIFS(Paths!$B$7:$B$406,1,Paths!$C$7:$C$406,1,Paths!$P$7:$P$406,"<>Complete")=0,COUNTIFS(Paths!$B$7:$B$406,1,Paths!$C$7:$C$406,1)=SUM('Fleet register'!$B$7:$B$106)),SUMIFS('Annual build'!$O$7:$O$4406,'Annual build'!$B$7:$B$4406,1,'Annual build'!$C$7:$C$4406,$A53),"n.a.") -> 108908.1 | D53: =IF(AND(COUNTIFS(Paths!$B$7:$B$406,2,Paths!$C$7:$C$406,1,Paths!$P$7:$P$406,"<>Complete")=0,COUNTIFS(Paths!$B$7:$B$406,2,Paths!$C$7:$C$406,1)=SUM('Fleet register'!$B$7:$B$106)),IF(ISNUMBER(H53),SUMIFS('Annual build'!$O$7:$O$4406,'Annual build'!$B$7:$B$4406,2,'Annual build'!$C$7:$C$4406,$A53)+H53,"n.a."),"n.a.") -> n.a. | E53: =IF(AND(COUNTIFS(Paths!$B$7:$B$406,3,Paths!$C$7:$C$406,1,Paths!$P$7:$P$406,"<>Complete")=0,COUNTIFS(Paths!$B$7:$B$406,3,Paths!$C$7:$C$406,1)=SUM('Fleet register'!$B$7:$B$106)),IF(ISNUMBER(I53),SUMIFS('Annual build'!$O$7:$O$4406,'Annual build'!$B$7:$B$4406,3,'Annual build'!$C$7:$C$4406,$A53)+I53,"n.a."),"n.a.") -> n.a. | F53: =IF('Energy and charging'!$B$60="No EV site",0,IF('Energy and charging'!$B$60="Public only",IF(IF('Energy and charging'!$B$33=0,$A53=0,AND($A53>0,'Energy and charging'!$B$33>($A53-1)*12,'Energy and charging'!$B$33<=$A53*12)),'Energy and charging'!$B$27,0)+MAX(0,MIN(8*12,120)-MAX(84,'Energy and charging'!$B$33))/12*'Energy and charging'!$B$29*(1+'Operating costs'!$B$53)^MAX(0,$A53-1),IF('Energy and charging'!$B$60="Complete",IF(IF('Energy and charging'!$B$33=0,$A53=0,AND($A53>0,'Energy and charging'!$B$33>($A53-1)*12,'Energy and charging'!$B$33<=$A53*12)),'Energy and charging'!$B$61,0)+MAX(0,MIN(8*12,120)-MAX(84,'Energy and charging'!$B$33))/12*'Energy and charging'!$B$62*(1+'Operating costs'!$B$53)^MAX(0,$A53-1)-IF(IF('Energy and charging'!$B$45=0,$A53=0,AND($A53>0,'Energy and charging'!$B$45>($A53-1)*12,'Energy and charging'!$B$45<=$A53*12)),'Energy and charging'!$B$44,0)+IF(IF('Energy and charging'!$B$38=0,$A53=0,AND($A53>0,'Energy and charging'!$B$38>($A53-1)*12,'Energy and charging'!$B$38<=$A53*12)),'Energy and charging'!$B$37,0)+IF(IF('Energy and charging'!$B$41=0,$A53=0,AND($A53>0,'Energy and charging'!$B$41>($A53-1)*12,'Energy and charging'!$B$41<=$A53*12)),'Energy and charging'!$B$16*'Energy and charging'!$B$40,0)+IF(IF('Energy and charging'!$B$33+'Energy and charging'!$B$34=0,$A53=0,AND($A53>0,'Energy and charging'!$B$33+'Energy and charging'!$B$34>($A53-1)*12,'Energy and charging'!$B$33+'Energy and charging'!$B$34<=$A53*12)),'Energy and charging'!$B$36,0)-IF($A53=10,'Energy and charging'!$B$35,0),"n.a."))) -> n.a. | G53: =IF('Energy and charging'!$C$60="No EV site",0,IF('Energy and charging'!$C$60="Public only",IF(IF('Energy and charging'!$C$33=0,$A53=0,AND($A53>0,'Energy and charging'!$C$33>($A53-1)*12,'Energy and charging'!$C$33<=$A53*12)),'Energy and charging'!$C$27,0)+MAX(0,MIN(8*12,120)-MAX(84,'Energy and charging'!$C$33))/12*'Energy and charging'!$C$29*(1+'Operating costs'!$B$53)^MAX(0,$A53-1),IF('Energy and charging'!$C$60="Complete",IF(IF('Energy and charging'!$C$33=0,$A53=0,AND($A53>0,'Energy and charging'!$C$33>($A53-1)*12,'Energy and charging'!$C$33<=$A53*12)),'Energy and charging'!$C$61,0)+MAX(0,MIN(8*12,120)-MAX(84,'Energy and charging'!$C$33))/12*'Energy and charging'!$C$62*(1+'Operating costs'!$B$53)^MAX(0,$A53-1)-IF(IF('Energy and charging'!$C$45=0,$A53=0,AND($A53>0,'Energy and charging'!$C$45>($A53-1)*12,'Energy and charging'!$C$45<=$A53*12)),'Energy and charging'!$C$44,0)+IF(IF('Energy and charging'!$C$38=0,$A53=0,AND($A53>0,'Energy and charging'!$C$38>($A53-1)*12,'Energy and charging'!$C$38<=$A53*12)),'Energy and charging'!$C$37,0)+IF(IF('Energy and charging'!$C$41=0,$A53=0,AND($A53>0,'Energy and charging'!$C$41>($A53-1)*12,'Energy and charging'!$C$41<=$A53*12)),'Energy and charging'!$C$16*'Energy and charging'!$C$40,0)+IF(IF('Energy and charging'!$C$33+'Energy and charging'!$C$34=0,$A53=0,AND($A53>0,'Energy and charging'!$C$33+'Energy and charging'!$C$34>($A53-1)*12,'Energy and charging'!$C$33+'Energy and charging'!$C$34<=$A53*12)),'Energy and charging'!$C$36,0)-IF($A53=10,'Energy and charging'!$C$35,0),"n.a."))) -> n.a. | H53: =IF(ISNUMBER(F53),F53+IF(AND('Energy and charging'!$B$60="Complete",IF('Energy and charging'!$B$33=0,$A53=0,AND($A53>0,'Energy and charging'!$B$33>($A53-1)*12,'Energy and charging'!$B$33<=$A53*12))),'Energy and charging'!$B$42,0)-IF(AND('Energy and charging'!$B$60="Complete",IF('Energy and charging'!$B$43=0,$A53=0,AND($A53>0,'Energy and charging'!$B$43>($A53-1)*12,'Energy and charging'!$B$43<=$A53*12))),'Energy and charging'!$B$42,0),"n.a.") -> n.a. | I53: =IF(ISNUMBER(G53),G53+IF(AND('Energy and charging'!$C$60="Complete",IF('Energy and charging'!$C$33=0,$A53=0,AND($A53>0,'Energy and charging'!$C$33>($A53-1)*12,'Energy and charging'!$C$33<=$A53*12))),'Energy and charging'!$C$42,0)-IF(AND('Energy and charging'!$C$60="Complete",IF('Energy and charging'!$C$43=0,$A53=0,AND($A53>0,'Energy and charging'!$C$43>($A53-1)*12,'Energy and charging'!$C$43<=$A53*12))),'Energy and charging'!$C$42,0),"n.a.") -> n.a.
A54: 9 | B54: =IF(AND(COUNTIFS(Paths!$B$7:$B$406,0,Paths!$C$7:$C$406,1,Paths!$P$7:$P$406,"<>Complete")=0,COUNTIFS(Paths!$B$7:$B$406,0,Paths!$C$7:$C$406,1)=SUM('Fleet register'!$B$7:$B$106)),SUMIFS('Annual build'!$O$7:$O$4406,'Annual build'!$B$7:$B$4406,0,'Annual build'!$C$7:$C$4406,$A54),"n.a.") -> 108908.1 | C54: =IF(AND(COUNTIFS(Paths!$B$7:$B$406,1,Paths!$C$7:$C$406,1,Paths!$P$7:$P$406,"<>Complete")=0,COUNTIFS(Paths!$B$7:$B$406,1,Paths!$C$7:$C$406,1)=SUM('Fleet register'!$B$7:$B$106)),SUMIFS('Annual build'!$O$7:$O$4406,'Annual build'!$B$7:$B$4406,1,'Annual build'!$C$7:$C$4406,$A54),"n.a.") -> 108908.1 | D54: =IF(AND(COUNTIFS(Paths!$B$7:$B$406,2,Paths!$C$7:$C$406,1,Paths!$P$7:$P$406,"<>Complete")=0,COUNTIFS(Paths!$B$7:$B$406,2,Paths!$C$7:$C$406,1)=SUM('Fleet register'!$B$7:$B$106)),IF(ISNUMBER(H54),SUMIFS('Annual build'!$O$7:$O$4406,'Annual build'!$B$7:$B$4406,2,'Annual build'!$C$7:$C$4406,$A54)+H54,"n.a."),"n.a.") -> n.a. | E54: =IF(AND(COUNTIFS(Paths!$B$7:$B$406,3,Paths!$C$7:$C$406,1,Paths!$P$7:$P$406,"<>Complete")=0,COUNTIFS(Paths!$B$7:$B$406,3,Paths!$C$7:$C$406,1)=SUM('Fleet register'!$B$7:$B$106)),IF(ISNUMBER(I54),SUMIFS('Annual build'!$O$7:$O$4406,'Annual build'!$B$7:$B$4406,3,'Annual build'!$C$7:$C$4406,$A54)+I54,"n.a."),"n.a.") -> n.a. | F54: =IF('Energy and charging'!$B$60="No EV site",0,IF('Energy and charging'!$B$60="Public only",IF(IF('Energy and charging'!$B$33=0,$A54=0,AND($A54>0,'Energy and charging'!$B$33>($A54-1)*12,'Energy and charging'!$B$33<=$A54*12)),'Energy and charging'!$B$27,0)+MAX(0,MIN(9*12,120)-MAX(96,'Energy and charging'!$B$33))/12*'Energy and charging'!$B$29*(1+'Operating costs'!$B$53)^MAX(0,$A54-1),IF('Energy and charging'!$B$60="Complete",IF(IF('Energy and charging'!$B$33=0,$A54=0,AND($A54>0,'Energy and charging'!$B$33>($A54-1)*12,'Energy and charging'!$B$33<=$A54*12)),'Energy and charging'!$B$61,0)+MAX(0,MIN(9*12,120)-MAX(96,'Energy and charging'!$B$33))/12*'Energy and charging'!$B$62*(1+'Operating costs'!$B$53)^MAX(0,$A54-1)-IF(IF('Energy and charging'!$B$45=0,$A54=0,AND($A54>0,'Energy and charging'!$B$45>($A54-1)*12,'Energy and charging'!$B$45<=$A54*12)),'Energy and charging'!$B$44,0)+IF(IF('Energy and charging'!$B$38=0,$A54=0,AND($A54>0,'Energy and charging'!$B$38>($A54-1)*12,'Energy and charging'!$B$38<=$A54*12)),'Energy and charging'!$B$37,0)+IF(IF('Energy and charging'!$B$41=0,$A54=0,AND($A54>0,'Energy and charging'!$B$41>($A54-1)*12,'Energy and charging'!$B$41<=$A54*12)),'Energy and charging'!$B$16*'Energy and charging'!$B$40,0)+IF(IF('Energy and charging'!$B$33+'Energy and charging'!$B$34=0,$A54=0,AND($A54>0,'Energy and charging'!$B$33+'Energy and charging'!$B$34>($A54-1)*12,'Energy and charging'!$B$33+'Energy and charging'!$B$34<=$A54*12)),'Energy and charging'!$B$36,0)-IF($A54=10,'Energy and charging'!$B$35,0),"n.a."))) -> n.a. | G54: =IF('Energy and charging'!$C$60="No EV site",0,IF('Energy and charging'!$C$60="Public only",IF(IF('Energy and charging'!$C$33=0,$A54=0,AND($A54>0,'Energy and charging'!$C$33>($A54-1)*12,'Energy and charging'!$C$33<=$A54*12)),'Energy and charging'!$C$27,0)+MAX(0,MIN(9*12,120)-MAX(96,'Energy and charging'!$C$33))/12*'Energy and charging'!$C$29*(1+'Operating costs'!$B$53)^MAX(0,$A54-1),IF('Energy and charging'!$C$60="Complete",IF(IF('Energy and charging'!$C$33=0,$A54=0,AND($A54>0,'Energy and charging'!$C$33>($A54-1)*12,'Energy and charging'!$C$33<=$A54*12)),'Energy and charging'!$C$61,0)+MAX(0,MIN(9*12,120)-MAX(96,'Energy and charging'!$C$33))/12*'Energy and charging'!$C$62*(1+'Operating costs'!$B$53)^MAX(0,$A54-1)-IF(IF('Energy and charging'!$C$45=0,$A54=0,AND($A54>0,'Energy and charging'!$C$45>($A54-1)*12,'Energy and charging'!$C$45<=$A54*12)),'Energy and charging'!$C$44,0)+IF(IF('Energy and charging'!$C$38=0,$A54=0,AND($A54>0,'Energy and charging'!$C$38>($A54-1)*12,'Energy and charging'!$C$38<=$A54*12)),'Energy and charging'!$C$37,0)+IF(IF('Energy and charging'!$C$41=0,$A54=0,AND($A54>0,'Energy and charging'!$C$41>($A54-1)*12,'Energy and charging'!$C$41<=$A54*12)),'Energy and charging'!$C$16*'Energy and charging'!$C$40,0)+IF(IF('Energy and charging'!$C$33+'Energy and charging'!$C$34=0,$A54=0,AND($A54>0,'Energy and charging'!$C$33+'Energy and charging'!$C$34>($A54-1)*12,'Energy and charging'!$C$33+'Energy and charging'!$C$34<=$A54*12)),'Energy and charging'!$C$36,0)-IF($A54=10,'Energy and charging'!$C$35,0),"n.a."))) -> n.a. | H54: =IF(ISNUMBER(F54),F54+IF(AND('Energy and charging'!$B$60="Complete",IF('Energy and charging'!$B$33=0,$A54=0,AND($A54>0,'Energy and charging'!$B$33>($A54-1)*12,'Energy and charging'!$B$33<=$A54*12))),'Energy and charging'!$B$42,0)-IF(AND('Energy and charging'!$B$60="Complete",IF('Energy and charging'!$B$43=0,$A54=0,AND($A54>0,'Energy and charging'!$B$43>($A54-1)*12,'Energy and charging'!$B$43<=$A54*12))),'Energy and charging'!$B$42,0),"n.a.") -> n.a. | I54: =IF(ISNUMBER(G54),G54+IF(AND('Energy and charging'!$C$60="Complete",IF('Energy and charging'!$C$33=0,$A54=0,AND($A54>0,'Energy and charging'!$C$33>($A54-1)*12,'Energy and charging'!$C$33<=$A54*12))),'Energy and charging'!$C$42,0)-IF(AND('Energy and charging'!$C$60="Complete",IF('Energy and charging'!$C$43=0,$A54=0,AND($A54>0,'Energy and charging'!$C$43>($A54-1)*12,'Energy and charging'!$C$43<=$A54*12))),'Energy and charging'!$C$42,0),"n.a.") -> n.a.
A55: 10 | B55: =IF(AND(COUNTIFS(Paths!$B$7:$B$406,0,Paths!$C$7:$C$406,1,Paths!$P$7:$P$406,"<>Complete")=0,COUNTIFS(Paths!$B$7:$B$406,0,Paths!$C$7:$C$406,1)=SUM('Fleet register'!$B$7:$B$106)),SUMIFS('Annual build'!$O$7:$O$4406,'Annual build'!$B$7:$B$4406,0,'Annual build'!$C$7:$C$4406,$A55),"n.a.") -> -158391.9 | C55: =IF(AND(COUNTIFS(Paths!$B$7:$B$406,1,Paths!$C$7:$C$406,1,Paths!$P$7:$P$406,"<>Complete")=0,COUNTIFS(Paths!$B$7:$B$406,1,Paths!$C$7:$C$406,1)=SUM('Fleet register'!$B$7:$B$106)),SUMIFS('Annual build'!$O$7:$O$4406,'Annual build'!$B$7:$B$4406,1,'Annual build'!$C$7:$C$4406,$A55),"n.a.") -> 36908.1 | D55: =IF(AND(COUNTIFS(Paths!$B$7:$B$406,2,Paths!$C$7:$C$406,1,Paths!$P$7:$P$406,"<>Complete")=0,COUNTIFS(Paths!$B$7:$B$406,2,Paths!$C$7:$C$406,1)=SUM('Fleet register'!$B$7:$B$106)),IF(ISNUMBER(H55),SUMIFS('Annual build'!$O$7:$O$4406,'Annual build'!$B$7:$B$4406,2,'Annual build'!$C$7:$C$4406,$A55)+H55,"n.a."),"n.a.") -> n.a. | E55: =IF(AND(COUNTIFS(Paths!$B$7:$B$406,3,Paths!$C$7:$C$406,1,Paths!$P$7:$P$406,"<>Complete")=0,COUNTIFS(Paths!$B$7:$B$406,3,Paths!$C$7:$C$406,1)=SUM('Fleet register'!$B$7:$B$106)),IF(ISNUMBER(I55),SUMIFS('Annual build'!$O$7:$O$4406,'Annual build'!$B$7:$B$4406,3,'Annual build'!$C$7:$C$4406,$A55)+I55,"n.a."),"n.a.") -> n.a. | F55: =IF('Energy and charging'!$B$60="No EV site",0,IF('Energy and charging'!$B$60="Public only",IF(IF('Energy and charging'!$B$33=0,$A55=0,AND($A55>0,'Energy and charging'!$B$33>($A55-1)*12,'Energy and charging'!$B$33<=$A55*12)),'Energy and charging'!$B$27,0)+MAX(0,MIN(10*12,120)-MAX(108,'Energy and charging'!$B$33))/12*'Energy and charging'!$B$29*(1+'Operating costs'!$B$53)^MAX(0,$A55-1),IF('Energy and charging'!$B$60="Complete",IF(IF('Energy and charging'!$B$33=0,$A55=0,AND($A55>0,'Energy and charging'!$B$33>($A55-1)*12,'Energy and charging'!$B$33<=$A55*12)),'Energy and charging'!$B$61,0)+MAX(0,MIN(10*12,120)-MAX(108,'Energy and charging'!$B$33))/12*'Energy and charging'!$B$62*(1+'Operating costs'!$B$53)^MAX(0,$A55-1)-IF(IF('Energy and charging'!$B$45=0,$A55=0,AND($A55>0,'Energy and charging'!$B$45>($A55-1)*12,'Energy and charging'!$B$45<=$A55*12)),'Energy and charging'!$B$44,0)+IF(IF('Energy and charging'!$B$38=0,$A55=0,AND($A55>0,'Energy and charging'!$B$38>($A55-1)*12,'Energy and charging'!$B$38<=$A55*12)),'Energy and charging'!$B$37,0)+IF(IF('Energy and charging'!$B$41=0,$A55=0,AND($A55>0,'Energy and charging'!$B$41>($A55-1)*12,'Energy and charging'!$B$41<=$A55*12)),'Energy and charging'!$B$16*'Energy and charging'!$B$40,0)+IF(IF('Energy and charging'!$B$33+'Energy and charging'!$B$34=0,$A55=0,AND($A55>0,'Energy and charging'!$B$33+'Energy and charging'!$B$34>($A55-1)*12,'Energy and charging'!$B$33+'Energy and charging'!$B$34<=$A55*12)),'Energy and charging'!$B$36,0)-IF($A55=10,'Energy and charging'!$B$35,0),"n.a."))) -> n.a. | G55: =IF('Energy and charging'!$C$60="No EV site",0,IF('Energy and charging'!$C$60="Public only",IF(IF('Energy and charging'!$C$33=0,$A55=0,AND($A55>0,'Energy and charging'!$C$33>($A55-1)*12,'Energy and charging'!$C$33<=$A55*12)),'Energy and charging'!$C$27,0)+MAX(0,MIN(10*12,120)-MAX(108,'Energy and charging'!$C$33))/12*'Energy and charging'!$C$29*(1+'Operating costs'!$B$53)^MAX(0,$A55-1),IF('Energy and charging'!$C$60="Complete",IF(IF('Energy and charging'!$C$33=0,$A55=0,AND($A55>0,'Energy and charging'!$C$33>($A55-1)*12,'Energy and charging'!$C$33<=$A55*12)),'Energy and charging'!$C$61,0)+MAX(0,MIN(10*12,120)-MAX(108,'Energy and charging'!$C$33))/12*'Energy and charging'!$C$62*(1+'Operating costs'!$B$53)^MAX(0,$A55-1)-IF(IF('Energy and charging'!$C$45=0,$A55=0,AND($A55>0,'Energy and charging'!$C$45>($A55-1)*12,'Energy and charging'!$C$45<=$A55*12)),'Energy and charging'!$C$44,0)+IF(IF('Energy and charging'!$C$38=0,$A55=0,AND($A55>0,'Energy and charging'!$C$38>($A55-1)*12,'Energy and charging'!$C$38<=$A55*12)),'Energy and charging'!$C$37,0)+IF(IF('Energy and charging'!$C$41=0,$A55=0,AND($A55>0,'Energy and charging'!$C$41>($A55-1)*12,'Energy and charging'!$C$41<=$A55*12)),'Energy and charging'!$C$16*'Energy and charging'!$C$40,0)+IF(IF('Energy and charging'!$C$33+'Energy and charging'!$C$34=0,$A55=0,AND($A55>0,'Energy and charging'!$C$33+'Energy and charging'!$C$34>($A55-1)*12,'Energy and charging'!$C$33+'Energy and charging'!$C$34<=$A55*12)),'Energy and charging'!$C$36,0)-IF($A55=10,'Energy and charging'!$C$35,0),"n.a."))) -> n.a. | H55: =IF(ISNUMBER(F55),F55+IF(AND('Energy and charging'!$B$60="Complete",IF('Energy and charging'!$B$33=0,$A55=0,AND($A55>0,'Energy and charging'!$B$33>($A55-1)*12,'Energy and charging'!$B$33<=$A55*12))),'Energy and charging'!$B$42,0)-IF(AND('Energy and charging'!$B$60="Complete",IF('Energy and charging'!$B$43=0,$A55=0,AND($A55>0,'Energy and charging'!$B$43>($A55-1)*12,'Energy and charging'!$B$43<=$A55*12))),'Energy and charging'!$B$42,0),"n.a.") -> n.a. | I55: =IF(ISNUMBER(G55),G55+IF(AND('Energy and charging'!$C$60="Complete",IF('Energy and charging'!$C$33=0,$A55=0,AND($A55>0,'Energy and charging'!$C$33>($A55-1)*12,'Energy and charging'!$C$33<=$A55*12))),'Energy and charging'!$C$42,0)-IF(AND('Energy and charging'!$C$60="Complete",IF('Energy and charging'!$C$43=0,$A55=0,AND($A55>0,'Energy and charging'!$C$43>($A55-1)*12,'Energy and charging'!$C$43<=$A55*12))),'Energy and charging'!$C$42,0),"n.a.") -> n.a.
A58: Selected truck, direct vehicle costs only | B58: T001
A60: Selected truck metric | B60: Keep ICE | C60: New ICE now | D60: Plan A path | E60: Plan B path
A61: Vehicle-only economic TCO | B61: =IF(COUNTIFS(Paths!$A$7:$A$406,$B$58,Paths!$B$7:$B$406,0,Paths!$C$7:$C$406,1,Paths!$P$7:$P$406,"Complete")=1,SUMIFS('Annual build'!$N$7:$N$4406,'Annual build'!$A$7:$A$4406,$B$58,'Annual build'!$B$7:$B$4406,0),"n.a.") -> 355213.5 | C61: =IF(COUNTIFS(Paths!$A$7:$A$406,$B$58,Paths!$B$7:$B$406,1,Paths!$C$7:$C$406,1,Paths!$P$7:$P$406,"Complete")=1,SUMIFS('Annual build'!$N$7:$N$4406,'Annual build'!$A$7:$A$4406,$B$58,'Annual build'!$B$7:$B$4406,1),"n.a.") -> 350513.5 | D61: =IF(COUNTIFS(Paths!$A$7:$A$406,$B$58,Paths!$B$7:$B$406,2,Paths!$C$7:$C$406,1,Paths!$P$7:$P$406,"Complete")=1,SUMIFS('Annual build'!$N$7:$N$4406,'Annual build'!$A$7:$A$4406,$B$58,'Annual build'!$B$7:$B$4406,2),"n.a.") -> 320168.52 | E61: =IF(COUNTIFS(Paths!$A$7:$A$406,$B$58,Paths!$B$7:$B$406,3,Paths!$C$7:$C$406,1,Paths!$P$7:$P$406,"Complete")=1,SUMIFS('Annual build'!$N$7:$N$4406,'Annual build'!$A$7:$A$4406,$B$58,'Annual build'!$B$7:$B$4406,3),"n.a.") -> 320168.52
A62: Saving vs selected Keep ICE | B62: =IF(AND(ISNUMBER(B61),B61>0,ISNUMBER(B61)),(B61-B61)/B61,"n.a.") -> 0 | C62: =IF(AND(ISNUMBER(B61),B61>0,ISNUMBER(C61)),(B61-C61)/B61,"n.a.") -> 0.013231479 | D62: =IF(AND(ISNUMBER(B61),B61>0,ISNUMBER(D61)),(B61-D61)/B61,"n.a.") -> 0.098658933 | E62: =IF(AND(ISNUMBER(B61),B61>0,ISNUMBER(E61)),(B61-E61)/B61,"n.a.") -> 0.098658933
A63: Saving vs selected new ICE | B63: =IF(AND(ISNUMBER(C61),C61>0,ISNUMBER(B61)),(C61-B61)/C61,"n.a.") -> -0.013408899 | C63: =IF(AND(ISNUMBER(C61),C61>0,ISNUMBER(C61)),(C61-C61)/C61,"n.a.") -> 0 | D63: =IF(AND(ISNUMBER(C61),C61>0,ISNUMBER(D61)),(C61-D61)/C61,"n.a.") -> 0.086572942 | E63: =IF(AND(ISNUMBER(C61),C61>0,ISNUMBER(E61)),(C61-E61)/C61,"n.a.") -> 0.086572942
A64: Shared site cost is excluded above. Do not call this a standalone or allocated all-in truck saving.
A68: Alternative fleet benchmark: replace every included truck with new ICE now.
A70: Metric | B70: Keep ICE | C70: All-new ICE now | D70: Plan A | E70: Plan B
A71: Saving vs all-new ICE | B71: =IF(AND(ISNUMBER(C14),ISNUMBER(B14)),C14-B14,"n.a.") -> 21300 | C71: =IF(AND(ISNUMBER(C14),ISNUMBER(C14)),C14-C14,"n.a.") -> 0 | D71: =IF(AND(ISNUMBER(C14),ISNUMBER(D14)),C14-D14,"n.a.") -> n.a. | E71: =IF(AND(ISNUMBER(C14),ISNUMBER(E14)),C14-E14,"n.a.") -> n.a.
A72: Saving percentage vs new ICE | B72: =IF(AND(ISNUMBER(B71),ISNUMBER(C14),C14>0),B71/C14,"n.a.") -> 0.010127998 | C72: =IF(AND(ISNUMBER(C71),ISNUMBER(C14),C14>0),C71/C14,"n.a.") -> 0 | D72: =IF(AND(ISNUMBER(D71),ISNUMBER(C14),C14>0),D71/C14,"n.a.") -> n.a. | E72: =IF(AND(ISNUMBER(E71),ISNUMBER(C14),C14>0),E71/C14,"n.a.") -> n.a.
A73: 15% headroom vs new ICE | B73: =IF(AND(ISNUMBER(C14),ISNUMBER(B14)),0.85*C14-B14,"n.a.") -> -294162.15 | C73: =IF(AND(ISNUMBER(C14),ISNUMBER(C14)),0.85*C14-C14,"n.a.") -> -315462.15 | D73: =IF(AND(ISNUMBER(C14),ISNUMBER(D14)),0.85*C14-D14,"n.a.") -> n.a. | E73: =IF(AND(ISNUMBER(C14),ISNUMBER(E14)),0.85*C14-E14,"n.a.") -> n.a.

Sheet Fleet register
A2: 1. Enter each current truck and its work
A4: Include 1 = in this comparison. Up to 100 trucks. IDs must be unique. One duty is preserved in every plan.
A6: Truck ID | B6: Include 0/1 | C6: Duty / route | D6: Body | E6: Work km/day | F6: Days/year | G6: Peak route km | H6: Peak cargo kg | I6: Jobs/day | J6: COE months left | K6: Market value now | L6: Physical scrap | M6: COE paid basis | N6: COE term months | O6: Debt if sold now | P6: Fee when old truck sold | Q6: Evidence reference | R6: Vehicle age years | S6: Registration date
A7: T001 | B7: 1 | C7: Ambient demo | D7: Box | E7: 150 | F7: 300 | G7: 165 | H7: 1200 | I7: 24 | J7: 12 | K7: 24000 | L7: 10000 | M7: 60000 | N7: 120 | O7: 0 | P7: 0 | Q7: DEMO-1 | R7: 9
A8: T002 | B8: 1 | C8: Ambient demo | D8: Box | E8: 150 | F8: 300 | G8: 165 | H8: 1200 | I8: 24 | J8: 24 | K8: 30000 | L8: 10000 | M8: 60000 | N8: 120 | O8: 0 | P8: 0 | Q8: DEMO-2 | R8: 8
A9: T003 | B9: 1 | C9: Ambient demo | D9: Box | E9: 150 | F9: 300 | G9: 165 | H9: 1200 | I9: 24 | J9: 36 | K9: 36000 | L9: 10000 | M9: 60000 | N9: 120 | O9: 0 | P9: 0 | Q9: DEMO-3 | R9: 7
A10: T004 | B10: 1 | C10: Ambient demo | D10: Box | E10: 150 | F10: 300 | G10: 165 | H10: 1200 | I10: 24 | J10: 48 | K10: 42000 | L10: 10000 | M10: 60000 | N10: 120 | O10: 0 | P10: 0 | Q10: DEMO-4 | R10: 6
A11: T005 | B11: 1 | C11: Ambient demo | D11: Box | E11: 150 | F11: 300 | G11: 165 | H11: 1200 | I11: 24 | J11: 60 | K11: 48000 | L11: 10000 | M11: 60000 | N11: 120 | O11: 0 | P11: 0 | Q11: DEMO-5 | R11: 5
A12: T006 | B12: 1 | C12: Ambient demo | D12: Box | E12: 150 | F12: 300 | G12: 165 | H12: 1200 | I12: 24 | J12: 72 | K12: 54000 | L12: 10000 | M12: 60000 | N12: 120 | O12: 0 | P12: 0 | Q12: DEMO-6 | R12: 4
A13: T007 | B13: 0
A14: T008 | B14: 0
A15: T009 | B15: 0
A16: T010 | B16: 0
A17: T011 | B17: 0
A18: T012 | B18: 0
A19: T013 | B19: 0
A20: T014 | B20: 0
A21: T015 | B21: 0
A22: T016 | B22: 0
A23: T017 | B23: 0
A24: T018 | B24: 0
... A106: T100 | B106: 0

Sheet Replacement plan
A2: 2. Set replacements, quotes and future values
A4: Keep ICE = retire at expiry or earlier entered month, then buy ICE. New ICE / EV = replace at chosen month.
A6: Truck ID | B6: EV model | C6: New ICE all-in quote | D6: EV all-in override | E6: Usable battery kWh | F6: EV kWh/km override | G6: Energy basis | H6: Approved payload kg | I6: Body fits EV | J6: Depot average kW | K6: Depot AC/DC | L6: Public average kW | M6: Keep retire override | N6: Keep terminal at year 10 | O6: Plan A action | P6: A month override | Q6: A year-10 value | R6: Plan B action | S6: B month override | T6: B year-10 value | U6: A gross disposal override | V6: B gross disposal override | W6: Old ICE extra /year | X6: New ICE extra /year | Y6: EV extra /year | Z6: Manual EV grant total | AA6: Grant offset months | AB6: Grant eligibility checked | AC6: EV life months | AD6: ICE life months | AE6: Quote / value evidence | AF6: Record reference | AG6: Old ICE litres/km override | AH6: New ICE litres/km override | AI6: All-new ICE now year-10 value override
A7: T001 | B7: ChengLong L2EV | C7: 181000 | G7: Battery | I7: Unconfirmed | J7: 22 | K7: DC | L7: 48 | N7: 21300 | O7: EV | P7: 0 | Q7: 8000 | R7: EV | S7: 0 | T7: 8000 | W7: 0 | X7: 0 | Y7: 0 | Z7: 0 | AA7: 0 | AB7: No | AC7: 120 | AD7: 120 | AE7: Assumed | AF7: DEMO-1
A8: T002 | B8: ChengLong L2EV | C8: 181000 | G8: Battery | I8: Unconfirmed | J8: 22 | K8: DC | L8: 48 | N8: 30600 | O8: Keep ICE | Q8: 30600 | R8: EV | S8: 0 | T8: 8000 | W8: 0 | X8: 0 | Y8: 0 | Z8: 0 | AA8: 0 | AB8: No | AC8: 120 | AD8: 120 | AE8: Assumed | AF8: DEMO-2
A9: T003 | B9: ChengLong L2EV | C9: 181000 | G9: Battery | I9: Unconfirmed | J9: 22 | K9: DC | L9: 48 | N9: 39900 | O9: Keep ICE | Q9: 39900 | R9: EV | S9: 0 | T9: 8000 | W9: 0 | X9: 0 | Y9: 0 | Z9: 0 | AA9: 0 | AB9: No | AC9: 120 | AD9: 120 | AE9: Assumed | AF9: DEMO-3
A10: T004 | B10: ChengLong L2EV | C10: 181000 | G10: Battery | I10: Unconfirmed | J10: 22 | K10: DC | L10: 48 | N10: 49200 | O10: Keep ICE | Q10: 49200 | R10: Keep ICE | T10: 49200 | W10: 0 | X10: 0 | Y10: 0 | Z10: 0 | AA10: 0 | AB10: No | AC10: 120 | AD10: 120 | AE10: Assumed | AF10: DEMO-4
A11: T005 | B11: ChengLong L2EV | C11: 181000 | G11: Battery | I11: Unconfirmed | J11: 22 | K11: DC | L11: 48 | N11: 58500 | O11: Keep ICE | Q11: 58500 | R11: Keep ICE | T11: 58500 | W11: 0 | X11: 0 | Y11: 0 | Z11: 0 | AA11: 0 | AB11: No | AC11: 120 | AD11: 120 | AE11: Assumed | AF11: DEMO-5
A12: T006 | B12: ChengLong L2EV | C12: 181000 | G12: Battery | I12: Unconfirmed | J12: 22 | K12: DC | L12: 48 | N12: 67800 | O12: Keep ICE | Q12: 67800 | R12: Keep ICE | T12: 67800 | W12: 0 | X12: 0 | Y12: 0 | Z12: 0 | AA12: 0 | AB12: No | AC12: 120 | AD12: 120 | AE12: Assumed | AF12: DEMO-6
A13: T007 | B13: ChengLong L2EV | C13: 181000 | G13: Battery | I13: Unconfirmed | J13: 22 | K13: DC | L13: 48 | O13: Keep ICE | R13: Keep ICE | W13: 0 | X13: 0 | Y13: 0 | Z13: 0 | AA13: 0 | AB13: No | AC13: 120 | AD13: 120 | AE13: Assumed
A14: T008 | B14: ChengLong L2EV | C14: 181000 | G14: Battery | I14: Unconfirmed | J14: 22 | K14: DC | L14: 48 | O14: Keep ICE | R14: Keep ICE | W14: 0 | X14: 0 | Y14: 0 | Z14: 0 | AA14: 0 | AB14: No | AC14: 120 | AD14: 120 | AE14: Assumed
A15: T009 | B15: ChengLong L2EV | C15: 181000 | G15: Battery | I15: Unconfirmed | J15: 22 | K15: DC | L15: 48 | O15: Keep ICE | R15: Keep ICE | W15: 0 | X15: 0 | Y15: 0 | Z15: 0 | AA15: 0 | AB15: No | AC15: 120 | AD15: 120 | AE15: Assumed
A16: T010 | B16: ChengLong L2EV | C16: 181000 | G16: Battery | I16: Unconfirmed | J16: 22 | K16: DC | L16: 48 | O16: Keep ICE | R16: Keep ICE | W16: 0 | X16: 0 | Y16: 0 | Z16: 0 | AA16: 0 | AB16: No | AC16: 120 | AD16: 120 | AE16: Assumed
A17: T011 | B17: ChengLong L2EV | C17: 181000 | G17: Battery | I17: Unconfirmed | J17: 22 | K17: DC | L17: 48 | O17: Keep ICE | R17: Keep ICE | W17: 0 | X17: 0 | Y17: 0 | Z17: 0 | AA17: 0 | AB17: No | AC17: 120 | AD17: 120 | AE17: Assumed
A18: T012 | B18: ChengLong L2EV | C18: 181000 | G18: Battery | I18: Unconfirmed | J18: 22 | K18: DC | L18: 48 | O18: Keep ICE | R18: Keep ICE | W18: 0 | X18: 0 | Y18: 0 | Z18: 0 | AA18: 0 | AB18: No | AC18: 120 | AD18: 120 | AE18: Assumed
A19: T013 | B19: ChengLong L2EV | C19: 181000 | G19: Battery | I19: Unconfirmed | J19: 22 | K19: DC | L19: 48 | O19: Keep ICE | R19: Keep ICE | W19: 0 | X19: 0 | Y19: 0 | Z19: 0 | AA19: 0 | AB19: No | AC19: 120 | AD19: 120 | AE19: Assumed
A20: T014 | B20: ChengLong L2EV | C20: 181000 | G20: Battery | I20: Unconfirmed | J20: 22 | K20: DC | L20: 48 | O20: Keep ICE | R20: Keep ICE | W20: 0 | X20: 0 | Y20: 0 | Z20: 0 | AA20: 0 | AB20: No | AC20: 120 | AD20: 120 | AE20: Assumed
A21: T015 | B21: ChengLong L2EV | C21: 181000 | G21: Battery | I21: Unconfirmed | J21: 22 | K21: DC | L21: 48 | O21: Keep ICE | R21: Keep ICE | W21: 0 | X21: 0 | Y21: 0 | Z21: 0 | AA21: 0 | AB21: No | AC21: 120 | AD21: 120 | AE21: Assumed
A22: T016 | B22: ChengLong L2EV | C22: 181000 | G22: Battery | I22: Unconfirmed | J22: 22 | K22: DC | L22: 48 | O22: Keep ICE | R22: Keep ICE | W22: 0 | X22: 0 | Y22: 0 | Z22: 0 | AA22: 0 | AB22: No | AC22: 120 | AD22: 120 | AE22: Assumed
A23: T017 | B23: ChengLong L2EV | C23: 181000 | G23: Battery | I23: Unconfirmed | J23: 22 | K23: DC | L23: 48 | O23: Keep ICE | R23: Keep ICE | W23: 0 | X23: 0 | Y23: 0 | Z23: 0 | AA23: 0 | AB23: No | AC23: 120 | AD23: 120 | AE23: Assumed
A24: T018 | B24: ChengLong L2EV | C24: 181000 | G24: Battery | I24: Unconfirmed | J24: 22 | K24: DC | L24: 48 | O24: Keep ICE | R24: Keep ICE | W24: 0 | X24: 0 | Y24: 0 | Z24: 0 | AA24: 0 | AB24: No | AC24: 120 | AD24: 120 | AE24: Assumed
... A106: T100 | B106: ChengLong L2EV | C106: 181000 | G106: Battery | I106: Unconfirmed | J106: 22 | K106: DC | L106: 48 | O106: Keep ICE | R106: Keep ICE | W106: 0 | X106: 0 | Y106: 0 | Z106: 0 | AA106: 0 | AB106: No | AC106: 120 | AD106: 120 | AE106: Assumed

Sheet Energy and charging
A2: 3. Enter prices and each plan's charging arrangement
A4: Amber inputs. Blank site work = unknown, not zero. Costs apply once per plan, not once per truck.
A6: Input / cost item | B6: Plan A | C6: Plan B | D6: Unit | E6: Scope / evidence
A7: Commercial diesel | B7: 2 | C7: 2 | D7: SGD/litre | E7: Inherited assumption; enter net fleet invoice
A8: Public diesel | B8: 3 | C8: 3 | D8: SGD/litre | E8: Inherited assumption; enter net public pump price
A9: Commercial diesel share | B9: 1 | C9: 1 | D9: litres share | E9: Commercial purchase share
A10: Depot electricity | B10: 0.3478 | C10: 0.3478 | D10: SGD/grid kWh | E10: Inherited assumption; not current commercial offer
A11: Public charging | B11: 0.85 | C11: 0.85 | D11: SGD/grid kWh | E11: Inherited assumption; verify truck access
A12: Public electricity share | B12: 0.2 | C12: 0.2 | D12: grid-kWh share | E12: Energy share, not visits share
A13: Charging-site arrangement | B13: Existing depot | C13: Existing depot | D13: site | E13: Existing depot / New rented site / Public only / Operator funded
A14: Site location | B14: Unspecified | C14: Unspecified | D14: region | E14: All Singapore areas considered; does not select a rent quote
A15: Charger type | B15: DC60 | C15: DC60 | D15: type | E15: DC60 / DC120 / AC22 / Other
A16: Installed chargers | B16: 1 | C16: 2 | D16: units | E16: Actual installed hardware, not EV count
A17: Usable truck plugs | B17: 2 | C17: 4 | D17: usable plugs | E17: Actual simultaneous truck positions; sharing still limited by site power
A18: Charger equipment price | B18: 23800 | C18: 23800 | D18: SGD/charger | E18: E01 equipment-only advertised before GST/installation
A19: Local EV distribution board | D19: SGD/charger | E19: Local EV distribution equipment; itemised quote required
A20: Licensed electrical worker | D20: SGD/charger | E20: Site/project LEW; quote required
A21: Local cable and installation | D21: SGD/charger | E21: Local cabling/install only; quote required
A22: Charger registration | B22: 375 | C22: 375 | D22: SGD/charger | E22: L01 no GST; current 23-150kW fee only through Mar2027
A23: Major electrical upgrade | D23: SGD/site | E23: Switchboard/transformer upgrade; NOT automatic EHVCG eligible cost
A24: General civil work | D24: SGD/site | E24: Separate paving/drainage/site infrastructure; quote required
A25: SP connection fee | D25: SGD/site | E25: SP incremental connection quote; NOT automatic S$16,700
A26: Other site preparation | D26: SGD/site | E26: Land preparation, permits, professional fees; no duplicate cable work
A27: Training and transition | B27: 1000 | C27: 1000 | D27: SGD/site | E27: Inherited training/setup assumption
A28: Extra monthly space rent | D28: SGD/site/month | E28: Incremental EV space only. Existing common factory rent excluded
A29: Other fixed annual fees | D29: SGD/site/year | E29: Network/IT/insurance/standing fees not already in kWh price
A30: Annual demand charge | D30: SGD/site/year | E30: Only actual tariff demand charges. Do not assume all LT sites pay HT charges
A31: Lost space value /year | D31: SGD/site/year | E31: Only evidenced lost bay/use value, not duplicate rent
A32: Maintenance per charger | B32: 1180 | C32: 1180 | D32: SGD/charger/year | E32: E05 advertised DC maintenance; check service and inspections included
A33: Installation month | B33: 0 | C33: 0 | D33: analysis month | E33: Ready before first depot EV operation
A34: Site rights after install | B34: 120 | C34: 120 | D34: months after installation | E34: Confirmed rights, not merely parking permit
A35: Year-10 equipment recovery | B35: 0 | C35: 0 | D35: SGD/site at year 10 | E35: Explicit equipment terminal forecast
A36: Lease-end restoration | B36: 0 | C36: 0 | D36: SGD/site | E36: Lease-end restoration quote or evidenced zero
A37: Replacement-site cost | B37: 0 | C37: 0 | D37: SGD/site | E37: Replacement site total, no assumed free land
A38: Replacement-site month | B38: 60 | C38: 60 | D38: analysis month | E38: Chargers/site change within horizon
A39: Next site confirmed | B39: No | C39: No | D39: Yes/No | E39: Needed if current site rights end before horizon
A40: Charger replacement cost | B40: 0 | C40: 0 | D40: SGD/charger | E40: Scheduled replacement, exclude duplicate maintenance
A41: Charger replacement month | B41: 60 | C41: 60 | D41: analysis month | E41: Scheduled charger replacement
A42: Refundable deposit | B42: 0 | C42: 0 | D42: SGD/site | E42: Refundable funding tie-up, not full economic expense
A43: Deposit refund month | B43: 120 | C43: 120 | D43: analysis month | E43: Enter refund date; beyond horizon remains cash tied up
A44: Approved charger grant | B44: 0 | C44: 0 | D44: SGD/site | E44: Only written grant quantum. Budget ceiling below is NOT a grant award
A45: Grant receipt month | B45: 12 | C45: 12 | D45: analysis month | E45: Reimbursement date, not upfront discount
A46: Award checked | B46: No | C46: No | D46: Yes/No | E46: Written award and component caps checked
A47: Approved funded chargers | B47: 0 | C47: 0 | D47: eligible units | E47: Approved units, <=3 and <=eligible new eHVs at this site
A48: Accepted cost per charger | D48: SGD/eligible charger | E48: LTA-accepted eligible cost after component caps; blank ceiling unavailable
A49: Site quote basis | B49: Gross | C49: Gross | D49: Gross/Net | E49: Site cost before approved grant
A50: Net site power | B50: 44 | C50: 44 | D50: kW | E50: Net usable grid input after other site loads
A51: Charging window | B51: 10 | C51: 10 | D51: hours | E51: Uninterrupted charging window
A52: Site permission and access | B52: Unconfirmed | C52: Unconfirmed | D52: Yes/No/Unconfirmed | E52: Landlord/JTC, physical bays, connector, cable and permissions
A53: Shared schedule confirmed | B53: No | C53: No | D53: Yes/No | E53: Observed fleet arrivals, departures and shared-power schedule
A54: Site cost evidence | B54: Unknown | C54: Unknown | D54: Unknown/Assumed/Quoted/Verified | E54: Scope-complete values are not a site survey
A55: Public truck access | B55: Unconfirmed | C55: Unconfirmed | D55: Yes/No/Unconfirmed | E55: Truck-compatible charger and availability evidence
A56: Charger rated input power | B56: 60 | C56: 60 | D56: kW/charger | E56: Update price, power, maintenance and fee when changing charger type.
A59: Calculated site result | B59: Plan A | C59: Plan B | D59: Unit | E59: Rule
A60: Input completeness | B60: =IF('Energy and charging'!$B$68=0,"No EV site",IF('Energy and charging'!$B$12=1,IF(AND(ISNUMBER('Energy and charging'!$B$27),'Energy and charging'!$B$27>=0,ISNUMBER('Energy and charging'!$B$29),'Energy and charging'!$B$29>=0,ISNUMBER('Energy and charging'!$B$33),'Energy and charging'!$B$33>=0,'Energy and charging'!$B$33<=120,'Energy and charging'!$B$33=INT('Energy and charging'!$B$33)),"Public only","Missing public fixed cost"),IF(NOT(AND(ISNUMBER('Energy and charging'!$B$18),ISNUMBER('Energy and charging'!$B$16),ISNUMBER('Energy and charging'!$B$17),ISNUMBER('Energy and charging'!$B$19),ISNUMBER('Energy and charging'!$B$20),ISNUMBER('Energy and charging'!$B$21),ISNUMBER('Energy and charging'!$B$22),ISNUMBER('Energy and charging'!$B$23),ISNUMBER('Energy and charging'!$B$24),ISNUMBER('Energy and charging'!$B$25),ISNUMBER('Energy and charging'!$B$26),ISNUMBER('Energy and charging'!$B$27),ISNUMBER('Energy and charging'!$B$28),ISNUMBER('Energy and charging'!$B$29),ISNUMBER('Energy and charging'!$B$30),ISNUMBER('Energy and charging'!$B$31),ISNUMBER('Energy and charging'!$B$32),ISNUMBER('Energy and charging'!$B$33),ISNUMBER('Energy and charging'!$B$34),ISNUMBER('Energy and charging'!$B$35),ISNUMBER('Energy and charging'!$B$36),ISNUMBER('Energy and charging'!$B$37),ISNUMBER('Energy and charging'!$B$38),ISNUMBER('Energy and charging'!$B$40),ISNUMBER('Energy and charging'!$B$41),ISNUMBER('Energy and charging'!$B$42),ISNUMBER('Energy and charging'!$B$43),ISNUMBER('Energy and charging'!$B$44),ISNUMBER('Energy and charging'!$B$45),ISNUMBER('Energy and charging'!$B$47),ISNUMBER('Energy and charging'!$B$50),ISNUMBER('Energy and charging'!$B$51))),"Missing site quote",IF(OR(MIN('Energy and charging'!$B$18,'Energy and charging'!$B$16,'Energy and charging'!$B$17,'Energy and charging'!$B$19,'Energy and charging'!$B$20,'Energy and charging'!$B$21,'Energy and charging'!$B$22,'Energy and charging'!$B$23,'Energy and charging'!$B$24,'Energy and charging'!$B$25,'Energy and charging'!$B$26,'Energy and charging'!$B$27,'Energy and charging'!$B$28,'Energy and charging'!$B$29,'Energy and charging'!$B$30,'Energy and charging'!$B$31,'Energy and charging'!$B$32,'Energy and charging'!$B$33,'Energy and charging'!$B$34,'Energy and charging'!$B$35,'Energy and charging'!$B$36,'Energy and charging'!$B$37,'Energy and charging'!$B$38,'Energy and charging'!$B$40,'Energy and charging'!$B$41,'Energy and charging'!$B$42,'Energy and charging'!$B$43,'Energy and charging'!$B$44,'Energy and charging'!$B$45,'Energy and charging'!$B$47,'Energy and charging'!$B$50,'Energy and charging'!$B$51)<0,'Energy and charging'!$B$16<1,'Energy and charging'!$B$17<1,'Energy and charging'!$B$33>120,'Energy and charging'!$B$33<>INT('Energy and charging'!$B$33),'Energy and charging'!$B$34<=0,'Energy and charging'!$B$51<=0,'Energy and charging'!$B$12<0,'Energy and charging'!$B$12>1,AND('Energy and charging'!$B$44>0,OR(NOT(ISNUMBER('Energy and charging'!$B$63)),'Energy and charging'!$B$44>'Energy and charging'!$B$63,'Energy and charging'!$B$47>MIN(3,'Energy and charging'!$B$16,COUNTIFS(Paths!$B$7:$B$406,2,Paths!$C$7:$C$406,1,Paths!$D$7:$D$406,"EV",Paths!$E$7:$E$406,"<120",Paths!$AL$7:$AL$406,">3500",Paths!$AK$7:$AK$406,">="&DATE(2026,1,1),Paths!$AK$7:$AK$406,"<="&DATE(2028,12,31))),'Energy and charging'!$B$15="AC22",'Energy and charging'!$B$56<50,'Energy and charging'!$B$45<'Energy and charging'!$B$33)),AND('Energy and charging'!$B$44>0,OR('Energy and charging'!$B$46<>"Yes",'Energy and charging'!$B$49<>"Gross"))),"Review site inputs",IF(OR(NOT(ISNUMBER('Energy and charging'!$B$56)),'Energy and charging'!$B$56<=0,'Energy and charging'!$B$16<>INT('Energy and charging'!$B$16),'Energy and charging'!$B$17<>INT('Energy and charging'!$B$17),'Energy and charging'!$B$34<>INT('Energy and charging'!$B$34),'Energy and charging'!$B$43<'Energy and charging'!$B$33,'Energy and charging'!$B$38<'Energy and charging'!$B$33,'Energy and charging'!$B$41<'Energy and charging'!$B$33,AND('Energy and charging'!$B$44>0,'Energy and charging'!$B$34<36)),"Review site inputs","Complete"))))) -> Missing site quote | C60: =IF('Energy and charging'!$C$68=0,"No EV site",IF('Energy and charging'!$C$12=1,IF(AND(ISNUMBER('Energy and charging'!$C$27),'Energy and charging'!$C$27>=0,ISNUMBER('Energy and charging'!$C$29),'Energy and charging'!$C$29>=0,ISNUMBER('Energy and charging'!$C$33),'Energy and charging'!$C$33>=0,'Energy and charging'!$C$33<=120,'Energy and charging'!$C$33=INT('Energy and charging'!$C$33)),"Public only","Missing public fixed cost"),IF(NOT(AND(ISNUMBER('Energy and charging'!$C$18),ISNUMBER('Energy and charging'!$C$16),ISNUMBER('Energy and charging'!$C$17),ISNUMBER('Energy and charging'!$C$19),ISNUMBER('Energy and charging'!$C$20),ISNUMBER('Energy and charging'!$C$21),ISNUMBER('Energy and charging'!$C$22),ISNUMBER('Energy and charging'!$C$23),ISNUMBER('Energy and charging'!$C$24),ISNUMBER('Energy and charging'!$C$25),ISNUMBER('Energy and charging'!$C$26),ISNUMBER('Energy and charging'!$C$27),ISNUMBER('Energy and charging'!$C$28),ISNUMBER('Energy and charging'!$C$29),ISNUMBER('Energy and charging'!$C$30),ISNUMBER('Energy and charging'!$C$31),ISNUMBER('Energy and charging'!$C$32),ISNUMBER('Energy and charging'!$C$33),ISNUMBER('Energy and charging'!$C$34),ISNUMBER('Energy and charging'!$C$35),ISNUMBER('Energy and charging'!$C$36),ISNUMBER('Energy and charging'!$C$37),ISNUMBER('Energy and charging'!$C$38),ISNUMBER('Energy and charging'!$C$40),ISNUMBER('Energy and charging'!$C$41),ISNUMBER('Energy and charging'!$C$42),ISNUMBER('Energy and charging'!$C$43),ISNUMBER('Energy and charging'!$C$44),ISNUMBER('Energy and charging'!$C$45),ISNUMBER('Energy and charging'!$C$47),ISNUMBER('Energy and charging'!$C$50),ISNUMBER('Energy and charging'!$C$51))),"Missing site quote",IF(OR(MIN('Energy and charging'!$C$18,'Energy and charging'!$C$16,'Energy and charging'!$C$17,'Energy and charging'!$C$19,'Energy and charging'!$C$20,'Energy and charging'!$C$21,'Energy and charging'!$C$22,'Energy and charging'!$C$23,'Energy and charging'!$C$24,'Energy and charging'!$C$25,'Energy and charging'!$C$26,'Energy and charging'!$C$27,'Energy and charging'!$C$28,'Energy and charging'!$C$29,'Energy and charging'!$C$30,'Energy and charging'!$C$31,'Energy and charging'!$C$32,'Energy and charging'!$C$33,'Energy and charging'!$C$34,'Energy and charging'!$C$35,'Energy and charging'!$C$36,'Energy and charging'!$C$37,'Energy and charging'!$C$38,'Energy and charging'!$C$40,'Energy and charging'!$C$41,'Energy and charging'!$C$42,'Energy and charging'!$C$43,'Energy and charging'!$C$44,'Energy and charging'!$C$45,'Energy and charging'!$C$47,'Energy and charging'!$C$50,'Energy and charging'!$C$51)<0,'Energy and charging'!$C$16<1,'Energy and charging'!$C$17<1,'Energy and charging'!$C$33>120,'Energy and charging'!$C$33<>INT('Energy and charging'!$C$33),'Energy and charging'!$C$34<=0,'Energy and charging'!$C$51<=0,'Energy and charging'!$C$12<0,'Energy and charging'!$C$12>1,AND('Energy and charging'!$C$44>0,OR(NOT(ISNUMBER('Energy and charging'!$C$63)),'Energy and charging'!$C$44>'Energy and charging'!$C$63,'Energy and charging'!$C$47>MIN(3,'Energy and charging'!$C$16,COUNTIFS(Paths!$B$7:$B$406,3,Paths!$C$7:$C$406,1,Paths!$D$7:$D$406,"EV",Paths!$E$7:$E$406,"<120",Paths!$AL$7:$AL$406,">3500",Paths!$AK$7:$AK$406,">="&DATE(2026,1,1),Paths!$AK$7:$AK$406,"<="&DATE(2028,12,31))),'Energy and charging'!$C$15="AC22",'Energy and charging'!$C$56<50,'Energy and charging'!$C$45<'Energy and charging'!$C$33)),AND('Energy and charging'!$C$44>0,OR('Energy and charging'!$C$46<>"Yes",'Energy and charging'!$C$49<>"Gross"))),"Review site inputs",IF(OR(NOT(ISNUMBER('Energy and charging'!$C$56)),'Energy and charging'!$C$56<=0,'Energy and charging'!$C$16<>INT('Energy and charging'!$C$16),'Energy and charging'!$C$17<>INT('Energy and charging'!$C$17),'Energy and charging'!$C$34<>INT('Energy and charging'!$C$34),'Energy and charging'!$C$43<'Energy and charging'!$C$33,'Energy and charging'!$C$38<'Energy and charging'!$C$33,'Energy and charging'!$C$41<'Energy and charging'!$C$33,AND('Energy and charging'!$C$44>0,'Energy and charging'!$C$34<36)),"Review site inputs","Complete"))))) -> Missing site quote | D60: status | E60: Required unknown site costs block all-in totals.
A61: Gross initial site cost | B61: =IF('Energy and charging'!$B$60="No EV site",0,IF('Energy and charging'!$B$60="Public only",'Energy and charging'!$B$27,IF('Energy and charging'!$B$60="Complete",'Energy and charging'!$B$16*SUM('Energy and charging'!$B$18,'Energy and charging'!$B$19,'Energy and charging'!$B$20,'Energy and charging'!$B$21,'Energy and charging'!$B$22)+SUM('Energy and charging'!$B$23,'Energy and charging'!$B$24,'Energy and charging'!$B$25,'Energy and charging'!$B$26,'Energy and charging'!$B$27),"n.a."))) -> n.a. | C61: =IF('Energy and charging'!$C$60="No EV site",0,IF('Energy and charging'!$C$60="Public only",'Energy and charging'!$C$27,IF('Energy and charging'!$C$60="Complete",'Energy and charging'!$C$16*SUM('Energy and charging'!$C$18,'Energy and charging'!$C$19,'Energy and charging'!$C$20,'Energy and charging'!$C$21,'Energy and charging'!$C$22)+SUM('Energy and charging'!$C$23,'Energy and charging'!$C$24,'Energy and charging'!$C$25,'Energy and charging'!$C$26,'Energy and charging'!$C$27),"n.a."))) -> n.a. | D61: SGD/site | E61: Actual charger count plus shared site preparation.
A62: Annual site cost | B62: =IF('Energy and charging'!$B$60="No EV site",0,IF('Energy and charging'!$B$60="Public only",'Energy and charging'!$B$29,IF('Energy and charging'!$B$60="Complete",12*'Energy and charging'!$B$28+SUM('Energy and charging'!$B$29,'Energy and charging'!$B$30,'Energy and charging'!$B$31)+'Energy and charging'!$B$16*'Energy and charging'!$B$32,"n.a."))) -> n.a. | C62: =IF('Energy and charging'!$C$60="No EV site",0,IF('Energy and charging'!$C$60="Public only",'Energy and charging'!$C$29,IF('Energy and charging'!$C$60="Complete",12*'Energy and charging'!$C$28+SUM('Energy and charging'!$C$29,'Energy and charging'!$C$30,'Energy and charging'!$C$31)+'Energy and charging'!$C$16*'Energy and charging'!$C$32,"n.a."))) -> n.a. | D62: SGD/site/year | E62: Incremental rent, fixed charges and maintenance.
A63: Grant budget ceiling only | B63: =IF('Energy and charging'!$B$47=0,0,IF(ISNUMBER('Energy and charging'!$B$48),MIN(30000,0.5*'Energy and charging'!$B$48)*MIN(3,'Energy and charging'!$B$47),"n.a.")) -> 0 | C63: =IF('Energy and charging'!$C$47=0,0,IF(ISNUMBER('Energy and charging'!$C$48),MIN(30000,0.5*'Energy and charging'!$C$48)*MIN(3,'Energy and charging'!$C$47),"n.a.")) -> 0 | D63: SGD/site | E63: Illustrative eligible-cost ceiling. Not an entitlement.
A64: Initial cost less award | B64: =IF(ISNUMBER('Energy and charging'!$B$61),'Energy and charging'!$B$61-IF('Energy and charging'!$B$60="Complete",'Energy and charging'!$B$44,0),"n.a.") -> n.a. | C64: =IF(ISNUMBER('Energy and charging'!$C$61),'Energy and charging'!$C$61-IF('Energy and charging'!$C$60="Complete",'Energy and charging'!$C$44,0),"n.a.") -> n.a. | D64: SGD/site | E64: Approved reimbursement may arrive later than installation.
A65: Peak depot energy | B65: =SUMIFS(Paths!$Y$7:$Y$406,Paths!$B$7:$B$406,2,Paths!$C$7:$C$406,1) -> 41.576817 | C65: =SUMIFS(Paths!$Y$7:$Y$406,Paths!$B$7:$B$406,3,Paths!$C$7:$C$406,1) -> 124.73045 | D65: grid kWh/day | E65: Sum of entered peak-day depot energy.
A66: Total truck charging hours | B66: =SUMIFS(Paths!$Z$7:$Z$406,Paths!$B$7:$B$406,2,Paths!$C$7:$C$406,1) -> 1.8898553 | C66: =SUMIFS(Paths!$Z$7:$Z$406,Paths!$B$7:$B$406,3,Paths!$C$7:$C$406,1) -> 5.6695659 | D66: truck hours/day | E66: Sum of charging time; also limited by shared site power.
A67: Access and capacity check | B67: =IF('Energy and charging'!$B$68=0,"No EV",IF('Energy and charging'!$B$12=1,IF('Energy and charging'!$B$55="Yes","Public access entered","Public access unconfirmed"),IF('Energy and charging'!$B$60<>"Complete",'Energy and charging'!$B$60,IF(OR('Energy and charging'!$B$65>MIN('Energy and charging'!$B$50,'Energy and charging'!$B$16*'Energy and charging'!$B$56)*'Energy and charging'!$B$51,'Energy and charging'!$B$66>'Energy and charging'!$B$17*'Energy and charging'!$B$51,SUMPRODUCT(--(Paths!$B$7:$B$406=2),--(Paths!$C$7:$C$406=1),--(Paths!$D$7:$D$406="EV"),--(Paths!$E$7:$E$406<120),--(Paths!$E$7:$E$406<'Energy and charging'!$B$33))>0,AND('Energy and charging'!$B$15="AC22",COUNTIFS(Paths!$B$7:$B$406,2,Paths!$C$7:$C$406,1,Paths!$D$7:$D$406,"EV",Paths!$E$7:$E$406,"<120",Paths!$AM$7:$AM$406,"<>AC")>0),AND(OR('Energy and charging'!$B$15="DC60",'Energy and charging'!$B$15="DC120"),COUNTIFS(Paths!$B$7:$B$406,2,Paths!$C$7:$C$406,1,Paths!$D$7:$D$406,"EV",Paths!$E$7:$E$406,"<120",Paths!$AM$7:$AM$406,"<>DC")>0),AND('Energy and charging'!$B$33+'Energy and charging'!$B$34<120,'Energy and charging'!$B$39<>"Yes")),"Site timing/power fails",IF(OR('Energy and charging'!$B$52<>"Yes",'Energy and charging'!$B$53<>"Yes",'Energy and charging'!$B$54<>"Verified"),"Site unverified","Within entered site limits"))))) -> Missing site quote | C67: =IF('Energy and charging'!$C$68=0,"No EV",IF('Energy and charging'!$C$12=1,IF('Energy and charging'!$C$55="Yes","Public access entered","Public access unconfirmed"),IF('Energy and charging'!$C$60<>"Complete",'Energy and charging'!$C$60,IF(OR('Energy and charging'!$C$65>MIN('Energy and charging'!$C$50,'Energy and charging'!$C$16*'Energy and charging'!$C$56)*'Energy and charging'!$C$51,'Energy and charging'!$C$66>'Energy and charging'!$C$17*'Energy and charging'!$C$51,SUMPRODUCT(--(Paths!$B$7:$B$406=3),--(Paths!$C$7:$C$406=1),--(Paths!$D$7:$D$406="EV"),--(Paths!$E$7:$E$406<120),--(Paths!$E$7:$E$406<'Energy and charging'!$C$33))>0,AND('Energy and charging'!$C$15="AC22",COUNTIFS(Paths!$B$7:$B$406,3,Paths!$C$7:$C$406,1,Paths!$D$7:$D$406,"EV",Paths!$E$7:$E$406,"<120",Paths!$AM$7:$AM$406,"<>AC")>0),AND(OR('Energy and charging'!$C$15="DC60",'Energy and charging'!$C$15="DC120"),COUNTIFS(Paths!$B$7:$B$406,3,Paths!$C$7:$C$406,1,Paths!$D$7:$D$406,"EV",Paths!$E$7:$E$406,"<120",Paths!$AM$7:$AM$406,"<>DC")>0),AND('Energy and charging'!$C$33+'Energy and charging'!$C$34<120,'Energy and charging'!$C$39<>"Yes")),"Site timing/power fails",IF(OR('Energy and charging'!$C$52<>"Yes",'Energy and charging'!$C$53<>"Yes",'Energy and charging'!$C$54<>"Verified"),"Site unverified","Within entered site limits"))))) -> Missing site quote | D67: status | E67: Coarse site gate, not a dispatch scheduling solution.
A68: EVs using arrangement | B68: =COUNTIFS(Paths!$B$7:$B$406,2,Paths!$C$7:$C$406,1,Paths!$D$7:$D$406,"EV",Paths!$E$7:$E$406,"<120") -> 1 | C68: =COUNTIFS(Paths!$B$7:$B$406,3,Paths!$C$7:$C$406,1,Paths!$D$7:$D$406,"EV",Paths!$E$7:$E$406,"<120") -> 3 | D68: trucks | E68: EV paths active before month 120.
A72: Evidence ID | B72: Item / location | C72: Value | D72: Unit / GST basis | E72: Applicability and limits | F72: Source URL
A73: E01 | B73: DC equipment 60 kW | C73: 23800 | D73: SGD/charger, excl GST and installation | E73: Supplier advertised price, not binding quote | F73: https://www.electric.com.sg/ev-charger/
A74: E02 | B74: DC equipment 120 kW | C74: 29800 | D74: SGD/charger, excl GST and installation | E74: Supplier advertised price, not binding quote | F74: https://www.electric.com.sg/ev-charger/
A75: E03 | B75: AC equipment 22 kW minimum | C75: 1800 | D75: SGD/charger, excl GST and installation | E75: Range lower end only | F75: https://www.electric.com.sg/ev-charger/
A76: E04 | B76: AC equipment 22 kW maximum | C76: 3500 | D76: SGD/charger, excl GST and installation | E76: Range upper end only; midpoint is not a quote | F76: https://www.electric.com.sg/ev-charger/
A77: E05 | B77: DC private-use maintenance | C77: 1180 | D77: SGD/charger/year, excl GST | E77: Check inspection and service inclusions | F77: https://www.electric.com.sg/ev-charger/
A78: E06 | B78: AC non-restricted maintenance | C78: 380 | D78: SGD/charger/year, excl GST | E78: Check inspection and service inclusions | F78: https://www.electric.com.sg/ev-charger/
A79: L01 | B79: Registration 23-150 kW | C79: 375 | D79: SGD/charger, no GST | E79: Non-restricted statutory classification; fee valid through 31-Mar-2027 | F79: https://www.lta.gov.sg/content/ltagov/en/industry_innovations/technologies/electric_vehicles/regulating_safety_of_ev_chargers/registration-of-ev-chargers.html
A80: S01 | B80: LT connection 76-140 kVA | C80: 16700 | D80: SGD, excl GST | E80: Standard new underground shared-network connection without substation only; not total installation or universal upgrade fee | F80: https://www.spgroup.com.sg/dam/jcr:ed6d35eb-7bb5-450c-8386-b61f0cc13142/Transmission%20Service%20Rate%20Schedule%20(effective%20from%201%20Jul%202026).pdf
A81: S02 | B81: LT connection 46-75 kVA | C81: 8800 | D81: SGD, excl GST | E81: Same conditional schedule; actual incremental charge needs SP confirmation | F81: https://www.spgroup.com.sg/dam/jcr:ed6d35eb-7bb5-450c-8386-b61f0cc13142/Transmission%20Service%20Rate%20Schedule%20(effective%20from%201%20Jul%202026).pdf
A82: J01 | B82: Tuas View, PR <=1.0 | C82: 13.41 | D82: SGD/m2/year, incl GST | E82: Ground rent only, not a developed yard or parking-space offer | F82: https://www.jtc.gov.sg/-/media/project/jtc-cx/corpweb/assets/find-land/land-rates/cx-land-rents-2h2026-with-impt-notes_.pdf
A83: J02 | B83: West of Jurong River, PR <=1.0 | C83: 19.89 | D83: SGD/m2/year, incl GST | E83: Ground rent; plot-ratio basis differs between rows | F83: https://www.jtc.gov.sg/-/media/project/jtc-cx/corpweb/assets/find-land/land-rates/cx-land-rents-2h2026-with-impt-notes_.pdf
A84: J03 | B84: Woodlands East / Senoko, PR <=1.4 | C84: 21.27 | D84: SGD/m2/year, incl GST | E84: Ground rent only; lease eligibility and actual availability unconfirmed | F84: https://www.jtc.gov.sg/-/media/project/jtc-cx/corpweb/assets/find-land/land-rates/cx-land-rents-2h2026-with-impt-notes_.pdf
... A90: G01 | B90: EHVCG maximum per charger | C90: 30000 | D90: SGD/eligible charger | E90: Up to 50% eligible cost with component caps; minimum 50 kW; maximum 3 chargers per site/applicant; 2026-2028 window or first 500 approved | F90: https://www.lta.gov.sg/content/ltagov/en/industry_innovations/technologies/electric_vehicles/charger_grants.html
A91: G02 | B91: Excluded large site costs | D91: Qualitative rule | E91: Major electrical infrastructure, civil infrastructure, signage/painting and grid connection excluded. Local charger cabling/trenching can be eligible; itemised scope and LTA assessment decide. | F91: https://www.lta.gov.sg/content/dam/ltagov/industry_innovations/Technologies/Electric_Vehicles/PDF/Guidelines%20and%20Frequently%20Asked%20Questions%20for%20EHVCG.pdf
A92: D01 | B92: Installer inspection/setup promotion | D92: Supplier promotion, T&Cs apply | E92: Free site assessment; first Form A inspection and setup-fee waiver advertised. No fixed saving, expiry or customer eligibility established. | F92: https://www.limkimhai.com.sg/dc-charger-installation-for-commercial-fleets-singapore/
A93: C01 | B93: Commercial DC installation from | C93: 25000 | D93: SGD/project, scope and GST unresolved | E93: Installer marketing starting figure only. Not a comparable installed project quotation or upper bound. | F93: https://mmengine.com/ev-charger-installation-singapore/
A94: P01 | B94: 25 Loyang Crescent heavy-duty yard | D94: Rental quotation required | E94: Public property listing found, but rent and charging rights not published | F94: https://www.cushmanwakefield.com/en/singapore/properties/for-lease/industrial/singapore/singapore/25-loyang-crescent/25loyang-crescent---heavy-duty-open-yard-l
A95: A01 | B95: JTC charger deployment approval | D95: Site approval condition | E95: Consult JTC engagement officer and obtain relevant consent; parking tenancy alone does not authorise installation | F95: https://www.jtc.gov.sg/get-help/development-and-renovation-works/qp-submission
A96: U01 | B96: Partner site preparation claim | C96: 500000 | D96: SGD, scope/date/GST unknown | E96: User-supplied stakeholder claim. Do not use as standard cost or subtract 50% grant from the whole amount. | F96: User-supplied interview account
A99: Ground land rent, factory floor rent and parking-bay rent are different. No rent benchmark is auto-loaded.
A101: EHVCG: major grid/electrical/civil costs excluded. Local charger cabling/trenching needs itemised eligibility review.
A103: A generic industrial/office-site discount was not established. ECCG is residential, not an industrial rebate.

Sheet Operating costs
A2: Operating assumptions and forecast controls
A4: Inherited demonstration inputs. Replace with records. Normal wages, loans, income tax and recoverable GST excluded.
A6: Input | B6: Value | C6: Unit | D6: Meaning / evidence
A7: ICE fuel consumption | B7: 0.1 | C7: litres/km | D7: Stock-balanced fuel / total km
A8: Diesel refill per visit | B8: 80 | C8: litres/visit | D8: Refill, not tank capacity
A9: Fuel-station detour | B9: 4 | C9: km/visit | D9: Extra round trip only
A10: Fuel queue and service | B10: 17 | C10: min/visit | D10: Queue and refuelling
A11: Detour driving speed | B11: 25 | C11: km/hour | D11: Detour speed
A12: Public-charger detour | B12: 8 | C12: km/visit | D12: Extra public-charger round trip
A13: Charging queue | B13: 15 | C13: min/visit | D13: Observed site/period queue
A14: Public plug handling | B14: 5 | C14: min/visit | D14: Public handling
A15: Public session fee | B15: 2 | C15: SGD/visit | D15: Exclude if tariff already includes it
A16: Depot handling time | B16: 4 | C16: min/day | D16: Depot handling
A17: Other EV paid time | B17: 0 | C17: min/day | D17: Distinct EV paid time
A18: Maximum public stop | B18: 90 | C18: min/visit | D18: Operating limit
... A57: Fallback EV COE | B57: 93000 | C57: SGD | D57: Archived quote fallback COE assumption
A58: Backup confirmed | B58: No | C58: Yes/No | D58: Capacity and all-in terms confirmed
A59: Loaded trial confirmed | B59: No | C59: Yes/No | D59: Loaded route and charging trial
A60: Energy prices confirmed | B60: No | C60: Yes/No | D60: Current company energy contracts
A61: Data mode | B61: Demonstration | C61: mode | D61: Demonstration / Customer
A62: Vehicle quote basis | B62: Gross | C62: Gross/Net/Unknown | D62: Vehicle inputs must be gross if grant separately deducted
A63: Analysis start date | B63: 46298 | C63: date | D63: Analysis start date; fixed 120 months
A64: EV scheduled repair | B64: 0 | C64: SGD/truck | D64: Separate scheduled battery/vehicle repair
A65: EV repair after purchase | B65: 60 | C65: months after purchase | D65: Repair timing
A66: ICE scheduled repair | B66: 0 | C66: SGD/truck | D66: Separate scheduled ICE repair
A67: ICE repair month | B67: 60 | C67: analysis month | D67: Applies to active ICE only
A68: EV servicing basis | B68: Hong Seh 200k average | C68: basis | D68: Hong Seh 200,000 km average uses the selected EV model. Annual override uses the value in row 26.

Sheet Products
A2: Recorded Hong Seh truck specifications
A4: Archived specifications and prices. Not current quotes or loaded performance evidence.
A6: Model | B6: MLW kg | C6: Kerb kg | D6: Listed battery kWh | E6: Proxy battery kWh/km | F6: Basis | G6: AC kW | H6: DC kW | I6: Archived price excl COE | J6: Range km | K6: Source | L6: Evidence | M6: Archived usable kWh | N6: Service schedule | O6: Service total at 200,000 km | P6: Average service cost / km | Q6: Source / treatment
A7: Farizon F3E | B7: 4300 | C7: 2100 | D7: 73.3 | E7: 0.24076598 | F7: Battery | G7: 11 | H7: 100 | I7: 70800 | J7: 367 | K7: Farizon F3E Electric 22158_30-Aug-2026.pdf, p1-2 | L7: Unconfirmed | M7: 72.8 | N7: Farizon F3e | O7: =IFERROR(INDEX('Service costs'!$X$7:$X$14,MATCH(N7,'Service costs'!$A$7:$A$14,0)),"n.a.") -> 1861 | P7: =IF(ISNUMBER(O7),O7/200000,"n.a.") -> 0.009305 | Q7: Hong Seh schedule supplied 18-Oct-2026. S$/km average smooths timing; use beyond 200,000 km is a projection.
A8: SRM T3EV | B8: 3500 | C8: 1560 | D8: 53.58 | E8: 0.1786 | F8: Battery | G8: 11 | H8: 55 | I8: 63800 | J8: 300 | K8: https://evhubs.sg/electric-vehicles/srm-t3-ev.html | L8: Unconfirmed | M8: 53.58 | N8: SRM T3 | O8: =IFERROR(INDEX('Service costs'!$X$7:$X$14,MATCH(N8,'Service costs'!$A$7:$A$14,0)),"n.a.") -> 2220 | P8: =IF(ISNUMBER(O8),O8/200000,"n.a.") -> 0.0111 | Q8: Hong Seh schedule supplied 18-Oct-2026. S$/km average smooths timing; use beyond 200,000 km is a projection.
A9: ChengLong L2EV | B9: 5000 | C9: 2480 | D9: 86.55 | E9: 0.27036947 | F9: Battery | G9: 22 | H9: 120 | I9: 78800 | J9: 320 | K9: Cheng Long L2 22151_14-Sep-2026.pdf, p1-2 | L9: Unconfirmed | M9: 86.55 | N9: Chenglong L2 | O9: =IFERROR(INDEX('Service costs'!$X$7:$X$14,MATCH(N9,'Service costs'!$A$7:$A$14,0)),"n.a.") -> 3285 | P9: =IF(ISNUMBER(O9),O9/200000,"n.a.") -> 0.016425 | Q9: Hong Seh schedule supplied 18-Oct-2026. S$/km average smooths timing; use beyond 200,000 km is a projection.
A10: Farizon H5E | B10: 5000 | C10: 2700 | D10: 100.46 | E10: 0.35560307 | F10: Battery | G10: 22 | H10: 100 | I10: 98000 | J10: 344 | K10: Farizon H5E 22109_14-Sep-2026.pdf, p1-2; user DC correction 17-Sep-2026 | L10: Unconfirmed | M10: 104.6 | N10: Farizon H5E / H9E | O10: =IFERROR(INDEX('Service costs'!$X$7:$X$14,MATCH(N10,'Service costs'!$A$7:$A$14,0)),"n.a.") -> 1400 | P10: =IF(ISNUMBER(O10),O10/200000,"n.a.") -> 0.007 | Q10: Hong Seh schedule supplied 18-Oct-2026. S$/km average smooths timing; use beyond 200,000 km is a projection.
A11: SRM T3EV+ | B11: 3505 | C11: 1660 | D11: 53.58 | E11: 0.1786 | F11: Battery | G11: 11 | H11: 55 | I11: 66800 | J11: 300 | K11: https://evhubs.sg/electric-vehicles/srm-t3-ev.html | L11: Unconfirmed | M11: 106 | N11: SRM T3 | O11: =IFERROR(INDEX('Service costs'!$X$7:$X$14,MATCH(N11,'Service costs'!$A$7:$A$14,0)),"n.a.") -> 2220 | P11: =IF(ISNUMBER(O11),O11/200000,"n.a.") -> 0.0111 | Q11: Hong Seh schedule supplied 18-Oct-2026. S$/km average smooths timing; use beyond 200,000 km is a projection.
A12: Farizon H9E 14ft | B12: 9800 | C12: 3400 | D12: 106.95 | E12: 0.44777631 | F12: Battery | H12: 100 | I12: 108000 | J12: 243 | K12: https://evhubs.sg/electric-vehicles/farizon-h9e.html | L12: Unconfirmed | M12: 106 | N12: Farizon H5E / H9E | O12: =IFERROR(INDEX('Service costs'!$X$7:$X$14,MATCH(N12,'Service costs'!$A$7:$A$14,0)),"n.a.") -> 1400 | P12: =IF(ISNUMBER(O12),O12/200000,"n.a.") -> 0.007 | Q12: Hong Seh schedule supplied 18-Oct-2026. S$/km average smooths timing; use beyond 200,000 km is a projection.
A13: Farizon H9E 20ft | B13: 9800 | C13: 3400 | D13: 162.28 | E13: 0.45914823 | F13: Battery | H13: 100 | I13: 128000 | J13: 372 | K13: https://evhubs.sg/electric-vehicles/farizon-h9e.html | L13: Unconfirmed | M13: 162 | N13: Farizon H5E / H9E | O13: =IFERROR(INDEX('Service costs'!$X$7:$X$14,MATCH(N13,'Service costs'!$A$7:$A$14,0)),"n.a.") -> 1400 | P13: =IF(ISNUMBER(O13),O13/200000,"n.a.") -> 0.007 | Q13: Hong Seh schedule supplied 18-Oct-2026. S$/km average smooths timing; use beyond 200,000 km is a projection.
A16: T3EV+ 106 kWh and H5E usable/listed conflicts are preserved, not selected as verified capacities.
A18: G: MLW <=3,500 kg. Y: >3,500-16,000 kg. X: >16,000 kg. H9E 9.8t is HGV, not VHGV.

Sheet Paths
A2: Vehicle paths and operating calculations
A4: One calculation engine, keyed truck and plan. Code 0=Keep ICE; 1=all-new ICE; 2=Plan A; 3=Plan B.
A6: Truck ID | B6: Plan code | C6: Included | D6: New type | E6: Replace month | F6: Current value | G6: Purchase | H6: Gross disposal | I6: Year-10 asset | J6: Old energy/year | K6: Old other/year | L6: New energy/year | M6: New other/year | N6: Grant | O6: Grant month | P6: Input status | Q6: Service status | R6: Days/year | S6: Work km/day | T6: Public share | U6: EV grid kWh/km | V6: Usable battery | W6: Public visits/year | X6: EV grid kWh/year | Y6: Peak depot kWh | Z6: Peak depot hours | AA6: Fuel litres/year | AB6: EV years | AC6: Peak public minutes | AD6: EV model | AE6: Peak load kg | AF6: Approved payload | AG6: Depot average kW | AH6: Accepted depot kW | AI6: Peak battery kWh | AJ6: Bank power kW | AK6: Registration date | AL6: EV MLW kg | AM6: Depot mode | AN6: Quote/value evidence | AO6: EV odometer km/year | AP6: EV servicing /year | AQ6: EV servicing basis
A7: ='Replacement plan'!A7 -> T001 | B7: 0 | C7: =IF(COUNTIFS('Fleet register'!$A$7:$A$106,$A7)=1,VLOOKUP($A7,'Fleet register'!$A$7:$S$106,2,FALSE),0) -> 1 | D7: =IF("Keep ICE"="EV","EV","ICE") -> ICE | E7: =IF(C7=0,0,IF('Replacement plan'!$M$7="",VLOOKUP($A7,'Fleet register'!$A$7:$S$106,10,FALSE),'Replacement plan'!$M$7)) -> 12 | F7: =IF(C7=0,0,VLOOKUP($A7,'Fleet register'!$A$7:$S$106,11,FALSE)) -> 24000 | G7: =IFERROR(IF(C7=0,0,IF(E7=120,0,IF(D7="ICE",'Replacement plan'!$C$7,IF('Replacement plan'!$D$7="",INDEX(Products!$I$7:$I$13,MATCH('Replacement plan'!$B$7,Products!$A$7:$A$13,0))+'Operating costs'!$B$57,'Replacement plan'!$D$7))*(1+'Operating costs'!$B$50)^(E7/12))),"n.a.") -> 181000 | H7: =IFERROR(IF(C7=0,0,IF(E7=0,F7,VLOOKUP($A7,'Fleet register'!$A$7:$S$106,12,FALSE)+VLOOKUP($A7,'Fleet register'!$A$7:$S$106,13,FALSE)*MAX(0,VLOOKUP($A7,'Fleet register'!$A$7:$S$106,10,FALSE)-E7)/VLOOKUP($A7,'Fleet register'!$A$7:$S$106,14,FALSE))),"n.a.") -> 10000 | I7: =IF(C7=0,0,IF(E7=120,0,'Replacement plan'!$N$7)) -> 21300 | J7: =IF(C7=0,0,IF(P7="Complete",((S7*(R7-'Operating costs'!$B$39))+ROUNDUP(S7*(R7-'Operating costs'!$B$39)*IF('Replacement plan'!$AG$7="",'Operating costs'!$B$7,'Replacement plan'!$AG$7)/('Operating costs'!$B$8-'Operating costs'!$B$9*IF('Replacement plan'!$AG$7="",'Operating costs'!$B$7,'Replacement plan'!$AG$7)),0)*'Operating costs'!$B$9)*IF('Replacement plan'!$AG$7="",'Operating costs'!$B$7,'Replacement plan'!$AG$7)*('Energy and charging'!$B$9*'Energy and charging'!$B$7+(1-'Energy and charging'!$B$9)*'Energy and charging'!$B$8)*'Operating costs'!$B$23,"n.a.")) -> 9045.6 | K7: =IF(C7=0,0,IF(P7="Complete",SUM('Operating costs'!$B$24,'Operating costs'!$B$27,'Operating costs'!$B$29,'Operating costs'!$B$31,'Operating costs'!$B$33,'Operating costs'!$B$34,'Operating costs'!$B$37,'Replacement plan'!$W$7)+'Operating costs'!$B$39*'Operating costs'!$B$42+ROUNDUP(S7*(R7-'Operating costs'!$B$39)*IF('Replacement plan'!$AG$7="",'Operating costs'!$B$7,'Replacement plan'!$AG$7)/('Operating costs'!$B$8-'Operating costs'!$B$9*IF('Replacement plan'!$AG$7="",'Operating costs'!$B$7,'Replacement plan'!$AG$7)),0)*('Operating costs'!$B$9/'Operating costs'!$B$11+'Operating costs'!$B$10/60)*'Operating costs'!$B$19*'Operating costs'!$B$21,"n.a.")) -> 9105.75 | L7: =IF(C7=0,0,IF(P7="Complete",IF(D7="EV",X7*((1-T7)*'Energy and charging'!$B$10+T7*'Energy and charging'!$B$11)*'Operating costs'!$B$22,AA7*('Energy and charging'!$B$9*'Energy and charging'!$B$7+(1-'Energy and charging'!$B$9)*'Energy and charging'!$B$8)*'Operating costs'!$B$23),"n.a.")) -> 9045.6 | M7: =IF(C7=0,0,IF(P7="Complete",IF(D7="ICE",SUM('Operating costs'!$B$25,'Operating costs'!$B$27,'Operating costs'!$B$29,'Operating costs'!$B$31,'Operating costs'!$B$33,'Operating costs'!$B$35,'Operating costs'!$B$37,'Replacement plan'!$X$7)+'Operating costs'!$B$40*'Operating costs'!$B$42+ROUNDUP(S7*(R7-'Operating costs'!$B$40)*IF('Replacement plan'!$AH$7="",'Operating costs'!$B$7,'Replacement plan'!$AH$7)/('Operating costs'!$B$8-'Operating costs'!$B$9*IF('Replacement plan'!$AH$7="",'Operating costs'!$B$7,'Replacement plan'!$AH$7)),0)*('Operating costs'!$B$9/'Operating costs'!$B$11+'Operating costs'!$B$10/60)*'Operating costs'!$B$19*'Operating costs'!$B$21,SUM(AP7,'Operating costs'!$B$28,'Operating costs'!$B$30,'Operating costs'!$B$32,'Operating costs'!$B$33,'Operating costs'!$B$36,'Operating costs'!$B$38,'Replacement plan'!$Y$7)+'Operating costs'!$B$41*'Operating costs'!$B$43+W7*'Operating costs'!$B$15+(T7*X7/'Replacement plan'!$L$7+W7*('Operating costs'!$B$12/'Operating costs'!$B$11+('Operating costs'!$B$13+'Operating costs'!$B$14)/60)+(R7-'Operating costs'!$B$41)*(IF(T7<1,'Operating costs'!$B$16,0)+'Operating costs'!$B$17)/60)*'Operating costs'!$B$19*'Operating costs'!$B$20),"n.a.")) -> 9105.75 | N7: =IF(AND(C7=1,D7="EV",E7<120,E7+'Replacement plan'!$AA$7<=120),'Replacement plan'!$Z$7,0) -> 0 | O7: =E7+'Replacement plan'!$AA$7 -> 12 | P7: =IFERROR(IF(C7=0,"Excluded",IF(OR(COUNTIFS('Fleet register'!$A$7:$A$106,A7)<>1,COUNTIFS('Replacement plan'!$A$7:$A$106,A7)<>1),"Duplicate/missing ID",IF(NOT(AND(ISNUMBER(VLOOKUP($A7,'Fleet register'!$A$7:$S$106,5,FALSE)),ISNUMBER(VLOOKUP($A7,'Fleet register'!$A$7:$S$106,6,FALSE)),ISNUMBER(VLOOKUP($A7,'Fleet register'!$A$7:$S$106,10,FALSE)),ISNUMBER(VLOOKUP($A7,'Fleet register'!$A$7:$S$106,11,FALSE)),ISNUMBER(VLOOKUP($A7,'Fleet register'!$A$7:$S$106,12,FALSE)),ISNUMBER(VLOOKUP($A7,'Fleet register'!$A$7:$S$106,13,FALSE)),ISNUMBER(VLOOKUP($A7,'Fleet register'!$A$7:$S$106,14,FALSE)),VLOOKUP($A7,'Fleet register'!$A$7:$S$106,14,FALSE)>0,ISNUMBER('Replacement plan'!$C$7),OR(E7=120,ISNUMBER('Replacement plan'!$N$7)),ISNUMBER(E7))),"Missing vehicle input",IF(OR(E7<0,E7>VLOOKUP($A7,'Fleet register'!$A$7:$S$106,10,FALSE),E7>120,E7<>INT(E7),VLOOKUP($A7,'Fleet register'!$A$7:$S$106,6,FALSE)<=0,VLOOKUP($A7,'Fleet register'!$A$7:$S$106,6,FALSE)>366,VLOOKUP($A7,'Fleet register'!$A$7:$S$106,5,FALSE)<0,VLOOKUP($A7,'Fleet register'!$A$7:$S$106,11,FALSE)<0,I7<0,'Operating costs'!$B$8<='Operating costs'!$B$7*'Operating costs'!$B$9,'Operating costs'!$B$11<=0,'Operating costs'!$B$39>R7,'Operating costs'!$B$40>R7,'Operating costs'!$B$41>R7,NOT(OR("Keep ICE"="Keep ICE","Keep ICE"="New ICE","Keep ICE"="EV"))),"Invalid vehicle input",IF(AND(D7="EV",E7<120,OR(NOT(ISNUMBER(U7)),NOT(ISNUMBER(V7)),V7<=0,T7<0,T7>1,'Replacement plan'!$L$7<=0,'Operating costs'!$B$44<0,'Operating costs'!$B$44>=1,'Operating costs'!$B$47<=0,'Operating costs'!$B$47>1,V7*'Operating costs'!$B$47/(1-'Operating costs'!$B$44)<=T7*'Operating costs'!$B$12*U7,AND('Replacement plan'!$Z$7>0,OR('Replacement plan'!$AB$7<>"Yes",'Operating costs'!$B$62<>"Gross")))),"Invalid EV input",IF(AND(ISNUMBER('Operating costs'!$B$7),ISNUMBER('Operating costs'!$B$8),ISNUMBER('Operating costs'!$B$9),ISNUMBER('Operating costs'!$B$10),ISNUMBER('Operating costs'!$B$11),ISNUMBER('Operating costs'!$B$19),ISNUMBER('Operating costs'!$B$21),ISNUMBER('Operating costs'!$B$23),ISNUMBER('Operating costs'!$B$24),ISNUMBER('Operating costs'!$B$25),ISNUMBER('Operating costs'!$B$27),ISNUMBER('Operating costs'!$B$29),ISNUMBER('Operating costs'!$B$31),ISNUMBER('Operating costs'!$B$33),ISNUMBER('Operating costs'!$B$34),ISNUMBER('Operating costs'!$B$35),ISNUMBER('Operating costs'!$B$37),ISNUMBER('Operating costs'!$B$39),ISNUMBER('Operating costs'!$B$40),ISNUMBER('Operating costs'!$B$42),ISNUMBER('Operating costs'!$B$50),ISNUMBER('Operating costs'!$B$51),ISNUMBER('Operating costs'!$B$53),ISNUMBER('Operating costs'!$B$54),ISNUMBER('Operating costs'!$B$66),ISNUMBER('Operating costs'!$B$67),AND(ISNUMBER('Energy and charging'!$B$9),'Energy and charging'!$B$9>=0,'Energy and charging'!$B$9<=1,OR('Energy and charging'!$B$9=0,AND(ISNUMBER('Energy and charging'!$B$7),'Energy and charging'!$B$7>=0)),OR('Energy and charging'!$B$9=1,AND(ISNUMBER('Energy and charging'!$B$8),'Energy and charging'!$B$8>=0))),ISNUMBER(VLOOKUP($A7,'Fleet register'!$A$7:$S$106,15,FALSE)),ISNUMBER(VLOOKUP($A7,'Fleet register'!$A$7:$S$106,16,FALSE)),ISNUMBER('Replacement plan'!$W$7),ISNUMBER('Replacement plan'!$X$7),OR(E7=120,AND(ISNUMBER(G7),G7>=0)),ISNUMBER(H7),H7>=0,OR(D7<>"EV",E7=120,AND(ISNUMBER('Operating costs'!$B$12),ISNUMBER('Operating costs'!$B$13),ISNUMBER('Operating costs'!$B$14),ISNUMBER('Operating costs'!$B$15),ISNUMBER('Operating costs'!$B$16),ISNUMBER('Operating costs'!$B$17),ISNUMBER('Operating costs'!$B$18),ISNUMBER('Operating costs'!$B$20),ISNUMBER('Operating costs'!$B$22),OR(AND('Operating costs'!$B$68="Annual override",ISNUMBER('Operating costs'!$B$26)),AND('Operating costs'!$B$68="Hong Seh 200k average",ISNUMBER(IFERROR(INDEX(Products!$P$7:$P$13,MATCH(AD7,Products!$A$7:$A$13,0)),"")))),ISNUMBER('Operating costs'!$B$28),ISNUMBER('Operating costs'!$B$30),ISNUMBER('Operating costs'!$B$32),ISNUMBER('Operating costs'!$B$36),ISNUMBER('Operating costs'!$B$38),ISNUMBER('Operating costs'!$B$41),ISNUMBER('Operating costs'!$B$43),ISNUMBER('Operating costs'!$B$44),ISNUMBER('Operating costs'!$B$45),ISNUMBER('Operating costs'!$B$46),ISNUMBER('Operating costs'!$B$47),ISNUMBER('Operating costs'!$B$48),ISNUMBER('Operating costs'!$B$49),ISNUMBER('Operating costs'!$B$52),ISNUMBER('Operating costs'!$B$64),ISNUMBER('Operating costs'!$B$65),ISNUMBER('Energy and charging'!$B$12),AND(ISNUMBER(1-'Energy and charging'!$B$12),1-'Energy and charging'!$B$12>=0,1-'Energy and charging'!$B$12<=1,OR(1-'Energy and charging'!$B$12=0,AND(ISNUMBER('Energy and charging'!$B$10),'Energy and charging'!$B$10>=0)),OR(1-'Energy and charging'!$B$12=1,AND(ISNUMBER('Energy and charging'!$B$11),'Energy and charging'!$B$11>=0))),ISNUMBER('Replacement plan'!$Y$7),ISNUMBER('Replacement plan'!$Z$7),'Replacement plan'!$Z$7>=0,ISNUMBER('Replacement plan'!$AA$7),'Replacement plan'!$AA$7>=0,'Replacement plan'!$AA$7=INT('Replacement plan'!$AA$7),ISNUMBER('Replacement plan'!$L$7))),'Operating costs'!$B$7>=0,'Operating costs'!$B$21>=0,'Operating costs'!$B$21<=1,'Operating costs'!$B$23>=0,'Operating costs'!$B$23<=1,'Operating costs'!$B$50>-1,'Operating costs'!$B$51>-1,'Operating costs'!$B$53>-1,'Operating costs'!$B$54>-1),IF(AND(ISNUMBER(IF('Replacement plan'!$AG$7="",'Operating costs'!$B$7,'Replacement plan'!$AG$7)),IF('Replacement plan'!$AG$7="",'Operating costs'!$B$7,'Replacement plan'!$AG$7)>=0,ISNUMBER(IF('Replacement plan'!$AH$7="",'Operating costs'!$B$7,'Replacement plan'!$AH$7)),IF('Replacement plan'!$AH$7="",'Operating costs'!$B$7,'Replacement plan'!$AH$7)>=0,'Operating costs'!$B$8>MAX(IF('Replacement plan'!$AG$7="",'Operating costs'!$B$7,'Replacement plan'!$AG$7),IF('Replacement plan'!$AH$7="",'Operating costs'!$B$7,'Replacement plan'!$AH$7))*'Operating costs'!$B$9),IF(AND(VLOOKUP($A7,'Fleet register'!$A$7:$S$106,10,FALSE)>=0,VLOOKUP($A7,'Fleet register'!$A$7:$S$106,10,FALSE)<=120,VLOOKUP($A7,'Fleet register'!$A$7:$S$106,10,FALSE)=INT(VLOOKUP($A7,'Fleet register'!$A$7:$S$106,10,FALSE)),VLOOKUP($A7,'Fleet register'!$A$7:$S$106,15,FALSE)>=0,VLOOKUP($A7,'Fleet register'!$A$7:$S$106,16,FALSE)>=0,MIN('Operating costs'!$B$7,'Operating costs'!$B$8,'Operating costs'!$B$9,'Operating costs'!$B$10,'Operating costs'!$B$11,'Operating costs'!$B$19,'Operating costs'!$B$21,'Operating costs'!$B$23,'Operating costs'!$B$24,'Operating costs'!$B$25,'Operating costs'!$B$27,'Operating costs'!$B$29,'Operating costs'!$B$31,'Operating costs'!$B$33,'Operating costs'!$B$34,'Operating costs'!$B$35,'Operating costs'!$B$37,'Operating costs'!$B$39,'Operating costs'!$B$40,'Operating costs'!$B$42,'Operating costs'!$B$66,'Operating costs'!$B$67)>=0,OR(D7<>"EV",E7=120,AND(MIN('Operating costs'!$B$12,'Operating costs'!$B$13,'Operating costs'!$B$14,'Operating costs'!$B$15,'Operating costs'!$B$16,'Operating costs'!$B$17,'Operating costs'!$B$18,'Operating costs'!$B$20,'Operating costs'!$B$22,'Operating costs'!$B$26,'Operating costs'!$B$28,'Operating costs'!$B$30,'Operating costs'!$B$32,'Operating costs'!$B$36,'Operating costs'!$B$38,'Operating costs'!$B$41,'Operating costs'!$B$43,'Operating costs'!$B$44,'Operating costs'!$B$45,'Operating costs'!$B$46,'Operating costs'!$B$47,'Operating costs'!$B$48,'Operating costs'!$B$49,'Operating costs'!$B$64,'Operating costs'!$B$65)>=0,'Operating costs'!$B$20<=1,'Operating costs'!$B$22<=1,'Operating costs'!$B$45<1,'Operating costs'!$B$46<1,'Operating costs'!$B$52>-1))),"Complete","Invalid operating limits"),"Invalid fuel override"),"Missing/invalid operating input")))))),"Invalid input type") -> Complete | Q7: =IF(C7=0,"Excluded",IF(P7<>"Complete",P7,IF(OR('Replacement plan'!$AD$7<120-E7,AND(D7="EV",E7<120,OR('Replacement plan'!$AC$7<120-E7,'Replacement plan'!$I$7="No",AND(ISNUMBER(AF7),AE7>AF7),AI7>V7*(1-'Operating costs'!$B$46)^MAX(0,AB7-1)*(1-'Operating costs'!$B$45),AC7>'Operating costs'!$B$18,AND(T7<1,OR(AG7<=0,AND(ISNUMBER(AH7),AG7>AH7))),'Replacement plan'!$L$7>INDEX(Products!$H$7:$H$13,MATCH('Replacement plan'!$B$7,Products!$A$7:$A$13,0))))),"Fails entered limits",IF(AND(D7="EV",E7<120,OR(NOT(ISNUMBER(VLOOKUP($A7,'Fleet register'!$A$7:$S$106,7,FALSE))),NOT(ISNUMBER(VLOOKUP($A7,'Fleet register'!$A$7:$S$106,8,FALSE))),NOT(ISNUMBER(AF7)),'Replacement plan'!$I$7<>"Yes",NOT(ISNUMBER(AH7)),'Operating costs'!$B$59<>"Yes",'Operating costs'!$B$58<>"Yes")),"Unverified","Within entered limits")))) -> Within entered limits | R7: =IF(C7=0,0,VLOOKUP($A7,'Fleet register'!$A$7:$S$106,6,FALSE)) -> 300 | S7: =IF(C7=0,0,VLOOKUP($A7,'Fleet register'!$A$7:$S$106,5,FALSE)) -> 150 | T7: =IF(D7="EV",'Energy and charging'!$B$12,0) -> 0 | U7: =IFERROR(IF(C7=0,0,IF(D7="EV",IF('Replacement plan'!$F$7="",INDEX(Products!$E$7:$E$13,MATCH('Replacement plan'!$B$7,Products!$A$7:$A$13,0)),'Replacement plan'!$F$7)/IF('Replacement plan'!$G$7="Battery",1-'Operating costs'!$B$44,1),0)),"n.a.") -> 0 | V7: =IFERROR(IF(C7=0,0,IF(D7="EV",IF('Replacement plan'!$E$7="",INDEX(Products!$D$7:$D$13,MATCH('Replacement plan'!$B$7,Products!$A$7:$A$13,0)),'Replacement plan'!$E$7),0)),"n.a.") -> 0 | W7: =IF(C7=0,0,IF(AND(P7="Complete",D7="EV",E7<120),IF(T7=0,0,ROUNDUP(T7*(R7-'Operating costs'!$B$41)*(S7*U7+'Operating costs'!$B$48/(1-'Operating costs'!$B$44))/(V7*'Operating costs'!$B$47/(1-'Operating costs'!$B$44)-T7*'Operating costs'!$B$12*U7),0)),0)) -> 0 | X7: =IF(C7=0,0,IF(AND(P7="Complete",D7="EV",E7<120),(R7-'Operating costs'!$B$41)*(S7*U7+'Operating costs'!$B$48/(1-'Operating costs'!$B$44))+W7*'Operating costs'!$B$12*U7,0)) -> 0 | Y7: =IF(AND(C7=1,D7="EV",E7<120),AI7/(1-'Operating costs'!$B$44)*(1-T7),0) -> 0 | Z7: =IF(AND(C7=1,D7="EV",E7<120,T7<1,AG7>0),Y7/AG7,0) -> 0 | AA7: =IF(C7=0,0,IF(P7="Complete",((S7*(R7-'Operating costs'!$B$40))+ROUNDUP(S7*(R7-'Operating costs'!$B$40)*IF('Replacement plan'!$AH$7="",'Operating costs'!$B$7,'Replacement plan'!$AH$7)/('Operating costs'!$B$8-'Operating costs'!$B$9*IF('Replacement plan'!$AH$7="",'Operating costs'!$B$7,'Replacement plan'!$AH$7)),0)*'Operating costs'!$B$9)*IF('Replacement plan'!$AH$7="",'Operating costs'!$B$7,'Replacement plan'!$AH$7),"n.a.")) -> 4522.8 | AB7: =IF(D7="EV",(120-E7)/12,0) -> 0 | AC7: =IF(AND(C7=1,D7="EV",E7<120,T7>0),'Operating costs'!$B$12/'Operating costs'!$B$11*60+'Operating costs'!$B$13+'Operating costs'!$B$14+V7*'Operating costs'!$B$47/(1-'Operating costs'!$B$44)/'Replacement plan'!$L$7*60,0) -> 0 | AD7: ='Replacement plan'!$B$7 -> ChengLong L2EV | AE7: =IF(C7=0,0,VLOOKUP($A7,'Fleet register'!$A$7:$S$106,8,FALSE)) -> 1200 | AF7: =IF('Replacement plan'!$H$7="","n.a.",'Replacement plan'!$H$7) -> n.a. | AG7: ='Replacement plan'!$J$7 -> 22 | AH7: =IFERROR(IF(D7="EV",IF('Replacement plan'!$K$7="AC",IF(ISNUMBER(INDEX(Products!$G$7:$G$13,MATCH('Replacement plan'!$B$7,Products!$A$7:$A$13,0))),INDEX(Products!$G$7:$G$13,MATCH('Replacement plan'!$B$7,Products!$A$7:$A$13,0)),"n.a."),IF(ISNUMBER(INDEX(Products!$H$7:$H$13,MATCH('Replacement plan'!$B$7,Products!$A$7:$A$13,0))),INDEX(Products!$H$7:$H$13,MATCH('Replacement plan'!$B$7,Products!$A$7:$A$13,0)),"n.a.")),0),"n.a.") -> 0 | AI7: =IF(AND(C7=1,D7="EV",E7<120),(VLOOKUP($A7,'Fleet register'!$A$7:$S$106,7,FALSE)+IF(T7>0,'Operating costs'!$B$12,0))*U7*(1-'Operating costs'!$B$44)+'Operating costs'!$B$49,0) -> 0 | AJ7: =IF(D7="EV",'Energy and charging'!$B$50,0) -> 0 | AK7: =EDATE('Operating costs'!$B$63,E7) -> 46663 | AL7: =IFERROR(IF(D7="EV",INDEX(Products!$B$7:$B$13,MATCH('Replacement plan'!$B$7,Products!$A$7:$A$13,0)),0),"n.a.") -> 0 | AM7: ='Replacement plan'!$K$7 -> DC | AN7: ='Replacement plan'!$AE$7 -> Assumed | AO7: =IF(AND(C7=1,D7="EV",E7<120),(R7-'Operating costs'!$B$41)*S7+W7*'Operating costs'!$B$12,0) -> 0 | AP7: =IF(AND(C7=1,D7="EV",E7<120),IF('Operating costs'!$B$68="Hong Seh 200k average",AO7*IFERROR(INDEX(Products!$P$7:$P$13,MATCH(AD7,Products!$A$7:$A$13,0)),"n.a."),'Operating costs'!$B$26),0) -> 0 | AQ7: =IF(D7="EV",'Operating costs'!$B$68,"Not applicable") -> Not applicable
A8: ='Replacement plan'!A7 -> T001 | B8: 1 | C8: =IF(COUNTIFS('Fleet register'!$A$7:$A$106,$A8)=1,VLOOKUP($A8,'Fleet register'!$A$7:$S$106,2,FALSE),0) -> 1 | D8: =IF("New ICE"="EV","EV","ICE") -> ICE | E8: =IF(C8=0,0,0) -> 0 | F8: =IF(C8=0,0,VLOOKUP($A8,'Fleet register'!$A$7:$S$106,11,FALSE)) -> 24000 | G8: =IFERROR(IF(C8=0,0,IF(E8=120,0,IF(D8="ICE",'Replacement plan'!$C$7,IF('Replacement plan'!$D$7="",INDEX(Products!$I$7:$I$13,MATCH('Replacement plan'!$B$7,Products!$A$7:$A$13,0))+'Operating costs'!$B$57,'Replacement plan'!$D$7))*(1+'Operating costs'!$B$50)^(E8/12))),"n.a.") -> 181000 | H8: =IFERROR(IF(C8=0,0,IF(E8=0,F8,VLOOKUP($A8,'Fleet register'!$A$7:$S$106,12,FALSE)+VLOOKUP($A8,'Fleet register'!$A$7:$S$106,13,FALSE)*MAX(0,VLOOKUP($A8,'Fleet register'!$A$7:$S$106,10,FALSE)-E8)/VLOOKUP($A8,'Fleet register'!$A$7:$S$106,14,FALSE))),"n.a.") -> 24000 | I8: =IF(C8=0,0,IF(E8=120,0,IF('Replacement plan'!$AI$7="",'Operating costs'!$B$56,'Replacement plan'!$AI$7))) -> 12000 | J8: =IF(C8=0,0,IF(P8="Complete",((S8*(R8-'Operating costs'!$B$39))+ROUNDUP(S8*(R8-'Operating costs'!$B$39)*IF('Replacement plan'!$AG$7="",'Operating costs'!$B$7,'Replacement plan'!$AG$7)/('Operating costs'!$B$8-'Operating costs'!$B$9*IF('Replacement plan'!$AG$7="",'Operating costs'!$B$7,'Replacement plan'!$AG$7)),0)*'Operating costs'!$B$9)*IF('Replacement plan'!$AG$7="",'Operating costs'!$B$7,'Replacement plan'!$AG$7)*('Energy and charging'!$B$9*'Energy and charging'!$B$7+(1-'Energy and charging'!$B$9)*'Energy and charging'!$B$8)*'Operating costs'!$B$23,"n.a.")) -> 9045.6 | K8: =IF(C8=0,0,IF(P8="Complete",SUM('Operating costs'!$B$24,'Operating costs'!$B$27,'Operating costs'!$B$29,'Operating costs'!$B$31,'Operating costs'!$B$33,'Operating costs'!$B$34,'Operating costs'!$B$37,'Replacement plan'!$W$7)+'Operating costs'!$B$39*'Operating costs'!$B$42+ROUNDUP(S8*(R8-'Operating costs'!$B$39)*IF('Replacement plan'!$AG$7="",'Operating costs'!$B$7,'Replacement plan'!$AG$7)/('Operating costs'!$B$8-'Operating costs'!$B$9*IF('Replacement plan'!$AG$7="",'Operating costs'!$B$7,'Replacement plan'!$AG$7)),0)*('Operating costs'!$B$9/'Operating costs'!$B$11+'Operating costs'!$B$10/60)*'Operating costs'!$B$19*'Operating costs'!$B$21,"n.a.")) -> 9105.75 | L8: =IF(C8=0,0,IF(P8="Complete",IF(D8="EV",X8*((1-T8)*'Energy and charging'!$B$10+T8*'Energy and charging'!$B$11)*'Operating costs'!$B$22,AA8*('Energy and charging'!$B$9*'Energy and charging'!$B$7+(1-'Energy and charging'!$B$9)*'Energy and charging'!$B$8)*'Operating costs'!$B$23),"n.a.")) -> 9045.6 | M8: =IF(C8=0,0,IF(P8="Complete",IF(D8="ICE",SUM('Operating costs'!$B$25,'Operating costs'!$B$27,'Operating costs'!$B$29,'Operating costs'!$B$31,'Operating costs'!$B$33,'Operating costs'!$B$35,'Operating costs'!$B$37,'Replacement plan'!$X$7)+'Operating costs'!$B$40*'Operating costs'!$B$42+ROUNDUP(S8*(R8-'Operating costs'!$B$40)*IF('Replacement plan'!$AH$7="",'Operating costs'!$B$7,'Replacement plan'!$AH$7)/('Operating costs'!$B$8-'Operating costs'!$B$9*IF('Replacement plan'!$AH$7="",'Operating costs'!$B$7,'Replacement plan'!$AH$7)),0)*('Operating costs'!$B$9/'Operating costs'!$B$11+'Operating costs'!$B$10/60)*'Operating costs'!$B$19*'Operating costs'!$B$21,SUM(AP8,'Operating costs'!$B$28,'Operating costs'!$B$30,'Operating costs'!$B$32,'Operating costs'!$B$33,'Operating costs'!$B$36,'Operating costs'!$B$38,'Replacement plan'!$Y$7)+'Operating costs'!$B$41*'Operating costs'!$B$43+W8*'Operating costs'!$B$15+(T8*X8/'Replacement plan'!$L$7+W8*('Operating costs'!$B$12/'Operating costs'!$B$11+('Operating costs'!$B$13+'Operating costs'!$B$14)/60)+(R8-'Operating costs'!$B$41)*(IF(T8<1,'Operating costs'!$B$16,0)+'Operating costs'!$B$17)/60)*'Operating costs'!$B$19*'Operating costs'!$B$20),"n.a.")) -> 9105.75 | N8: =IF(AND(C8=1,D8="EV",E8<120,E8+'Replacement plan'!$AA$7<=120),'Replacement plan'!$Z$7,0) -> 0 | O8: =E8+'Replacement plan'!$AA$7 -> 0 | P8: =IFERROR(IF(C8=0,"Excluded",IF(OR(COUNTIFS('Fleet register'!$A$7:$A$106,A8)<>1,COUNTIFS('Replacement plan'!$A$7:$A$106,A8)<>1),"Duplicate/missing ID",IF(NOT(AND(ISNUMBER(VLOOKUP($A8,'Fleet register'!$A$7:$S$106,5,FALSE)),ISNUMBER(VLOOKUP($A8,'Fleet register'!$A$7:$S$106,6,FALSE)),ISNUMBER(VLOOKUP($A8,'Fleet register'!$A$7:$S$106,10,FALSE)),ISNUMBER(VLOOKUP($A8,'Fleet register'!$A$7:$S$106,11,FALSE)),ISNUMBER(VLOOKUP($A8,'Fleet register'!$A$7:$S$106,12,FALSE)),ISNUMBER(VLOOKUP($A8,'Fleet register'!$A$7:$S$106,13,FALSE)),ISNUMBER(VLOOKUP($A8,'Fleet register'!$A$7:$S$106,14,FALSE)),VLOOKUP($A8,'Fleet register'!$A$7:$S$106,14,FALSE)>0,ISNUMBER('Replacement plan'!$C$7),OR(E8=120,OR(ISNUMBER('Replacement plan'!$AI$7),AND('Replacement plan'!$AI$7="",ISNUMBER('Operating costs'!$B$56)))),ISNUMBER(E8))),"Missing vehicle input",IF(OR(E8<0,E8>VLOOKUP($A8,'Fleet register'!$A$7:$S$106,10,FALSE),E8>120,E8<>INT(E8),VLOOKUP($A8,'Fleet register'!$A$7:$S$106,6,FALSE)<=0,VLOOKUP($A8,'Fleet register'!$A$7:$S$106,6,FALSE)>366,VLOOKUP($A8,'Fleet register'!$A$7:$S$106,5,FALSE)<0,VLOOKUP($A8,'Fleet register'!$A$7:$S$106,11,FALSE)<0,I8<0,'Operating costs'!$B$8<='Operating costs'!$B$7*'Operating costs'!$B$9,'Operating costs'!$B$11<=0,'Operating costs'!$B$39>R8,'Operating costs'!$B$40>R8,'Operating costs'!$B$41>R8,NOT(OR("New ICE"="Keep ICE","New ICE"="New ICE","New ICE"="EV"))),"Invalid vehicle input",IF(AND(D8="EV",E8<120,OR(NOT(ISNUMBER(U8)),NOT(ISNUMBER(V8)),V8<=0,T8<0,T8>1,'Replacement plan'!$L$7<=0,'Operating costs'!$B$44<0,'Operating costs'!$B$44>=1,'Operating costs'!$B$47<=0,'Operating costs'!$B$47>1,V8*'Operating costs'!$B$47/(1-'Operating costs'!$B$44)<=T8*'Operating costs'!$B$12*U8,AND('Replacement plan'!$Z$7>0,OR('Replacement plan'!$AB$7<>"Yes",'Operating costs'!$B$62<>"Gross")))),"Invalid EV input",IF(AND(ISNUMBER('Operating costs'!$B$7),ISNUMBER('Operating costs'!$B$8),ISNUMBER('Operating costs'!$B$9),ISNUMBER('Operating costs'!$B$10),ISNUMBER('Operating costs'!$B$11),ISNUMBER('Operating costs'!$B$19),ISNUMBER('Operating costs'!$B$21),ISNUMBER('Operating costs'!$B$23),ISNUMBER('Operating costs'!$B$24),ISNUMBER('Operating costs'!$B$25),ISNUMBER('Operating costs'!$B$27),ISNUMBER('Operating costs'!$B$29),ISNUMBER('Operating costs'!$B$31),ISNUMBER('Operating costs'!$B$33),ISNUMBER('Operating costs'!$B$34),ISNUMBER('Operating costs'!$B$35),ISNUMBER('Operating costs'!$B$37),ISNUMBER('Operating costs'!$B$39),ISNUMBER('Operating costs'!$B$40),ISNUMBER('Operating costs'!$B$42),ISNUMBER('Operating costs'!$B$50),ISNUMBER('Operating costs'!$B$51),ISNUMBER('Operating costs'!$B$53),ISNUMBER('Operating costs'!$B$54),ISNUMBER('Operating costs'!$B$66),ISNUMBER('Operating costs'!$B$67),AND(ISNUMBER('Energy and charging'!$B$9),'Energy and charging'!$B$9>=0,'Energy and charging'!$B$9<=1,OR('Energy and charging'!$B$9=0,AND(ISNUMBER('Energy and charging'!$B$7),'Energy and charging'!$B$7>=0)),OR('Energy and charging'!$B$9=1,AND(ISNUMBER('Energy and charging'!$B$8),'Energy and charging'!$B$8>=0))),ISNUMBER(VLOOKUP($A8,'Fleet register'!$A$7:$S$106,15,FALSE)),ISNUMBER(VLOOKUP($A8,'Fleet register'!$A$7:$S$106,16,FALSE)),ISNUMBER('Replacement plan'!$W$7),ISNUMBER('Replacement plan'!$X$7),OR(E8=120,AND(ISNUMBER(G8),G8>=0)),ISNUMBER(H8),H8>=0,OR(D8<>"EV",E8=120,AND(ISNUMBER('Operating costs'!$B$12),ISNUMBER('Operating costs'!$B$13),ISNUMBER('Operating costs'!$B$14),ISNUMBER('Operating costs'!$B$15),ISNUMBER('Operating costs'!$B$16),ISNUMBER('Operating costs'!$B$17),ISNUMBER('Operating costs'!$B$18),ISNUMBER('Operating costs'!$B$20),ISNUMBER('Operating costs'!$B$22),OR(AND('Operating costs'!$B$68="Annual override",ISNUMBER('Operating costs'!$B$26)),AND('Operating costs'!$B$68="Hong Seh 200k average",ISNUMBER(IFERROR(INDEX(Products!$P$7:$P$13,MATCH(AD8,Products!$A$7:$A$13,0)),"")))),ISNUMBER('Operating costs'!$B$28),ISNUMBER('Operating costs'!$B$30),ISNUMBER('Operating costs'!$B$32),ISNUMBER('Operating costs'!$B$36),ISNUMBER('Operating costs'!$B$38),ISNUMBER('Operating costs'!$B$41),ISNUMBER('Operating costs'!$B$43),ISNUMBER('Operating costs'!$B$44),ISNUMBER('Operating costs'!$B$45),ISNUMBER('Operating costs'!$B$46),ISNUMBER('Operating costs'!$B$47),ISNUMBER('Operating costs'!$B$48),ISNUMBER('Operating costs'!$B$49),ISNUMBER('Operating costs'!$B$52),ISNUMBER('Operating costs'!$B$64),ISNUMBER('Operating costs'!$B$65),ISNUMBER('Energy and charging'!$B$12),AND(ISNUMBER(1-'Energy and charging'!$B$12),1-'Energy and charging'!$B$12>=0,1-'Energy and charging'!$B$12<=1,OR(1-'Energy and charging'!$B$12=0,AND(ISNUMBER('Energy and charging'!$B$10),'Energy and charging'!$B$10>=0)),OR(1-'Energy and charging'!$B$12=1,AND(ISNUMBER('Energy and charging'!$B$11),'Energy and charging'!$B$11>=0))),ISNUMBER('Replacement plan'!$Y$7),ISNUMBER('Replacement plan'!$Z$7),'Replacement plan'!$Z$7>=0,ISNUMBER('Replacement plan'!$AA$7),'Replacement plan'!$AA$7>=0,'Replacement plan'!$AA$7=INT('Replacement plan'!$AA$7),ISNUMBER('Replacement plan'!$L$7))),'Operating costs'!$B$7>=0,'Operating costs'!$B$21>=0,'Operating costs'!$B$21<=1,'Operating costs'!$B$23>=0,'Operating costs'!$B$23<=1,'Operating costs'!$B$50>-1,'Operating costs'!$B$51>-1,'Operating costs'!$B$53>-1,'Operating costs'!$B$54>-1),IF(AND(ISNUMBER(IF('Replacement plan'!$AG$7="",'Operating costs'!$B$7,'Replacement plan'!$AG$7)),IF('Replacement plan'!$AG$7="",'Operating costs'!$B$7,'Replacement plan'!$AG$7)>=0,ISNUMBER(IF('Replacement plan'!$AH$7="",'Operating costs'!$B$7,'Replacement plan'!$AH$7)),IF('Replacement plan'!$AH$7="",'Operating costs'!$B$7,'Replacement plan'!$AH$7)>=0,'Operating costs'!$B$8>MAX(IF('Replacement plan'!$AG$7="",'Operating costs'!$B$7,'Replacement plan'!$AG$7),IF('Replacement plan'!$AH$7="",'Operating costs'!$B$7,'Replacement plan'!$AH$7))*'Operating costs'!$B$9),IF(AND(VLOOKUP($A8,'Fleet register'!$A$7:$S$106,10,FALSE)>=0,VLOOKUP($A8,'Fleet register'!$A$7:$S$106,10,FALSE)<=120,VLOOKUP($A8,'Fleet register'!$A$7:$S$106,10,FALSE)=INT(VLOOKUP($A8,'Fleet register'!$A$7:$S$106,10,FALSE)),VLOOKUP($A8,'Fleet register'!$A$7:$S$106,15,FALSE)>=0,VLOOKUP($A8,'Fleet register'!$A$7:$S$106,16,FALSE)>=0,MIN('Operating costs'!$B$7,'Operating costs'!$B$8,'Operating costs'!$B$9,'Operating costs'!$B$10,'Operating costs'!$B$11,'Operating costs'!$B$19,'Operating costs'!$B$21,'Operating costs'!$B$23,'Operating costs'!$B$24,'Operating costs'!$B$25,'Operating costs'!$B$27,'Operating costs'!$B$29,'Operating costs'!$B$31,'Operating costs'!$B$33,'Operating costs'!$B$34,'Operating costs'!$B$35,'Operating costs'!$B$37,'Operating costs'!$B$39,'Operating costs'!$B$40,'Operating costs'!$B$42,'Operating costs'!$B$66,'Operating costs'!$B$67)>=0,OR(D8<>"EV",E8=120,AND(MIN('Operating costs'!$B$12,'Operating costs'!$B$13,'Operating costs'!$B$14,'Operating costs'!$B$15,'Operating costs'!$B$16,'Operating costs'!$B$17,'Operating costs'!$B$18,'Operating costs'!$B$20,'Operating costs'!$B$22,'Operating costs'!$B$26,'Operating costs'!$B$28,'Operating costs'!$B$30,'Operating costs'!$B$32,'Operating costs'!$B$36,'Operating costs'!$B$38,'Operating costs'!$B$41,'Operating costs'!$B$43,'Operating costs'!$B$44,'Operating costs'!$B$45,'Operating costs'!$B$46,'Operating costs'!$B$47,'Operating costs'!$B$48,'Operating costs'!$B$49,'Operating costs'!$B$64,'Operating costs'!$B$65)>=0,'Operating costs'!$B$20<=1,'Operating costs'!$B$22<=1,'Operating costs'!$B$45<1,'Operating costs'!$B$46<1,'Operating costs'!$B$52>-1))),"Complete","Invalid operating limits"),"Invalid fuel override"),"Missing/invalid operating input")))))),"Invalid input type") -> Complete | Q8: =IF(C8=0,"Excluded",IF(P8<>"Complete",P8,IF(OR('Replacement plan'!$AD$7<120-E8,AND(D8="EV",E8<120,OR('Replacement plan'!$AC$7<120-E8,'Replacement plan'!$I$7="No",AND(ISNUMBER(AF8),AE8>AF8),AI8>V8*(1-'Operating costs'!$B$46)^MAX(0,AB8-1)*(1-'Operating costs'!$B$45),AC8>'Operating costs'!$B$18,AND(T8<1,OR(AG8<=0,AND(ISNUMBER(AH8),AG8>AH8))),'Replacement plan'!$L$7>INDEX(Products!$H$7:$H$13,MATCH('Replacement plan'!$B$7,Products!$A$7:$A$13,0))))),"Fails entered limits",IF(AND(D8="EV",E8<120,OR(NOT(ISNUMBER(VLOOKUP($A8,'Fleet register'!$A$7:$S$106,7,FALSE))),NOT(ISNUMBER(VLOOKUP($A8,'Fleet register'!$A$7:$S$106,8,FALSE))),NOT(ISNUMBER(AF8)),'Replacement plan'!$I$7<>"Yes",NOT(ISNUMBER(AH8)),'Operating costs'!$B$59<>"Yes",'Operating costs'!$B$58<>"Yes")),"Unverified","Within entered limits")))) -> Within entered limits | R8: =IF(C8=0,0,VLOOKUP($A8,'Fleet register'!$A$7:$S$106,6,FALSE)) -> 300 | S8: =IF(C8=0,0,VLOOKUP($A8,'Fleet register'!$A$7:$S$106,5,FALSE)) -> 150 | T8: =IF(D8="EV",'Energy and charging'!$B$12,0) -> 0 | U8: =IFERROR(IF(C8=0,0,IF(D8="EV",IF('Replacement plan'!$F$7="",INDEX(Products!$E$7:$E$13,MATCH('Replacement plan'!$B$7,Products!$A$7:$A$13,0)),'Replacement plan'!$F$7)/IF('Replacement plan'!$G$7="Battery",1-'Operating costs'!$B$44,1),0)),"n.a.") -> 0 | V8: =IFERROR(IF(C8=0,0,IF(D8="EV",IF('Replacement plan'!$E$7="",INDEX(Products!$D$7:$D$13,MATCH('Replacement plan'!$B$7,Products!$A$7:$A$13,0)),'Replacement plan'!$E$7),0)),"n.a.") -> 0 | W8: =IF(C8=0,0,IF(AND(P8="Complete",D8="EV",E8<120),IF(T8=0,0,ROUNDUP(T8*(R8-'Operating costs'!$B$41)*(S8*U8+'Operating costs'!$B$48/(1-'Operating costs'!$B$44))/(V8*'Operating costs'!$B$47/(1-'Operating costs'!$B$44)-T8*'Operating costs'!$B$12*U8),0)),0)) -> 0 | X8: =IF(C8=0,0,IF(AND(P8="Complete",D8="EV",E8<120),(R8-'Operating costs'!$B$41)*(S8*U8+'Operating costs'!$B$48/(1-'Operating costs'!$B$44))+W8*'Operating costs'!$B$12*U8,0)) -> 0 | Y8: =IF(AND(C8=1,D8="EV",E8<120),AI8/(1-'Operating costs'!$B$44)*(1-T8),0) -> 0 | Z8: =IF(AND(C8=1,D8="EV",E8<120,T8<1,AG8>0),Y8/AG8,0) -> 0 | AA8: =IF(C8=0,0,IF(P8="Complete",((S8*(R8-'Operating costs'!$B$40))+ROUNDUP(S8*(R8-'Operating costs'!$B$40)*IF('Replacement plan'!$AH$7="",'Operating costs'!$B$7,'Replacement plan'!$AH$7)/('Operating costs'!$B$8-'Operating costs'!$B$9*IF('Replacement plan'!$AH$7="",'Operating costs'!$B$7,'Replacement plan'!$AH$7)),0)*'Operating costs'!$B$9)*IF('Replacement plan'!$AH$7="",'Operating costs'!$B$7,'Replacement plan'!$AH$7),"n.a.")) -> 4522.8 | AB8: =IF(D8="EV",(120-E8)/12,0) -> 0 | AC8: =IF(AND(C8=1,D8="EV",E8<120,T8>0),'Operating costs'!$B$12/'Operating costs'!$B$11*60+'Operating costs'!$B$13+'Operating costs'!$B$14+V8*'Operating costs'!$B$47/(1-'Operating costs'!$B$44)/'Replacement plan'!$L$7*60,0) -> 0 | AD8: ='Replacement plan'!$B$7 -> ChengLong L2EV | AE8: =IF(C8=0,0,VLOOKUP($A8,'Fleet register'!$A$7:$S$106,8,FALSE)) -> 1200 | AF8: =IF('Replacement plan'!$H$7="","n.a.",'Replacement plan'!$H$7) -> n.a. | AG8: ='Replacement plan'!$J$7 -> 22 | AH8: =IFERROR(IF(D8="EV",IF('Replacement plan'!$K$7="AC",IF(ISNUMBER(INDEX(Products!$G$7:$G$13,MATCH('Replacement plan'!$B$7,Products!$A$7:$A$13,0))),INDEX(Products!$G$7:$G$13,MATCH('Replacement plan'!$B$7,Products!$A$7:$A$13,0)),"n.a."),IF(ISNUMBER(INDEX(Products!$H$7:$H$13,MATCH('Replacement plan'!$B$7,Products!$A$7:$A$13,0))),INDEX(Products!$H$7:$H$13,MATCH('Replacement plan'!$B$7,Products!$A$7:$A$13,0)),"n.a.")),0),"n.a.") -> 0 | AI8: =IF(AND(C8=1,D8="EV",E8<120),(VLOOKUP($A8,'Fleet register'!$A$7:$S$106,7,FALSE)+IF(T8>0,'Operating costs'!$B$12,0))*U8*(1-'Operating costs'!$B$44)+'Operating costs'!$B$49,0) -> 0 | AJ8: =IF(D8="EV",'Energy and charging'!$B$50,0) -> 0 | AK8: =EDATE('Operating costs'!$B$63,E8) -> 46298 | AL8: =IFERROR(IF(D8="EV",INDEX(Products!$B$7:$B$13,MATCH('Replacement plan'!$B$7,Products!$A$7:$A$13,0)),0),"n.a.") -> 0 | AM8: ='Replacement plan'!$K$7 -> DC | AN8: ='Replacement plan'!$AE$7 -> Assumed | AO8: =IF(AND(C8=1,D8="EV",E8<120),(R8-'Operating costs'!$B$41)*S8+W8*'Operating costs'!$B$12,0) -> 0 | AP8: =IF(AND(C8=1,D8="EV",E8<120),IF('Operating costs'!$B$68="Hong Seh 200k average",AO8*IFERROR(INDEX(Products!$P$7:$P$13,MATCH(AD8,Products!$A$7:$A$13,0)),"n.a."),'Operating costs'!$B$26),0) -> 0 | AQ8: =IF(D8="EV",'Operating costs'!$B$68,"Not applicable") -> Not applicable
A9: ='Replacement plan'!A7 -> T001 | B9: 2 | C9: =IF(COUNTIFS('Fleet register'!$A$7:$A$106,$A9)=1,VLOOKUP($A9,'Fleet register'!$A$7:$S$106,2,FALSE),0) -> 1 | D9: =IF('Replacement plan'!$O$7="EV","EV","ICE") -> EV | E9: =IF(C9=0,0,IF('Replacement plan'!$P$7="",IF('Replacement plan'!$O$7="Keep ICE",IF('Replacement plan'!$M$7="",VLOOKUP($A9,'Fleet register'!$A$7:$S$106,10,FALSE),'Replacement plan'!$M$7),0),'Replacement plan'!$P$7)) -> 0 | F9: =IF(C9=0,0,VLOOKUP($A9,'Fleet register'!$A$7:$S$106,11,FALSE)) -> 24000 | G9: =IFERROR(IF(C9=0,0,IF(E9=120,0,IF(D9="ICE",'Replacement plan'!$C$7,IF('Replacement plan'!$D$7="",INDEX(Products!$I$7:$I$13,MATCH('Replacement plan'!$B$7,Products!$A$7:$A$13,0))+'Operating costs'!$B$57,'Replacement plan'!$D$7))*(1+'Operating costs'!$B$50)^(E9/12))),"n.a.") -> 171800 | H9: =IFERROR(IF(C9=0,0,IF('Replacement plan'!$U$7<>"",'Replacement plan'!$U$7,IF(E9=0,F9,VLOOKUP($A9,'Fleet register'!$A$7:$S$106,12,FALSE)+VLOOKUP($A9,'Fleet register'!$A$7:$S$106,13,FALSE)*MAX(0,VLOOKUP($A9,'Fleet register'!$A$7:$S$106,10,FALSE)-E9)/VLOOKUP($A9,'Fleet register'!$A$7:$S$106,14,FALSE)))),"n.a.") -> 24000 | I9: =IF(C9=0,0,IF(E9=120,0,'Replacement plan'!$Q$7)) -> 8000 | J9: =IF(C9=0,0,IF(P9="Complete",((S9*(R9-'Operating costs'!$B$39))+ROUNDUP(S9*(R9-'Operating costs'!$B$39)*IF('Replacement plan'!$AG$7="",'Operating costs'!$B$7,'Replacement plan'!$AG$7)/('Operating costs'!$B$8-'Operating costs'!$B$9*IF('Replacement plan'!$AG$7="",'Operating costs'!$B$7,'Replacement plan'!$AG$7)),0)*'Operating costs'!$B$9)*IF('Replacement plan'!$AG$7="",'Operating costs'!$B$7,'Replacement plan'!$AG$7)*('Energy and charging'!$B$9*'Energy and charging'!$B$7+(1-'Energy and charging'!$B$9)*'Energy and charging'!$B$8)*'Operating costs'!$B$23,"n.a.")) -> 9045.6 | K9: =IF(C9=0,0,IF(P9="Complete",SUM('Operating costs'!$B$24,'Operating costs'!$B$27,'Operating costs'!$B$29,'Operating costs'!$B$31,'Operating costs'!$B$33,'Operating costs'!$B$34,'Operating costs'!$B$37,'Replacement plan'!$W$7)+'Operating costs'!$B$39*'Operating costs'!$B$42+ROUNDUP(S9*(R9-'Operating costs'!$B$39)*IF('Replacement plan'!$AG$7="",'Operating costs'!$B$7,'Replacement plan'!$AG$7)/('Operating costs'!$B$8-'Operating costs'!$B$9*IF('Replacement plan'!$AG$7="",'Operating costs'!$B$7,'Replacement plan'!$AG$7)),0)*('Operating costs'!$B$9/'Operating costs'!$B$11+'Operating costs'!$B$10/60)*'Operating costs'!$B$19*'Operating costs'!$B$21,"n.a.")) -> 9105.75 | L9: =IF(C9=0,0,IF(P9="Complete",IF(D9="EV",X9*((1-T9)*'Energy and charging'!$B$10+T9*'Energy and charging'!$B$11)*'Operating costs'!$B$22,AA9*('Energy and charging'!$B$9*'Energy and charging'!$B$7+(1-'Energy and charging'!$B$9)*'Energy and charging'!$B$8)*'Operating costs'!$B$23),"n.a.")) -> 6111.2286 | M9: =IF(C9=0,0,IF(P9="Complete",IF(D9="ICE",SUM('Operating costs'!$B$25,'Operating costs'!$B$27,'Operating costs'!$B$29,'Operating costs'!$B$31,'Operating costs'!$B$33,'Operating costs'!$B$35,'Operating costs'!$B$37,'Replacement plan'!$X$7)+'Operating costs'!$B$40*'Operating costs'!$B$42+ROUNDUP(S9*(R9-'Operating costs'!$B$40)*IF('Replacement plan'!$AH$7="",'Operating costs'!$B$7,'Replacement plan'!$AH$7)/('Operating costs'!$B$8-'Operating costs'!$B$9*IF('Replacement plan'!$AH$7="",'Operating costs'!$B$7,'Replacement plan'!$AH$7)),0)*('Operating costs'!$B$9/'Operating costs'!$B$11+'Operating costs'!$B$10/60)*'Operating costs'!$B$19*'Operating costs'!$B$21,SUM(AP9,'Operating costs'!$B$28,'Operating costs'!$B$30,'Operating costs'!$B$32,'Operating costs'!$B$33,'Operating costs'!$B$36,'Operating costs'!$B$38,'Replacement plan'!$Y$7)+'Operating costs'!$B$41*'Operating costs'!$B$43+W9*'Operating costs'!$B$15+(T9*X9/'Replacement plan'!$L$7+W9*('Operating costs'!$B$12/'Operating costs'!$B$11+('Operating costs'!$B$13+'Operating costs'!$B$14)/60)+(R9-'Operating costs'!$B$41)*(IF(T9<1,'Operating costs'!$B$16,0)+'Operating costs'!$B$17)/60)*'Operating costs'!$B$19*'Operating costs'!$B$20),"n.a.")) -> 9525.623 | N9: =IF(AND(C9=1,D9="EV",E9<120,E9+'Replacement plan'!$AA$7<=120),'Replacement plan'!$Z$7,0) -> 0 | O9: =E9+'Replacement plan'!$AA$7 -> 0 | P9: =IFERROR(IF(C9=0,"Excluded",IF(OR(COUNTIFS('Fleet register'!$A$7:$A$106,A9)<>1,COUNTIFS('Replacement plan'!$A$7:$A$106,A9)<>1),"Duplicate/missing ID",IF(NOT(AND(ISNUMBER(VLOOKUP($A9,'Fleet register'!$A$7:$S$106,5,FALSE)),ISNUMBER(VLOOKUP($A9,'Fleet register'!$A$7:$S$106,6,FALSE)),ISNUMBER(VLOOKUP($A9,'Fleet register'!$A$7:$S$106,10,FALSE)),ISNUMBER(VLOOKUP($A9,'Fleet register'!$A$7:$S$106,11,FALSE)),ISNUMBER(VLOOKUP($A9,'Fleet register'!$A$7:$S$106,12,FALSE)),ISNUMBER(VLOOKUP($A9,'Fleet register'!$A$7:$S$106,13,FALSE)),ISNUMBER(VLOOKUP($A9,'Fleet register'!$A$7:$S$106,14,FALSE)),VLOOKUP($A9,'Fleet register'!$A$7:$S$106,14,FALSE)>0,ISNUMBER('Replacement plan'!$C$7),OR(E9=120,ISNUMBER('Replacement plan'!$Q$7)),ISNUMBER(E9))),"Missing vehicle input",IF(OR(E9<0,E9>VLOOKUP($A9,'Fleet register'!$A$7:$S$106,10,FALSE),E9>120,E9<>INT(E9),VLOOKUP($A9,'Fleet register'!$A$7:$S$106,6,FALSE)<=0,VLOOKUP($A9,'Fleet register'!$A$7:$S$106,6,FALSE)>366,VLOOKUP($A9,'Fleet register'!$A$7:$S$106,5,FALSE)<0,VLOOKUP($A9,'Fleet register'!$A$7:$S$106,11,FALSE)<0,I9<0,'Operating costs'!$B$8<='Operating costs'!$B$7*'Operating costs'!$B$9,'Operating costs'!$B$11<=0,'Operating costs'!$B$39>R9,'Operating costs'!$B$40>R9,'Operating costs'!$B$41>R9,NOT(OR('Replacement plan'!$O$7="Keep ICE",'Replacement plan'!$O$7="New ICE",'Replacement plan'!$O$7="EV"))),"Invalid vehicle input",IF(AND(D9="EV",E9<120,OR(NOT(ISNUMBER(U9)),NOT(ISNUMBER(V9)),V9<=0,T9<0,T9>1,'Replacement plan'!$L$7<=0,'Operating costs'!$B$44<0,'Operating costs'!$B$44>=1,'Operating costs'!$B$47<=0,'Operating costs'!$B$47>1,V9*'Operating costs'!$B$47/(1-'Operating costs'!$B$44)<=T9*'Operating costs'!$B$12*U9,AND('Replacement plan'!$Z$7>0,OR('Replacement plan'!$AB$7<>"Yes",'Operating costs'!$B$62<>"Gross")))),"Invalid EV input",IF(AND(ISNUMBER('Operating costs'!$B$7),ISNUMBER('Operating costs'!$B$8),ISNUMBER('Operating costs'!$B$9),ISNUMBER('Operating costs'!$B$10),ISNUMBER('Operating costs'!$B$11),ISNUMBER('Operating costs'!$B$19),ISNUMBER('Operating costs'!$B$21),ISNUMBER('Operating costs'!$B$23),ISNUMBER('Operating costs'!$B$24),ISNUMBER('Operating costs'!$B$25),ISNUMBER('Operating costs'!$B$27),ISNUMBER('Operating costs'!$B$29),ISNUMBER('Operating costs'!$B$31),ISNUMBER('Operating costs'!$B$33),ISNUMBER('Operating costs'!$B$34),ISNUMBER('Operating costs'!$B$35),ISNUMBER('Operating costs'!$B$37),ISNUMBER('Operating costs'!$B$39),ISNUMBER('Operating costs'!$B$40),ISNUMBER('Operating costs'!$B$42),ISNUMBER('Operating costs'!$B$50),ISNUMBER('Operating costs'!$B$51),ISNUMBER('Operating costs'!$B$53),ISNUMBER('Operating costs'!$B$54),ISNUMBER('Operating costs'!$B$66),ISNUMBER('Operating costs'!$B$67),AND(ISNUMBER('Energy and charging'!$B$9),'Energy and charging'!$B$9>=0,'Energy and charging'!$B$9<=1,OR('Energy and charging'!$B$9=0,AND(ISNUMBER('Energy and charging'!$B$7),'Energy and charging'!$B$7>=0)),OR('Energy and charging'!$B$9=1,AND(ISNUMBER('Energy and charging'!$B$8),'Energy and charging'!$B$8>=0))),ISNUMBER(VLOOKUP($A9,'Fleet register'!$A$7:$S$106,15,FALSE)),ISNUMBER(VLOOKUP($A9,'Fleet register'!$A$7:$S$106,16,FALSE)),ISNUMBER('Replacement plan'!$W$7),ISNUMBER('Replacement plan'!$X$7),OR(E9=120,AND(ISNUMBER(G9),G9>=0)),ISNUMBER(H9),H9>=0,OR(D9<>"EV",E9=120,AND(ISNUMBER('Operating costs'!$B$12),ISNUMBER('Operating costs'!$B$13),ISNUMBER('Operating costs'!$B$14),ISNUMBER('Operating costs'!$B$15),ISNUMBER('Operating costs'!$B$16),ISNUMBER('Operating costs'!$B$17),ISNUMBER('Operating costs'!$B$18),ISNUMBER('Operating costs'!$B$20),ISNUMBER('Operating costs'!$B$22),OR(AND('Operating costs'!$B$68="Annual override",ISNUMBER('Operating costs'!$B$26)),AND('Operating costs'!$B$68="Hong Seh 200k average",ISNUMBER(IFERROR(INDEX(Products!$P$7:$P$13,MATCH(AD9,Products!$A$7:$A$13,0)),"")))),ISNUMBER('Operating costs'!$B$28),ISNUMBER('Operating costs'!$B$30),ISNUMBER('Operating costs'!$B$32),ISNUMBER('Operating costs'!$B$36),ISNUMBER('Operating costs'!$B$38),ISNUMBER('Operating costs'!$B$41),ISNUMBER('Operating costs'!$B$43),ISNUMBER('Operating costs'!$B$44),ISNUMBER('Operating costs'!$B$45),ISNUMBER('Operating costs'!$B$46),ISNUMBER('Operating costs'!$B$47),ISNUMBER('Operating costs'!$B$48),ISNUMBER('Operating costs'!$B$49),ISNUMBER('Operating costs'!$B$52),ISNUMBER('Operating costs'!$B$64),ISNUMBER('Operating costs'!$B$65),ISNUMBER('Energy and charging'!$B$12),AND(ISNUMBER(1-'Energy and charging'!$B$12),1-'Energy and charging'!$B$12>=0,1-'Energy and charging'!$B$12<=1,OR(1-'Energy and charging'!$B$12=0,AND(ISNUMBER('Energy and charging'!$B$10),'Energy and charging'!$B$10>=0)),OR(1-'Energy and charging'!$B$12=1,AND(ISNUMBER('Energy and charging'!$B$11),'Energy and charging'!$B$11>=0))),ISNUMBER('Replacement plan'!$Y$7),ISNUMBER('Replacement plan'!$Z$7),'Replacement plan'!$Z$7>=0,ISNUMBER('Replacement plan'!$AA$7),'Replacement plan'!$AA$7>=0,'Replacement plan'!$AA$7=INT('Replacement plan'!$AA$7),ISNUMBER('Replacement plan'!$L$7))),'Operating costs'!$B$7>=0,'Operating costs'!$B$21>=0,'Operating costs'!$B$21<=1,'Operating costs'!$B$23>=0,'Operating costs'!$B$23<=1,'Operating costs'!$B$50>-1,'Operating costs'!$B$51>-1,'Operating costs'!$B$53>-1,'Operating costs'!$B$54>-1),IF(AND(ISNUMBER(IF('Replacement plan'!$AG$7="",'Operating costs'!$B$7,'Replacement plan'!$AG$7)),IF('Replacement plan'!$AG$7="",'Operating costs'!$B$7,'Replacement plan'!$AG$7)>=0,ISNUMBER(IF('Replacement plan'!$AH$7="",'Operating costs'!$B$7,'Replacement plan'!$AH$7)),IF('Replacement plan'!$AH$7="",'Operating costs'!$B$7,'Replacement plan'!$AH$7)>=0,'Operating costs'!$B$8>MAX(IF('Replacement plan'!$AG$7="",'Operating costs'!$B$7,'Replacement plan'!$AG$7),IF('Replacement plan'!$AH$7="",'Operating costs'!$B$7,'Replacement plan'!$AH$7))*'Operating costs'!$B$9),IF(AND(VLOOKUP($A9,'Fleet register'!$A$7:$S$106,10,FALSE)>=0,VLOOKUP($A9,'Fleet register'!$A$7:$S$106,10,FALSE)<=120,VLOOKUP($A9,'Fleet register'!$A$7:$S$106,10,FALSE)=INT(VLOOKUP($A9,'Fleet register'!$A$7:$S$106,10,FALSE)),VLOOKUP($A9,'Fleet register'!$A$7:$S$106,15,FALSE)>=0,VLOOKUP($A9,'Fleet register'!$A$7:$S$106,16,FALSE)>=0,MIN('Operating costs'!$B$7,'Operating costs'!$B$8,'Operating costs'!$B$9,'Operating costs'!$B$10,'Operating costs'!$B$11,'Operating costs'!$B$19,'Operating costs'!$B$21,'Operating costs'!$B$23,'Operating costs'!$B$24,'Operating costs'!$B$25,'Operating costs'!$B$27,'Operating costs'!$B$29,'Operating costs'!$B$31,'Operating costs'!$B$33,'Operating costs'!$B$34,'Operating costs'!$B$35,'Operating costs'!$B$37,'Operating costs'!$B$39,'Operating costs'!$B$40,'Operating costs'!$B$42,'Operating costs'!$B$66,'Operating costs'!$B$67)>=0,OR(D9<>"EV",E9=120,AND(MIN('Operating costs'!$B$12,'Operating costs'!$B$13,'Operating costs'!$B$14,'Operating costs'!$B$15,'Operating costs'!$B$16,'Operating costs'!$B$17,'Operating costs'!$B$18,'Operating costs'!$B$20,'Operating costs'!$B$22,'Operating costs'!$B$26,'Operating costs'!$B$28,'Operating costs'!$B$30,'Operating costs'!$B$32,'Operating costs'!$B$36,'Operating costs'!$B$38,'Operating costs'!$B$41,'Operating costs'!$B$43,'Operating costs'!$B$44,'Operating costs'!$B$45,'Operating costs'!$B$46,'Operating costs'!$B$47,'Operating costs'!$B$48,'Operating costs'!$B$49,'Operating costs'!$B$64,'Operating costs'!$B$65)>=0,'Operating costs'!$B$20<=1,'Operating costs'!$B$22<=1,'Operating costs'!$B$45<1,'Operating costs'!$B$46<1,'Operating costs'!$B$52>-1))),"Complete","Invalid operating limits"),"Invalid fuel override"),"Missing/invalid operating input")))))),"Invalid input type") -> Complete | Q9: =IF(C9=0,"Excluded",IF(P9<>"Complete",P9,IF(OR('Replacement plan'!$AD$7<120-E9,AND(D9="EV",E9<120,OR('Replacement plan'!$AC$7<120-E9,'Replacement plan'!$I$7="No",AND(ISNUMBER(AF9),AE9>AF9),AI9>V9*(1-'Operating costs'!$B$46)^MAX(0,AB9-1)*(1-'Operating costs'!$B$45),AC9>'Operating costs'!$B$18,AND(T9<1,OR(AG9<=0,AND(ISNUMBER(AH9),AG9>AH9))),'Replacement plan'!$L$7>INDEX(Products!$H$7:$H$13,MATCH('Replacement plan'!$B$7,Products!$A$7:$A$13,0))))),"Fails entered limits",IF(AND(D9="EV",E9<120,OR(NOT(ISNUMBER(VLOOKUP($A9,'Fleet register'!$A$7:$S$106,7,FALSE))),NOT(ISNUMBER(VLOOKUP($A9,'Fleet register'!$A$7:$S$106,8,FALSE))),NOT(ISNUMBER(AF9)),'Replacement plan'!$I$7<>"Yes",NOT(ISNUMBER(AH9)),'Operating costs'!$B$59<>"Yes",'Operating costs'!$B$58<>"Yes")),"Unverified","Within entered limits")))) -> Fails entered limits | R9: =IF(C9=0,0,VLOOKUP($A9,'Fleet register'!$A$7:$S$106,6,FALSE)) -> 300 | S9: =IF(C9=0,0,VLOOKUP($A9,'Fleet register'!$A$7:$S$106,5,FALSE)) -> 150 | T9: =IF(D9="EV",'Energy and charging'!$B$12,0) -> 0.2 | U9: =IFERROR(IF(C9=0,0,IF(D9="EV",IF('Replacement plan'!$F$7="",INDEX(Products!$E$7:$E$13,MATCH('Replacement plan'!$B$7,Products!$A$7:$A$13,0)),'Replacement plan'!$F$7)/IF('Replacement plan'!$G$7="Battery",1-'Operating costs'!$B$44,1),0)),"n.a.") -> 0.30041053 | V9: =IFERROR(IF(C9=0,0,IF(D9="EV",IF('Replacement plan'!$E$7="",INDEX(Products!$D$7:$D$13,MATCH('Replacement plan'!$B$7,Products!$A$7:$A$13,0)),'Replacement plan'!$E$7),0)),"n.a.") -> 86.55 | W9: =IF(C9=0,0,IF(AND(P9="Complete",D9="EV",E9<120),IF(T9=0,0,ROUNDUP(T9*(R9-'Operating costs'!$B$41)*(S9*U9+'Operating costs'!$B$48/(1-'Operating costs'!$B$44))/(V9*'Operating costs'!$B$47/(1-'Operating costs'!$B$44)-T9*'Operating costs'!$B$12*U9),0)),0)) -> 48 | X9: =IF(C9=0,0,IF(AND(P9="Complete",D9="EV",E9<120),(R9-'Operating costs'!$B$41)*(S9*U9+'Operating costs'!$B$48/(1-'Operating costs'!$B$44))+W9*'Operating costs'!$B$12*U9,0)) -> 13633.831 | Y9: =IF(AND(C9=1,D9="EV",E9<120),AI9/(1-'Operating costs'!$B$44)*(1-T9),0) -> 41.576817 | Z9: =IF(AND(C9=1,D9="EV",E9<120,T9<1,AG9>0),Y9/AG9,0) -> 1.8898553 | AA9: =IF(C9=0,0,IF(P9="Complete",((S9*(R9-'Operating costs'!$B$40))+ROUNDUP(S9*(R9-'Operating costs'!$B$40)*IF('Replacement plan'!$AH$7="",'Operating costs'!$B$7,'Replacement plan'!$AH$7)/('Operating costs'!$B$8-'Operating costs'!$B$9*IF('Replacement plan'!$AH$7="",'Operating costs'!$B$7,'Replacement plan'!$AH$7)),0)*'Operating costs'!$B$9)*IF('Replacement plan'!$AH$7="",'Operating costs'!$B$7,'Replacement plan'!$AH$7),"n.a.")) -> 4522.8 | AB9: =IF(D9="EV",(120-E9)/12,0) -> 10 | AC9: =IF(AND(C9=1,D9="EV",E9<120,T9>0),'Operating costs'!$B$12/'Operating costs'!$B$11*60+'Operating costs'!$B$13+'Operating costs'!$B$14+V9*'Operating costs'!$B$47/(1-'Operating costs'!$B$44)/'Replacement plan'!$L$7*60,0) -> 111.325 | AD9: ='Replacement plan'!$B$7 -> ChengLong L2EV | AE9: =IF(C9=0,0,VLOOKUP($A9,'Fleet register'!$A$7:$S$106,8,FALSE)) -> 1200 | AF9: =IF('Replacement plan'!$H$7="","n.a.",'Replacement plan'!$H$7) -> n.a. | AG9: ='Replacement plan'!$J$7 -> 22 | AH9: =IFERROR(IF(D9="EV",IF('Replacement plan'!$K$7="AC",IF(ISNUMBER(INDEX(Products!$G$7:$G$13,MATCH('Replacement plan'!$B$7,Products!$A$7:$A$13,0))),INDEX(Products!$G$7:$G$13,MATCH('Replacement plan'!$B$7,Products!$A$7:$A$13,0)),"n.a."),IF(ISNUMBER(INDEX(Products!$H$7:$H$13,MATCH('Replacement plan'!$B$7,Products!$A$7:$A$13,0))),INDEX(Products!$H$7:$H$13,MATCH('Replacement plan'!$B$7,Products!$A$7:$A$13,0)),"n.a.")),0),"n.a.") -> 120 | AI9: =IF(AND(C9=1,D9="EV",E9<120),(VLOOKUP($A9,'Fleet register'!$A$7:$S$106,7,FALSE)+IF(T9>0,'Operating costs'!$B$12,0))*U9*(1-'Operating costs'!$B$44)+'Operating costs'!$B$49,0) -> 46.773919 | AJ9: =IF(D9="EV",'Energy and charging'!$B$50,0) -> 44 | AK9: =EDATE('Operating costs'!$B$63,E9) -> 46298 | AL9: =IFERROR(IF(D9="EV",INDEX(Products!$B$7:$B$13,MATCH('Replacement plan'!$B$7,Products!$A$7:$A$13,0)),0),"n.a.") -> 5000 | AM9: ='Replacement plan'!$K$7 -> DC | AN9: ='Replacement plan'!$AE$7 -> Assumed | AO9: =IF(AND(C9=1,D9="EV",E9<120),(R9-'Operating costs'!$B$41)*S9+W9*'Operating costs'!$B$12,0) -> 45384 | AP9: =IF(AND(C9=1,D9="EV",E9<120),IF('Operating costs'!$B$68="Hong Seh 200k average",AO9*IFERROR(INDEX(Products!$P$7:$P$13,MATCH(AD9,Products!$A$7:$A$13,0)),"n.a."),'Operating costs'!$B$26),0) -> 745.4322 | AQ9: =IF(D9="EV",'Operating costs'!$B$68,"Not applicable") -> Hong Seh 200k average
A10: ='Replacement plan'!A7 -> T001 | B10: 3 | C10: =IF(COUNTIFS('Fleet register'!$A$7:$A$106,$A10)=1,VLOOKUP($A10,'Fleet register'!$A$7:$S$106,2,FALSE),0) -> 1 | D10: =IF('Replacement plan'!$R$7="EV","EV","ICE") -> EV | E10: =IF(C10=0,0,IF('Replacement plan'!$S$7="",IF('Replacement plan'!$R$7="Keep ICE",IF('Replacement plan'!$M$7="",VLOOKUP($A10,'Fleet register'!$A$7:$S$106,10,FALSE),'Replacement plan'!$M$7),0),'Replacement plan'!$S$7)) -> 0 | F10: =IF(C10=0,0,VLOOKUP($A10,'Fleet register'!$A$7:$S$106,11,FALSE)) -> 24000 | G10: =IFERROR(IF(C10=0,0,IF(E10=120,0,IF(D10="ICE",'Replacement plan'!$C$7,IF('Replacement plan'!$D$7="",INDEX(Products!$I$7:$I$13,MATCH('Replacement plan'!$B$7,Products!$A$7:$A$13,0))+'Operating costs'!$B$57,'Replacement plan'!$D$7))*(1+'Operating costs'!$B$50)^(E10/12))),"n.a.") -> 171800 | H10: =IFERROR(IF(C10=0,0,IF('Replacement plan'!$V$7<>"",'Replacement plan'!$V$7,IF(E10=0,F10,VLOOKUP($A10,'Fleet register'!$A$7:$S$106,12,FALSE)+VLOOKUP($A10,'Fleet register'!$A$7:$S$106,13,FALSE)*MAX(0,VLOOKUP($A10,'Fleet register'!$A$7:$S$106,10,FALSE)-E10)/VLOOKUP($A10,'Fleet register'!$A$7:$S$106,14,FALSE)))),"n.a.") -> 24000 | I10: =IF(C10=0,0,IF(E10=120,0,'Replacement plan'!$T$7)) -> 8000 | J10: =IF(C10=0,0,IF(P10="Complete",((S10*(R10-'Operating costs'!$B$39))+ROUNDUP(S10*(R10-'Operating costs'!$B$39)*IF('Replacement plan'!$AG$7="",'Operating costs'!$B$7,'Replacement plan'!$AG$7)/('Operating costs'!$B$8-'Operating costs'!$B$9*IF('Replacement plan'!$AG$7="",'Operating costs'!$B$7,'Replacement plan'!$AG$7)),0)*'Operating costs'!$B$9)*IF('Replacement plan'!$AG$7="",'Operating costs'!$B$7,'Replacement plan'!$AG$7)*('Energy and charging'!$C$9*'Energy and charging'!$C$7+(1-'Energy and charging'!$C$9)*'Energy and charging'!$C$8)*'Operating costs'!$B$23,"n.a.")) -> 9045.6 | K10: =IF(C10=0,0,IF(P10="Complete",SUM('Operating costs'!$B$24,'Operating costs'!$B$27,'Operating costs'!$B$29,'Operating costs'!$B$31,'Operating costs'!$B$33,'Operating costs'!$B$34,'Operating costs'!$B$37,'Replacement plan'!$W$7)+'Operating costs'!$B$39*'Operating costs'!$B$42+ROUNDUP(S10*(R10-'Operating costs'!$B$39)*IF('Replacement plan'!$AG$7="",'Operating costs'!$B$7,'Replacement plan'!$AG$7)/('Operating costs'!$B$8-'Operating costs'!$B$9*IF('Replacement plan'!$AG$7="",'Operating costs'!$B$7,'Replacement plan'!$AG$7)),0)*('Operating costs'!$B$9/'Operating costs'!$B$11+'Operating costs'!$B$10/60)*'Operating costs'!$B$19*'Operating costs'!$B$21,"n.a.")) -> 9105.75 | L10: =IF(C10=0,0,IF(P10="Complete",IF(D10="EV",X10*((1-T10)*'Energy and charging'!$C$10+T10*'Energy and charging'!$C$11)*'Operating costs'!$B$22,AA10*('Energy and charging'!$C$9*'Energy and charging'!$C$7+(1-'Energy and charging'!$C$9)*'Energy and charging'!$C$8)*'Operating costs'!$B$23),"n.a.")) -> 6111.2286 | M10: =IF(C10=0,0,IF(P10="Complete",IF(D10="ICE",SUM('Operating costs'!$B$25,'Operating costs'!$B$27,'Operating costs'!$B$29,'Operating costs'!$B$31,'Operating costs'!$B$33,'Operating costs'!$B$35,'Operating costs'!$B$37,'Replacement plan'!$X$7)+'Operating costs'!$B$40*'Operating costs'!$B$42+ROUNDUP(S10*(R10-'Operating costs'!$B$40)*IF('Replacement plan'!$AH$7="",'Operating costs'!$B$7,'Replacement plan'!$AH$7)/('Operating costs'!$B$8-'Operating costs'!$B$9*IF('Replacement plan'!$AH$7="",'Operating costs'!$B$7,'Replacement plan'!$AH$7)),0)*('Operating costs'!$B$9/'Operating costs'!$B$11+'Operating costs'!$B$10/60)*'Operating costs'!$B$19*'Operating costs'!$B$21,SUM(AP10,'Operating costs'!$B$28,'Operating costs'!$B$30,'Operating costs'!$B$32,'Operating costs'!$B$33,'Operating costs'!$B$36,'Operating costs'!$B$38,'Replacement plan'!$Y$7)+'Operating costs'!$B$41*'Operating costs'!$B$43+W10*'Operating costs'!$B$15+(T10*X10/'Replacement plan'!$L$7+W10*('Operating costs'!$B$12/'Operating costs'!$B$11+('Operating costs'!$B$13+'Operating costs'!$B$14)/60)+(R10-'Operating costs'!$B$41)*(IF(T10<1,'Operating costs'!$B$16,0)+'Operating costs'!$B$17)/60)*'Operating costs'!$B$19*'Operating costs'!$B$20),"n.a.")) -> 9525.623 | N10: =IF(AND(C10=1,D10="EV",E10<120,E10+'Replacement plan'!$AA$7<=120),'Replacement plan'!$Z$7,0) -> 0 | O10: =E10+'Replacement plan'!$AA$7 -> 0 | P10: =IFERROR(IF(C10=0,"Excluded",IF(OR(COUNTIFS('Fleet register'!$A$7:$A$106,A10)<>1,COUNTIFS('Replacement plan'!$A$7:$A$106,A10)<>1),"Duplicate/missing ID",IF(NOT(AND(ISNUMBER(VLOOKUP($A10,'Fleet register'!$A$7:$S$106,5,FALSE)),ISNUMBER(VLOOKUP($A10,'Fleet register'!$A$7:$S$106,6,FALSE)),ISNUMBER(VLOOKUP($A10,'Fleet register'!$A$7:$S$106,10,FALSE)),ISNUMBER(VLOOKUP($A10,'Fleet register'!$A$7:$S$106,11,FALSE)),ISNUMBER(VLOOKUP($A10,'Fleet register'!$A$7:$S$106,12,FALSE)),ISNUMBER(VLOOKUP($A10,'Fleet register'!$A$7:$S$106,13,FALSE)),ISNUMBER(VLOOKUP($A10,'Fleet register'!$A$7:$S$106,14,FALSE)),VLOOKUP($A10,'Fleet register'!$A$7:$S$106,14,FALSE)>0,ISNUMBER('Replacement plan'!$C$7),OR(E10=120,ISNUMBER('Replacement plan'!$T$7)),ISNUMBER(E10))),"Missing vehicle input",IF(OR(E10<0,E10>VLOOKUP($A10,'Fleet register'!$A$7:$S$106,10,FALSE),E10>120,E10<>INT(E10),VLOOKUP($A10,'Fleet register'!$A$7:$S$106,6,FALSE)<=0,VLOOKUP($A10,'Fleet register'!$A$7:$S$106,6,FALSE)>366,VLOOKUP($A10,'Fleet register'!$A$7:$S$106,5,FALSE)<0,VLOOKUP($A10,'Fleet register'!$A$7:$S$106,11,FALSE)<0,I10<0,'Operating costs'!$B$8<='Operating costs'!$B$7*'Operating costs'!$B$9,'Operating costs'!$B$11<=0,'Operating costs'!$B$39>R10,'Operating costs'!$B$40>R10,'Operating costs'!$B$41>R10,NOT(OR('Replacement plan'!$R$7="Keep ICE",'Replacement plan'!$R$7="New ICE",'Replacement plan'!$R$7="EV"))),"Invalid vehicle input",IF(AND(D10="EV",E10<120,OR(NOT(ISNUMBER(U10)),NOT(ISNUMBER(V10)),V10<=0,T10<0,T10>1,'Replacement plan'!$L$7<=0,'Operating costs'!$B$44<0,'Operating costs'!$B$44>=1,'Operating costs'!$B$47<=0,'Operating costs'!$B$47>1,V10*'Operating costs'!$B$47/(1-'Operating costs'!$B$44)<=T10*'Operating costs'!$B$12*U10,AND('Replacement plan'!$Z$7>0,OR('Replacement plan'!$AB$7<>"Yes",'Operating costs'!$B$62<>"Gross")))),"Invalid EV input",IF(AND(ISNUMBER('Operating costs'!$B$7),ISNUMBER('Operating costs'!$B$8),ISNUMBER('Operating costs'!$B$9),ISNUMBER('Operating costs'!$B$10),ISNUMBER('Operating costs'!$B$11),ISNUMBER('Operating costs'!$B$19),ISNUMBER('Operating costs'!$B$21),ISNUMBER('Operating costs'!$B$23),ISNUMBER('Operating costs'!$B$24),ISNUMBER('Operating costs'!$B$25),ISNUMBER('Operating costs'!$B$27),ISNUMBER('Operating costs'!$B$29),ISNUMBER('Operating costs'!$B$31),ISNUMBER('Operating costs'!$B$33),ISNUMBER('Operating costs'!$B$34),ISNUMBER('Operating costs'!$B$35),ISNUMBER('Operating costs'!$B$37),ISNUMBER('Operating costs'!$B$39),ISNUMBER('Operating costs'!$B$40),ISNUMBER('Operating costs'!$B$42),ISNUMBER('Operating costs'!$B$50),ISNUMBER('Operating costs'!$B$51),ISNUMBER('Operating costs'!$B$53),ISNUMBER('Operating costs'!$B$54),ISNUMBER('Operating costs'!$B$66),ISNUMBER('Operating costs'!$B$67),AND(ISNUMBER('Energy and charging'!$C$9),'Energy and charging'!$C$9>=0,'Energy and charging'!$C$9<=1,OR('Energy and charging'!$C$9=0,AND(ISNUMBER('Energy and charging'!$C$7),'Energy and charging'!$C$7>=0)),OR('Energy and charging'!$C$9=1,AND(ISNUMBER('Energy and charging'!$C$8),'Energy and charging'!$C$8>=0))),ISNUMBER(VLOOKUP($A10,'Fleet register'!$A$7:$S$106,15,FALSE)),ISNUMBER(VLOOKUP($A10,'Fleet register'!$A$7:$S$106,16,FALSE)),ISNUMBER('Replacement plan'!$W$7),ISNUMBER('Replacement plan'!$X$7),OR(E10=120,AND(ISNUMBER(G10),G10>=0)),ISNUMBER(H10),H10>=0,OR(D10<>"EV",E10=120,AND(ISNUMBER('Operating costs'!$B$12),ISNUMBER('Operating costs'!$B$13),ISNUMBER('Operating costs'!$B$14),ISNUMBER('Operating costs'!$B$15),ISNUMBER('Operating costs'!$B$16),ISNUMBER('Operating costs'!$B$17),ISNUMBER('Operating costs'!$B$18),ISNUMBER('Operating costs'!$B$20),ISNUMBER('Operating costs'!$B$22),OR(AND('Operating costs'!$B$68="Annual override",ISNUMBER('Operating costs'!$B$26)),AND('Operating costs'!$B$68="Hong Seh 200k average",ISNUMBER(IFERROR(INDEX(Products!$P$7:$P$13,MATCH(AD10,Products!$A$7:$A$13,0)),"")))),ISNUMBER('Operating costs'!$B$28),ISNUMBER('Operating costs'!$B$30),ISNUMBER('Operating costs'!$B$32),ISNUMBER('Operating costs'!$B$36),ISNUMBER('Operating costs'!$B$38),ISNUMBER('Operating costs'!$B$41),ISNUMBER('Operating costs'!$B$43),ISNUMBER('Operating costs'!$B$44),ISNUMBER('Operating costs'!$B$45),ISNUMBER('Operating costs'!$B$46),ISNUMBER('Operating costs'!$B$47),ISNUMBER('Operating costs'!$B$48),ISNUMBER('Operating costs'!$B$49),ISNUMBER('Operating costs'!$B$52),ISNUMBER('Operating costs'!$B$64),ISNUMBER('Operating costs'!$B$65),ISNUMBER('Energy and charging'!$C$12),AND(ISNUMBER(1-'Energy and charging'!$C$12),1-'Energy and charging'!$C$12>=0,1-'Energy and charging'!$C$12<=1,OR(1-'Energy and charging'!$C$12=0,AND(ISNUMBER('Energy and charging'!$C$10),'Energy and charging'!$C$10>=0)),OR(1-'Energy and charging'!$C$12=1,AND(ISNUMBER('Energy and charging'!$C$11),'Energy and charging'!$C$11>=0))),ISNUMBER('Replacement plan'!$Y$7),ISNUMBER('Replacement plan'!$Z$7),'Replacement plan'!$Z$7>=0,ISNUMBER('Replacement plan'!$AA$7),'Replacement plan'!$AA$7>=0,'Replacement plan'!$AA$7=INT('Replacement plan'!$AA$7),ISNUMBER('Replacement plan'!$L$7))),'Operating costs'!$B$7>=0,'Operating costs'!$B$21>=0,'Operating costs'!$B$21<=1,'Operating costs'!$B$23>=0,'Operating costs'!$B$23<=1,'Operating costs'!$B$50>-1,'Operating costs'!$B$51>-1,'Operating costs'!$B$53>-1,'Operating costs'!$B$54>-1),IF(AND(ISNUMBER(IF('Replacement plan'!$AG$7="",'Operating costs'!$B$7,'Replacement plan'!$AG$7)),IF('Replacement plan'!$AG$7="",'Operating costs'!$B$7,'Replacement plan'!$AG$7)>=0,ISNUMBER(IF('Replacement plan'!$AH$7="",'Operating costs'!$B$7,'Replacement plan'!$AH$7)),IF('Replacement plan'!$AH$7="",'Operating costs'!$B$7,'Replacement plan'!$AH$7)>=0,'Operating costs'!$B$8>MAX(IF('Replacement plan'!$AG$7="",'Operating costs'!$B$7,'Replacement plan'!$AG$7),IF('Replacement plan'!$AH$7="",'Operating costs'!$B$7,'Replacement plan'!$AH$7))*'Operating costs'!$B$9),IF(AND(VLOOKUP($A10,'Fleet register'!$A$7:$S$106,10,FALSE)>=0,VLOOKUP($A10,'Fleet register'!$A$7:$S$106,10,FALSE)<=120,VLOOKUP($A10,'Fleet register'!$A$7:$S$106,10,FALSE)=INT(VLOOKUP($A10,'Fleet register'!$A$7:$S$106,10,FALSE)),VLOOKUP($A10,'Fleet register'!$A$7:$S$106,15,FALSE)>=0,VLOOKUP($A10,'Fleet register'!$A$7:$S$106,16,FALSE)>=0,MIN('Operating costs'!$B$7,'Operating costs'!$B$8,'Operating costs'!$B$9,'Operating costs'!$B$10,'Operating costs'!$B$11,'Operating costs'!$B$19,'Operating costs'!$B$21,'Operating costs'!$B$23,'Operating costs'!$B$24,'Operating costs'!$B$25,'Operating costs'!$B$27,'Operating costs'!$B$29,'Operating costs'!$B$31,'Operating costs'!$B$33,'Operating costs'!$B$34,'Operating costs'!$B$35,'Operating costs'!$B$37,'Operating costs'!$B$39,'Operating costs'!$B$40,'Operating costs'!$B$42,'Operating costs'!$B$66,'Operating costs'!$B$67)>=0,OR(D10<>"EV",E10=120,AND(MIN('Operating costs'!$B$12,'Operating costs'!$B$13,'Operating costs'!$B$14,'Operating costs'!$B$15,'Operating costs'!$B$16,'Operating costs'!$B$17,'Operating costs'!$B$18,'Operating costs'!$B$20,'Operating costs'!$B$22,'Operating costs'!$B$26,'Operating costs'!$B$28,'Operating costs'!$B$30,'Operating costs'!$B$32,'Operating costs'!$B$36,'Operating costs'!$B$38,'Operating costs'!$B$41,'Operating costs'!$B$43,'Operating costs'!$B$44,'Operating costs'!$B$45,'Operating costs'!$B$46,'Operating costs'!$B$47,'Operating costs'!$B$48,'Operating costs'!$B$49,'Operating costs'!$B$64,'Operating costs'!$B$65)>=0,'Operating costs'!$B$20<=1,'Operating costs'!$B$22<=1,'Operating costs'!$B$45<1,'Operating costs'!$B$46<1,'Operating costs'!$B$52>-1))),"Complete","Invalid operating limits"),"Invalid fuel override"),"Missing/invalid operating input")))))),"Invalid input type") -> Complete | Q10: =IF(C10=0,"Excluded",IF(P10<>"Complete",P10,IF(OR('Replacement plan'!$AD$7<120-E10,AND(D10="EV",E10<120,OR('Replacement plan'!$AC$7<120-E10,'Replacement plan'!$I$7="No",AND(ISNUMBER(AF10),AE10>AF10),AI10>V10*(1-'Operating costs'!$B$46)^MAX(0,AB10-1)*(1-'Operating costs'!$B$45),AC10>'Operating costs'!$B$18,AND(T10<1,OR(AG10<=0,AND(ISNUMBER(AH10),AG10>AH10))),'Replacement plan'!$L$7>INDEX(Products!$H$7:$H$13,MATCH('Replacement plan'!$B$7,Products!$A$7:$A$13,0))))),"Fails entered limits",IF(AND(D10="EV",E10<120,OR(NOT(ISNUMBER(VLOOKUP($A10,'Fleet register'!$A$7:$S$106,7,FALSE))),NOT(ISNUMBER(VLOOKUP($A10,'Fleet register'!$A$7:$S$106,8,FALSE))),NOT(ISNUMBER(AF10)),'Replacement plan'!$I$7<>"Yes",NOT(ISNUMBER(AH10)),'Operating costs'!$B$59<>"Yes",'Operating costs'!$B$58<>"Yes")),"Unverified","Within entered limits")))) -> Fails entered limits | R10: =IF(C10=0,0,VLOOKUP($A10,'Fleet register'!$A$7:$S$106,6,FALSE)) -> 300 | S10: =IF(C10=0,0,VLOOKUP($A10,'Fleet register'!$A$7:$S$106,5,FALSE)) -> 150 | T10: =IF(D10="EV",'Energy and charging'!$C$12,0) -> 0.2 | U10: =IFERROR(IF(C10=0,0,IF(D10="EV",IF('Replacement plan'!$F$7="",INDEX(Products!$E$7:$E$13,MATCH('Replacement plan'!$B$7,Products!$A$7:$A$13,0)),'Replacement plan'!$F$7)/IF('Replacement plan'!$G$7="Battery",1-'Operating costs'!$B$44,1),0)),"n.a.") -> 0.30041053 | V10: =IFERROR(IF(C10=0,0,IF(D10="EV",IF('Replacement plan'!$E$7="",INDEX(Products!$D$7:$D$13,MATCH('Replacement plan'!$B$7,Products!$A$7:$A$13,0)),'Replacement plan'!$E$7),0)),"n.a.") -> 86.55 | W10: =IF(C10=0,0,IF(AND(P10="Complete",D10="EV",E10<120),IF(T10=0,0,ROUNDUP(T10*(R10-'Operating costs'!$B$41)*(S10*U10+'Operating costs'!$B$48/(1-'Operating costs'!$B$44))/(V10*'Operating costs'!$B$47/(1-'Operating costs'!$B$44)-T10*'Operating costs'!$B$12*U10),0)),0)) -> 48 | X10: =IF(C10=0,0,IF(AND(P10="Complete",D10="EV",E10<120),(R10-'Operating costs'!$B$41)*(S10*U10+'Operating costs'!$B$48/(1-'Operating costs'!$B$44))+W10*'Operating costs'!$B$12*U10,0)) -> 13633.831 | Y10: =IF(AND(C10=1,D10="EV",E10<120),AI10/(1-'Operating costs'!$B$44)*(1-T10),0) -> 41.576817 | Z10: =IF(AND(C10=1,D10="EV",E10<120,T10<1,AG10>0),Y10/AG10,0) -> 1.8898553 | AA10: =IF(C10=0,0,IF(P10="Complete",((S10*(R10-'Operating costs'!$B$40))+ROUNDUP(S10*(R10-'Operating costs'!$B$40)*IF('Replacement plan'!$AH$7="",'Operating costs'!$B$7,'Replacement plan'!$AH$7)/('Operating costs'!$B$8-'Operating costs'!$B$9*IF('Replacement plan'!$AH$7="",'Operating costs'!$B$7,'Replacement plan'!$AH$7)),0)*'Operating costs'!$B$9)*IF('Replacement plan'!$AH$7="",'Operating costs'!$B$7,'Replacement plan'!$AH$7),"n.a.")) -> 4522.8 | AB10: =IF(D10="EV",(120-E10)/12,0) -> 10 | AC10: =IF(AND(C10=1,D10="EV",E10<120,T10>0),'Operating costs'!$B$12/'Operating costs'!$B$11*60+'Operating costs'!$B$13+'Operating costs'!$B$14+V10*'Operating costs'!$B$47/(1-'Operating costs'!$B$44)/'Replacement plan'!$L$7*60,0) -> 111.325 | AD10: ='Replacement plan'!$B$7 -> ChengLong L2EV | AE10: =IF(C10=0,0,VLOOKUP($A10,'Fleet register'!$A$7:$S$106,8,FALSE)) -> 1200 | AF10: =IF('Replacement plan'!$H$7="","n.a.",'Replacement plan'!$H$7) -> n.a. | AG10: ='Replacement plan'!$J$7 -> 22 | AH10: =IFERROR(IF(D10="EV",IF('Replacement plan'!$K$7="AC",IF(ISNUMBER(INDEX(Products!$G$7:$G$13,MATCH('Replacement plan'!$B$7,Products!$A$7:$A$13,0))),INDEX(Products!$G$7:$G$13,MATCH('Replacement plan'!$B$7,Products!$A$7:$A$13,0)),"n.a."),IF(ISNUMBER(INDEX(Products!$H$7:$H$13,MATCH('Replacement plan'!$B$7,Products!$A$7:$A$13,0))),INDEX(Products!$H$7:$H$13,MATCH('Replacement plan'!$B$7,Products!$A$7:$A$13,0)),"n.a.")),0),"n.a.") -> 120 | AI10: =IF(AND(C10=1,D10="EV",E10<120),(VLOOKUP($A10,'Fleet register'!$A$7:$S$106,7,FALSE)+IF(T10>0,'Operating costs'!$B$12,0))*U10*(1-'Operating costs'!$B$44)+'Operating costs'!$B$49,0) -> 46.773919 | AJ10: =IF(D10="EV",'Energy and charging'!$C$50,0) -> 44 | AK10: =EDATE('Operating costs'!$B$63,E10) -> 46298 | AL10: =IFERROR(IF(D10="EV",INDEX(Products!$B$7:$B$13,MATCH('Replacement plan'!$B$7,Products!$A$7:$A$13,0)),0),"n.a.") -> 5000 | AM10: ='Replacement plan'!$K$7 -> DC | AN10: ='Replacement plan'!$AE$7 -> Assumed | AO10: =IF(AND(C10=1,D10="EV",E10<120),(R10-'Operating costs'!$B$41)*S10+W10*'Operating costs'!$B$12,0) -> 45384 | AP10: =IF(AND(C10=1,D10="EV",E10<120),IF('Operating costs'!$B$68="Hong Seh 200k average",AO10*IFERROR(INDEX(Products!$P$7:$P$13,MATCH(AD10,Products!$A$7:$A$13,0)),"n.a."),'Operating costs'!$B$26),0) -> 745.4322 | AQ10: =IF(D10="EV",'Operating costs'!$B$68,"Not applicable") -> Hong Seh 200k average
A11: ='Replacement plan'!A8 -> T002 | B11: 0 | C11: =IF(COUNTIFS('Fleet register'!$A$7:$A$106,$A11)=1,VLOOKUP($A11,'Fleet register'!$A$7:$S$106,2,FALSE),0) -> 1 | D11: =IF("Keep ICE"="EV","EV","ICE") -> ICE | E11: =IF(C11=0,0,IF('Replacement plan'!$M$8="",VLOOKUP($A11,'Fleet register'!$A$7:$S$106,10,FALSE),'Replacement plan'!$M$8)) -> 24 | F11: =IF(C11=0,0,VLOOKUP($A11,'Fleet register'!$A$7:$S$106,11,FALSE)) -> 30000 | G11: =IFERROR(IF(C11=0,0,IF(E11=120,0,IF(D11="ICE",'Replacement plan'!$C$8,IF('Replacement plan'!$D$8="",INDEX(Products!$I$7:$I$13,MATCH('Replacement plan'!$B$8,Products!$A$7:$A$13,0))+'Operating costs'!$B$57,'Replacement plan'!$D$8))*(1+'Operating costs'!$B$50)^(E11/12))),"n.a.") -> 181000 | H11: =IFERROR(IF(C11=0,0,IF(E11=0,F11,VLOOKUP($A11,'Fleet register'!$A$7:$S$106,12,FALSE)+VLOOKUP($A11,'Fleet register'!$A$7:$S$106,13,FALSE)*MAX(0,VLOOKUP($A11,'Fleet register'!$A$7:$S$106,10,FALSE)-E11)/VLOOKUP($A11,'Fleet register'!$A$7:$S$106,14,FALSE))),"n.a.") -> 10000 | I11: =IF(C11=0,0,IF(E11=120,0,'Replacement plan'!$N$8)) -> 30600 | J11: =IF(C11=0,0,IF(P11="Complete",((S11*(R11-'Operating costs'!$B$39))+ROUNDUP(S11*(R11-'Operating costs'!$B$39)*IF('Replacement plan'!$AG$8="",'Operating costs'!$B$7,'Replacement plan'!$AG$8)/('Operating costs'!$B$8-'Operating costs'!$B$9*IF('Replacement plan'!$AG$8="",'Operating costs'!$B$7,'Replacement plan'!$AG$8)),0)*'Operating costs'!$B$9)*IF('Replacement plan'!$AG$8="",'Operating costs'!$B$7,'Replacement plan'!$AG$8)*('Energy and charging'!$B$9*'Energy and charging'!$B$7+(1-'Energy and charging'!$B$9)*'Energy and charging'!$B$8)*'Operating costs'!$B$23,"n.a.")) -> 9045.6 | K11: =IF(C11=0,0,IF(P11="Complete",SUM('Operating costs'!$B$24,'Operating costs'!$B$27,'Operating costs'!$B$29,'Operating costs'!$B$31,'Operating costs'!$B$33,'Operating costs'!$B$34,'Operating costs'!$B$37,'Replacement plan'!$W$8)+'Operating costs'!$B$39*'Operating costs'!$B$42+ROUNDUP(S11*(R11-'Operating costs'!$B$39)*IF('Replacement plan'!$AG$8="",'Operating costs'!$B$7,'Replacement plan'!$AG$8)/('Operating costs'!$B$8-'Operating costs'!$B$9*IF('Replacement plan'!$AG$8="",'Operating costs'!$B$7,'Replacement plan'!$AG$8)),0)*('Operating costs'!$B$9/'Operating costs'!$B$11+'Operating costs'!$B$10/60)*'Operating costs'!$B$19*'Operating costs'!$B$21,"n.a.")) -> 9105.75 | L11: =IF(C11=0,0,IF(P11="Complete",IF(D11="EV",X11*((1-T11)*'Energy and charging'!$B$10+T11*'Energy and charging'!$B$11)*'Operating costs'!$B$22,AA11*('Energy and charging'!$B$9*'Energy and charging'!$B$7+(1-'Energy and charging'!$B$9)*'Energy and charging'!$B$8)*'Operating costs'!$B$23),"n.a.")) -> 9045.6 | M11: =IF(C11=0,0,IF(P11="Complete",IF(D11="ICE",SUM('Operating costs'!$B$25,'Operating costs'!$B$27,'Operating costs'!$B$29,'Operating costs'!$B$31,'Operating costs'!$B$33,'Operating costs'!$B$35,'Operating costs'!$B$37,'Replacement plan'!$X$8)+'Operating costs'!$B$40*'Operating costs'!$B$42+ROUNDUP(S11*(R11-'Operating costs'!$B$40)*IF('Replacement plan'!$AH$8="",'Operating costs'!$B$7,'Replacement plan'!$AH$8)/('Operating costs'!$B$8-'Operating costs'!$B$9*IF('Replacement plan'!$AH$8="",'Operating costs'!$B$7,'Replacement plan'!$AH$8)),0)*('Operating costs'!$B$9/'Operating costs'!$B$11+'Operating costs'!$B$10/60)*'Operating costs'!$B$19*'Operating costs'!$B$21,SUM(AP11,'Operating costs'!$B$28,'Operating costs'!$B$30,'Operating costs'!$B$32,'Operating costs'!$B$33,'Operating costs'!$B$36,'Operating costs'!$B$38,'Replacement plan'!$Y$8)+'Operating costs'!$B$41*'Operating costs'!$B$43+W11*'Operating costs'!$B$15+(T11*X11/'Replacement plan'!$L$8+W11*('Operating costs'!$B$12/'Operating costs'!$B$11+('Operating costs'!$B$13+'Operating costs'!$B$14)/60)+(R11-'Operating costs'!$B$41)*(IF(T11<1,'Operating costs'!$B$16,0)+'Operating costs'!$B$17)/60)*'Operating costs'!$B$19*'Operating costs'!$B$20),"n.a.")) -> 9105.75 | N11: =IF(AND(C11=1,D11="EV",E11<120,E11+'Replacement plan'!$AA$8<=120),'Replacement plan'!$Z$8,0) -> 0 | O11: =E11+'Replacement plan'!$AA$8 -> 24 | P11: =IFERROR(IF(C11=0,"Excluded",IF(OR(COUNTIFS('Fleet register'!$A$7:$A$106,A11)<>1,COUNTIFS('Replacement plan'!$A$7:$A$106,A11)<>1),"Duplicate/missing ID",IF(NOT(AND(ISNUMBER(VLOOKUP($A11,'Fleet register'!$A$7:$S$106,5,FALSE)),ISNUMBER(VLOOKUP($A11,'Fleet register'!$A$7:$S$106,6,FALSE)),ISNUMBER(VLOOKUP($A11,'Fleet register'!$A$7:$S$106,10,FALSE)),ISNUMBER(VLOOKUP($A11,'Fleet register'!$A$7:$S$106,11,FALSE)),ISNUMBER(VLOOKUP($A11,'Fleet register'!$A$7:$S$106,12,FALSE)),ISNUMBER(VLOOKUP($A11,'Fleet register'!$A$7:$S$106,13,FALSE)),ISNUMBER(VLOOKUP($A11,'Fleet register'!$A$7:$S$106,14,FALSE)),VLOOKUP($A11,'Fleet register'!$A$7:$S$106,14,FALSE)>0,ISNUMBER('Replacement plan'!$C$8),OR(E11=120,ISNUMBER('Replacement plan'!$N$8)),ISNUMBER(E11))),"Missing vehicle input",IF(OR(E11<0,E11>VLOOKUP($A11,'Fleet register'!$A$7:$S$106,10,FALSE),E11>120,E11<>INT(E11),VLOOKUP($A11,'Fleet register'!$A$7:$S$106,6,FALSE)<=0,VLOOKUP($A11,'Fleet register'!$A$7:$S$106,6,FALSE)>366,VLOOKUP($A11,'Fleet register'!$A$7:$S$106,5,FALSE)<0,VLOOKUP($A11,'Fleet register'!$A$7:$S$106,11,FALSE)<0,I11<0,'Operating costs'!$B$8<='Operating costs'!$B$7*'Operating costs'!$B$9,'Operating costs'!$B$11<=0,'Operating costs'!$B$39>R11,'Operating costs'!$B$40>R11,'Operating costs'!$B$41>R11,NOT(OR("Keep ICE"="Keep ICE","Keep ICE"="New ICE","Keep ICE"="EV"))),"Invalid vehicle input",IF(AND(D11="EV",E11<120,OR(NOT(ISNUMBER(U11)),NOT(ISNUMBER(V11)),V11<=0,T11<0,T11>1,'Replacement plan'!$L$8<=0,'Operating costs'!$B$44<0,'Operating costs'!$B$44>=1,'Operating costs'!$B$47<=0,'Operating costs'!$B$47>1,V11*'Operating costs'!$B$47/(1-'Operating costs'!$B$44)<=T11*'Operating costs'!$B$12*U11,AND('Replacement plan'!$Z$8>0,OR('Replacement plan'!$AB$8<>"Yes",'Operating costs'!$B$62<>"Gross")))),"Invalid EV input",IF(AND(ISNUMBER('Operating costs'!$B$7),ISNUMBER('Operating costs'!$B$8),ISNUMBER('Operating costs'!$B$9),ISNUMBER('Operating costs'!$B$10),ISNUMBER('Operating costs'!$B$11),ISNUMBER('Operating costs'!$B$19),ISNUMBER('Operating costs'!$B$21),ISNUMBER('Operating costs'!$B$23),ISNUMBER('Operating costs'!$B$24),ISNUMBER('Operating costs'!$B$25),ISNUMBER('Operating costs'!$B$27),ISNUMBER('Operating costs'!$B$29),ISNUMBER('Operating costs'!$B$31),ISNUMBER('Operating costs'!$B$33),ISNUMBER('Operating costs'!$B$34),ISNUMBER('Operating costs'!$B$35),ISNUMBER('Operating costs'!$B$37),ISNUMBER('Operating costs'!$B$39),ISNUMBER('Operating costs'!$B$40),ISNUMBER('Operating costs'!$B$42),ISNUMBER('Operating costs'!$B$50),ISNUMBER('Operating costs'!$B$51),ISNUMBER('Operating costs'!$B$53),ISNUMBER('Operating costs'!$B$54),ISNUMBER('Operating costs'!$B$66),ISNUMBER('Operating costs'!$B$67),AND(ISNUMBER('Energy and charging'!$B$9),'Energy and charging'!$B$9>=0,'Energy and charging'!$B$9<=1,OR('Energy and charging'!$B$9=0,AND(ISNUMBER('Energy and charging'!$B$7),'Energy and charging'!$B$7>=0)),OR('Energy and charging'!$B$9=1,AND(ISNUMBER('Energy and charging'!$B$8),'Energy and charging'!$B$8>=0))),ISNUMBER(VLOOKUP($A11,'Fleet register'!$A$7:$S$106,15,FALSE)),ISNUMBER(VLOOKUP($A11,'Fleet register'!$A$7:$S$106,16,FALSE)),ISNUMBER('Replacement plan'!$W$8),ISNUMBER('Replacement plan'!$X$8),OR(E11=120,AND(ISNUMBER(G11),G11>=0)),ISNUMBER(H11),H11>=0,OR(D11<>"EV",E11=120,AND(ISNUMBER('Operating costs'!$B$12),ISNUMBER('Operating costs'!$B$13),ISNUMBER('Operating costs'!$B$14),ISNUMBER('Operating costs'!$B$15),ISNUMBER('Operating costs'!$B$16),ISNUMBER('Operating costs'!$B$17),ISNUMBER('Operating costs'!$B$18),ISNUMBER('Operating costs'!$B$20),ISNUMBER('Operating costs'!$B$22),OR(AND('Operating costs'!$B$68="Annual override",ISNUMBER('Operating costs'!$B$26)),AND('Operating costs'!$B$68="Hong Seh 200k average",ISNUMBER(IFERROR(INDEX(Products!$P$7:$P$13,MATCH(AD11,Products!$A$7:$A$13,0)),"")))),ISNUMBER('Operating costs'!$B$28),ISNUMBER('Operating costs'!$B$30),ISNUMBER('Operating costs'!$B$32),ISNUMBER('Operating costs'!$B$36),ISNUMBER('Operating costs'!$B$38),ISNUMBER('Operating costs'!$B$41),ISNUMBER('Operating costs'!$B$43),ISNUMBER('Operating costs'!$B$44),ISNUMBER('Operating costs'!$B$45),ISNUMBER('Operating costs'!$B$46),ISNUMBER('Operating costs'!$B$47),ISNUMBER('Operating costs'!$B$48),ISNUMBER('Operating costs'!$B$49),ISNUMBER('Operating costs'!$B$52),ISNUMBER('Operating costs'!$B$64),ISNUMBER('Operating costs'!$B$65),ISNUMBER('Energy and charging'!$B$12),AND(ISNUMBER(1-'Energy and charging'!$B$12),1-'Energy and charging'!$B$12>=0,1-'Energy and charging'!$B$12<=1,OR(1-'Energy and charging'!$B$12=0,AND(ISNUMBER('Energy and charging'!$B$10),'Energy and charging'!$B$10>=0)),OR(1-'Energy and charging'!$B$12=1,AND(ISNUMBER('Energy and charging'!$B$11),'Energy and charging'!$B$11>=0))),ISNUMBER('Replacement plan'!$Y$8),ISNUMBER('Replacement plan'!$Z$8),'Replacement plan'!$Z$8>=0,ISNUMBER('Replacement plan'!$AA$8),'Replacement plan'!$AA$8>=0,'Replacement plan'!$AA$8=INT('Replacement plan'!$AA$8),ISNUMBER('Replacement plan'!$L$8))),'Operating costs'!$B$7>=0,'Operating costs'!$B$21>=0,'Operating costs'!$B$21<=1,'Operating costs'!$B$23>=0,'Operating costs'!$B$23<=1,'Operating costs'!$B$50>-1,'Operating costs'!$B$51>-1,'Operating costs'!$B$53>-1,'Operating costs'!$B$54>-1),IF(AND(ISNUMBER(IF('Replacement plan'!$AG$8="",'Operating costs'!$B$7,'Replacement plan'!$AG$8)),IF('Replacement plan'!$AG$8="",'Operating costs'!$B$7,'Replacement plan'!$AG$8)>=0,ISNUMBER(IF('Replacement plan'!$AH$8="",'Operating costs'!$B$7,'Replacement plan'!$AH$8)),IF('Replacement plan'!$AH$8="",'Operating costs'!$B$7,'Replacement plan'!$AH$8)>=0,'Operating costs'!$B$8>MAX(IF('Replacement plan'!$AG$8="",'Operating costs'!$B$7,'Replacement plan'!$AG$8),IF('Replacement plan'!$AH$8="",'Operating costs'!$B$7,'Replacement plan'!$AH$8))*'Operating costs'!$B$9),IF(AND(VLOOKUP($A11,'Fleet register'!$A$7:$S$106,10,FALSE)>=0,VLOOKUP($A11,'Fleet register'!$A$7:$S$106,10,FALSE)<=120,VLOOKUP($A11,'Fleet register'!$A$7:$S$106,10,FALSE)=INT(VLOOKUP($A11,'Fleet register'!$A$7:$S$106,10,FALSE)),VLOOKUP($A11,'Fleet register'!$A$7:$S$106,15,FALSE)>=0,VLOOKUP($A11,'Fleet register'!$A$7:$S$106,16,FALSE)>=0,MIN('Operating costs'!$B$7,'Operating costs'!$B$8,'Operating costs'!$B$9,'Operating costs'!$B$10,'Operating costs'!$B$11,'Operating costs'!$B$19,'Operating costs'!$B$21,'Operating costs'!$B$23,'Operating costs'!$B$24,'Operating costs'!$B$25,'Operating costs'!$B$27,'Operating costs'!$B$29,'Operating costs'!$B$31,'Operating costs'!$B$33,'Operating costs'!$B$34,'Operating costs'!$B$35,'Operating costs'!$B$37,'Operating costs'!$B$39,'Operating costs'!$B$40,'Operating costs'!$B$42,'Operating costs'!$B$66,'Operating costs'!$B$67)>=0,OR(D11<>"EV",E11=120,AND(MIN('Operating costs'!$B$12,'Operating costs'!$B$13,'Operating costs'!$B$14,'Operating costs'!$B$15,'Operating costs'!$B$16,'Operating costs'!$B$17,'Operating costs'!$B$18,'Operating costs'!$B$20,'Operating costs'!$B$22,'Operating costs'!$B$26,'Operating costs'!$B$28,'Operating costs'!$B$30,'Operating costs'!$B$32,'Operating costs'!$B$36,'Operating costs'!$B$38,'Operating costs'!$B$41,'Operating costs'!$B$43,'Operating costs'!$B$44,'Operating costs'!$B$45,'Operating costs'!$B$46,'Operating costs'!$B$47,'Operating costs'!$B$48,'Operating costs'!$B$49,'Operating costs'!$B$64,'Operating costs'!$B$65)>=0,'Operating costs'!$B$20<=1,'Operating costs'!$B$22<=1,'Operating costs'!$B$45<1,'Operating costs'!$B$46<1,'Operating costs'!$B$52>-1))),"Complete","Invalid operating limits"),"Invalid fuel override"),"Missing/invalid operating input")))))),"Invalid input type") -> Complete | Q11: =IF(C11=0,"Excluded",IF(P11<>"Complete",P11,IF(OR('Replacement plan'!$AD$8<120-E11,AND(D11="EV",E11<120,OR('Replacement plan'!$AC$8<120-E11,'Replacement plan'!$I$8="No",AND(ISNUMBER(AF11),AE11>AF11),AI11>V11*(1-'Operating costs'!$B$46)^MAX(0,AB11-1)*(1-'Operating costs'!$B$45),AC11>'Operating costs'!$B$18,AND(T11<1,OR(AG11<=0,AND(ISNUMBER(AH11),AG11>AH11))),'Replacement plan'!$L$8>INDEX(Products!$H$7:$H$13,MATCH('Replacement plan'!$B$8,Products!$A$7:$A$13,0))))),"Fails entered limits",IF(AND(D11="EV",E11<120,OR(NOT(ISNUMBER(VLOOKUP($A11,'Fleet register'!$A$7:$S$106,7,FALSE))),NOT(ISNUMBER(VLOOKUP($A11,'Fleet register'!$A$7:$S$106,8,FALSE))),NOT(ISNUMBER(AF11)),'Replacement plan'!$I$8<>"Yes",NOT(ISNUMBER(AH11)),'Operating costs'!$B$59<>"Yes",'Operating costs'!$B$58<>"Yes")),"Unverified","Within entered limits")))) -> Within entered limits | R11: =IF(C11=0,0,VLOOKUP($A11,'Fleet register'!$A$7:$S$106,6,FALSE)) -> 300 | S11: =IF(C11=0,0,VLOOKUP($A11,'Fleet register'!$A$7:$S$106,5,FALSE)) -> 150 | T11: =IF(D11="EV",'Energy and charging'!$B$12,0) -> 0 | U11: =IFERROR(IF(C11=0,0,IF(D11="EV",IF('Replacement plan'!$F$8="",INDEX(Products!$E$7:$E$13,MATCH('Replacement plan'!$B$8,Products!$A$7:$A$13,0)),'Replacement plan'!$F$8)/IF('Replacement plan'!$G$8="Battery",1-'Operating costs'!$B$44,1),0)),"n.a.") -> 0 | V11: =IFERROR(IF(C11=0,0,IF(D11="EV",IF('Replacement plan'!$E$8="",INDEX(Products!$D$7:$D$13,MATCH('Replacement plan'!$B$8,Products!$A$7:$A$13,0)),'Replacement plan'!$E$8),0)),"n.a.") -> 0 | W11: =IF(C11=0,0,IF(AND(P11="Complete",D11="EV",E11<120),IF(T11=0,0,ROUNDUP(T11*(R11-'Operating costs'!$B$41)*(S11*U11+'Operating costs'!$B$48/(1-'Operating costs'!$B$44))/(V11*'Operating costs'!$B$47/(1-'Operating costs'!$B$44)-T11*'Operating costs'!$B$12*U11),0)),0)) -> 0 | X11: =IF(C11=0,0,IF(AND(P11="Complete",D11="EV",E11<120),(R11-'Operating costs'!$B$41)*(S11*U11+'Operating costs'!$B$48/(1-'Operating costs'!$B$44))+W11*'Operating costs'!$B$12*U11,0)) -> 0 | Y11: =IF(AND(C11=1,D11="EV",E11<120),AI11/(1-'Operating costs'!$B$44)*(1-T11),0) -> 0 | Z11: =IF(AND(C11=1,D11="EV",E11<120,T11<1,AG11>0),Y11/AG11,0) -> 0 | AA11: =IF(C11=0,0,IF(P11="Complete",((S11*(R11-'Operating costs'!$B$40))+ROUNDUP(S11*(R11-'Operating costs'!$B$40)*IF('Replacement plan'!$AH$8="",'Operating costs'!$B$7,'Replacement plan'!$AH$8)/('Operating costs'!$B$8-'Operating costs'!$B$9*IF('Replacement plan'!$AH$8="",'Operating costs'!$B$7,'Replacement plan'!$AH$8)),0)*'Operating costs'!$B$9)*IF('Replacement plan'!$AH$8="",'Operating costs'!$B$7,'Replacement plan'!$AH$8),"n.a.")) -> 4522.8 | AB11: =IF(D11="EV",(120-E11)/12,0) -> 0 | AC11: =IF(AND(C11=1,D11="EV",E11<120,T11>0),'Operating costs'!$B$12/'Operating costs'!$B$11*60+'Operating costs'!$B$13+'Operating costs'!$B$14+V11*'Operating costs'!$B$47/(1-'Operating costs'!$B$44)/'Replacement plan'!$L$8*60,0) -> 0 | AD11: ='Replacement plan'!$B$8 -> ChengLong L2EV | AE11: =IF(C11=0,0,VLOOKUP($A11,'Fleet register'!$A$7:$S$106,8,FALSE)) -> 1200 | AF11: =IF('Replacement plan'!$H$8="","n.a.",'Replacement plan'!$H$8) -> n.a. | AG11: ='Replacement plan'!$J$8 -> 22 | AH11: =IFERROR(IF(D11="EV",IF('Replacement plan'!$K$8="AC",IF(ISNUMBER(INDEX(Products!$G$7:$G$13,MATCH('Replacement plan'!$B$8,Products!$A$7:$A$13,0))),INDEX(Products!$G$7:$G$13,MATCH('Replacement plan'!$B$8,Products!$A$7:$A$13,0)),"n.a."),IF(ISNUMBER(INDEX(Products!$H$7:$H$13,MATCH('Replacement plan'!$B$8,Products!$A$7:$A$13,0))),INDEX(Products!$H$7:$H$13,MATCH('Replacement plan'!$B$8,Products!$A$7:$A$13,0)),"n.a.")),0),"n.a.") -> 0 | AI11: =IF(AND(C11=1,D11="EV",E11<120),(VLOOKUP($A11,'Fleet register'!$A$7:$S$106,7,FALSE)+IF(T11>0,'Operating costs'!$B$12,0))*U11*(1-'Operating costs'!$B$44)+'Operating costs'!$B$49,0) -> 0 | AJ11: =IF(D11="EV",'Energy and charging'!$B$50,0) -> 0 | AK11: =EDATE('Operating costs'!$B$63,E11) -> 47029 | AL11: =IFERROR(IF(D11="EV",INDEX(Products!$B$7:$B$13,MATCH('Replacement plan'!$B$8,Products!$A$7:$A$13,0)),0),"n.a.") -> 0 | AM11: ='Replacement plan'!$K$8 -> DC | AN11: ='Replacement plan'!$AE$8 -> Assumed | AO11: =IF(AND(C11=1,D11="EV",E11<120),(R11-'Operating costs'!$B$41)*S11+W11*'Operating costs'!$B$12,0) -> 0 | AP11: =IF(AND(C11=1,D11="EV",E11<120),IF('Operating costs'!$B$68="Hong Seh 200k average",AO11*IFERROR(INDEX(Products!$P$7:$P$13,MATCH(AD11,Products!$A$7:$A$13,0)),"n.a."),'Operating costs'!$B$26),0) -> 0 | AQ11: =IF(D11="EV",'Operating costs'!$B$68,"Not applicable") -> Not applicable
